Workbook
Name Slicer_Period: #N/A
Name Slicer_Segment: #N/A

Sheet 01_Cover
A1: ROYAL BANK OF CANADA — BANKING FINANCIAL ANALYSIS
A4: Financial Performance, Credit Risk and Capital Adequacy Analysis
A6: Company | B6: Royal Bank of Canada
A7: Ticker | B7: RY
A8: Industry | B8: Banking and Financial Services
A9: Reporting Period | B9: FY2023–FY2025 and Q1 2024–Q2 2026
A10: Reporting Currency | B10: Canadian dollars
A11: Reporting Unit | B11: CAD millions unless otherwise stated
A12: Reporting Framework | B12: IFRS
A13: Prepared By | B13: Neha R K
A14: Project Type | B14: Independent Finance and Accounting Portfolio Project
A15: Project Status | B15: Completed
A16: Data Cutoff | B16: April 30, 2026
A18: Purpose
A19: Evaluate RBC’s profitability, operating efficiency, credit quality, business-segment performance, regulatory capital and liquidity using publicly available annual and quarterly disclosures.
A24: Disclaimer
A25: This independent educational portfolio project is based solely on publicly available information published by Royal Bank of Canada. It is not affiliated with, sponsored by, or endorsed by RBC and does not constitute investment, accounting, tax, legal, or financial advice.
A31: ADVANCED EXCEL REVIEW
A32: Review Sheet 22 for XLOOKUP, LET, IFS, FILTER, SORTBY, RANK.EQ and sparklines. Review Sheet 23 for the normalized Excel Table used as a PivotTable source. Review Sheet 24 for the interactive SUMIFS-driven pivot-style management summary.

Sheet 02_Project_Charter
A1: PROJECT CHARTER
A4: Project Overview
A5: Field | B5: Content
A6: Project Title | B6: Royal Bank of Canada Financial Performance, Credit Risk and Capital Adequacy Analysis
A7: Company | B7: Royal Bank of Canada
A8: Industry | B8: Banking and Financial Services
A9: Project Type | B9: Independent Finance and Accounting Portfolio Project
A10: Analysis Period | B10: FY2023–FY2025 and Q1 2024–Q2 2026
A11: Reporting Currency | B11: Canadian dollars
A12: Reporting Unit | B12: CAD millions unless otherwise stated
A13: Primary Tool | B13: Microsoft Excel
A14: Project Status | B14: Completed
A15: Prepared By | B15: Neha R K
A16: Data Cutoff | B16: April 30, 2026
A18: Project Objective
A19: The objective of this project is to evaluate Royal Bank of Canada’s financial performance, operating efficiency, credit-risk profile, business-segment performance and regulatory capital position using publicly available annual and quarterly disclosures. The project converts complex banking information into a structured Excel model, analytical dashboard and professional financial report.
A24: Business Questions
A25: 1 | B25: Is RBC generating sustainable revenue and earnings growth?
A26: 2 | B26: How are net interest income and non-interest income changing?
A27: 3 | B27: Are operating expenses growing faster or slower than revenue?
A28: 4 | B28: How has return on equity changed?
A29: 5 | B29: Is credit quality strengthening or deteriorating?
A30: 6 | B30: How have provisions for credit losses and impaired loans changed?
A31: 7 | B31: Does RBC maintain strong regulatory capital and liquidity?
A32: 8 | B32: Which business segments contribute most to revenue and net income?
A33: 9 | B33: What strengths and risks are visible in the latest results?
A35: Intended Audience | E35: Project Deliverables
A36: Junior Financial Analyst | E36: Excel financial-analysis model
A37: Financial Reporting Analyst | E37: Banking KPI and ratio analysis
A38: Accounting Analyst | E38: Credit-risk analysis
A39: Banking Analyst | E39: Capital and liquidity analysis
A40: Credit Analyst | E40: Segment-performance analysis
A41: Risk Analyst | E41: Executive dashboard
A42: Finance Operations | E42: Professional financial report
A43: New-Graduate Finance Programs | E43: Methodology and source documentation
A45: ADVANCED EXCEL CAPABILITIES DEMONSTRATED
A46: Feature | B46: Portfolio Evidence
A47: Excel Tables | B47: RBC_Annual_Performance, RBC_Quarterly_Performance, RBC_Segment_Results and RBC_Pivot_Source
A48: XLOOKUP | B48: Interactive KPI retrieval by selected period and metric
A49: LET and IFS | B49: Readable period-comparison logic and metric-aware performance assessment
A50: FILTER and SORTBY | B50: Dynamic segment ranking that recalculates from dropdown selections
A51: SUMIFS and RANK.EQ | B51: Pivot-style segment matrix, totals and rankings
A52: Data Validation, Conditional Formatting and Sparklines | B52: Interactive controls, heat maps, data bars and compact trend visualization

Sheet 03_Source_Register
A1: SOURCE REGISTER
A4: Source ID | B4: File Name | C4: Reporting Period | D4: Document Type | E4: Main Information Used | F4: Format | G4: Status | H4: Page / Table | I4: Source URL | J4: Notes
A5: AR-25 | B5: RBC_2025_Annual_Report.pdf | C5: FY2025 | D5: Audited Annual Report | E5: Annual statements, notes, MD&A and accounting policies | F5: PDF | G5: Validated | I5: https://www.rbc.com/investor-relations/financial-information.html | J5: Used in completed model; detailed source mapping is included in raw-data schedules
A6: SUP-25Q4-PDF | B6: RBC_Q4_2025_Financial_Supplement.pdf | C6: Q4/FY2025 | D6: Financial Supplement | E6: Annual and quarterly financial schedules | F6: PDF | G6: Validated | I6: https://www.rbc.com/investor-relations/financial-information.html | J6: Used in completed model; detailed source mapping is included in raw-data schedules
A7: SUP-25Q4-XLS | B7: RBC_Q4_2025_Financial_Supplement.xlsx | C7: Q4/FY2025 | D7: Financial Supplement | E7: Extractable annual and quarterly data | F7: Excel | G7: Validated | I7: https://www.rbc.com/investor-relations/financial-information.html | J7: Used in completed model; detailed source mapping is included in raw-data schedules
A8: QR-26Q2 | B8: RBC_Q2_2026_Report_to_Shareholders.pdf | C8: Q2 2026 | D8: Interim Report | E8: Latest results, MD&A and statements | F8: PDF | G8: Validated | I8: https://www.rbc.com/investor-relations/financial-information.html | J8: Used in completed model; detailed source mapping is included in raw-data schedules
A9: SUP-26Q2-PDF | B9: RBC_Q2_2026_Financial_Supplement.pdf | C9: Q2 2026 | D9: Financial Supplement | E9: Quarterly trends, segments, credit and capital | F9: PDF | G9: Validated | I9: https://www.rbc.com/investor-relations/financial-information.html | J9: Used in completed model; detailed source mapping is included in raw-data schedules
A10: SUP-26Q2-XLS | B10: RBC_Q2_2026_Financial_Supplement.xlsx | C10: Q2 2026 | D10: Financial Supplement | E10: Extractable quarterly data | F10: Excel | G10: Validated | I10: https://www.rbc.com/investor-relations/financial-information.html | J10: Used in completed model; detailed source mapping is included in raw-data schedules
A11: P3-26Q2-PDF | B11: RBC_Q2_2026_Pillar_3_Disclosure.pdf | C11: Q2 2026 | D11: Regulatory Disclosure | E11: Capital, RWA and risk exposure | F11: PDF | G11: Validated | I11: https://www.rbc.com/investor-relations/financial-information.html | J11: Used in completed model; detailed source mapping is included in raw-data schedules
A12: P3-26Q2-XLS | B12: RBC_Q2_2026_Pillar_3_Quantitative_Tables.xlsx | C12: Q2 2026 | D12: Regulatory Tables | E12: Capital and regulatory-risk data | F12: Excel | G12: Validated | I12: https://www.rbc.com/investor-relations/financial-information.html | J12: Used in completed model; detailed source mapping is included in raw-data schedules
A13: PR-26Q2 | B13: RBC_Q2_2026_Earnings_Release.pdf | C13: Q2 2026 | D13: Earnings Release | E13: Executive financial highlights | F13: PDF | G13: Validated | I13: https://www.rbc.com/investor-relations/financial-information.html | J13: Used in completed model; detailed source mapping is included in raw-data schedules

Sheet 04_Definitions
A1: BANKING DEFINITIONS
A4: Term | B4: Abbreviation | C4: Working Definition | D4: Why It Matters | E4: Primary Source
A5: Net Interest Income | B5: NII | C5: Interest income earned less interest expense | D5: Core banking revenue and sensitivity to rates, loan growth and funding costs | E5: RBC Annual / Quarterly Reports
A6: Non-Interest Income | B6: — | C6: Revenue from fees, trading, insurance and other non-interest activities | D6: Shows diversification beyond lending spreads | E6: RBC Financial Supplement
A7: Provision for Credit Losses | B7: PCL | C7: Expense recognized for expected credit losses | D7: Directly affects earnings and signals expected credit deterioration | E7: RBC Reports and Supplement
A8: Allowance for Credit Losses | B8: ACL | C8: Balance-sheet reserve against expected credit losses | D8: Indicates reserves available to absorb expected loan losses | E8: RBC Reports and Supplement
A9: Gross Impaired Loans | B9: GIL | C9: Loans identified as credit-impaired | D9: Measures the stock of problem loans | E9: RBC Financial Supplement
A10: Common Equity Tier 1 Ratio | B10: CET1 | C10: Highest-quality regulatory capital relative to risk-weighted assets | D10: Key measure of loss-absorbing capital strength | E10: RBC Pillar 3
A11: Risk-Weighted Assets | B11: RWA | C11: Assets weighted according to regulatory risk | D11: Denominator for regulatory capital ratios | E11: RBC Pillar 3
A12: Return on Equity | B12: ROE | C12: Net income available to common shareholders relative to common equity | D12: Measures profitability generated from shareholder capital | E12: RBC Financial Supplement
A13: Efficiency Ratio | B13: — | C13: Non-interest expense divided by total revenue | D13: Lower values generally indicate better operating efficiency | E13: RBC Financial Supplement
A14: Operating Leverage | B14: — | C14: Revenue growth minus expense growth | D14: Shows whether revenue is growing faster than costs | E14: RBC Reports
A15: Liquidity Coverage Ratio | B15: LCR | C15: High-quality liquid assets relative to projected short-term cash outflows | D15: Assesses short-term liquidity resilience | E15: RBC Pillar 3 / Liquidity Disclosure
... A20: Adjusted Results | B20: — | C20: Management-defined results excluding specified items | D20: Useful supplementary view but must not be mixed with reported figures | E20: RBC Reports

Sheet 05_Raw_Annual_Performance
A1: RAW ANNUAL PERFORMANCE
A4: Metric | B4: Unit | C4: FY2023 | D4: FY2024 | E4: FY2025 | F4: Source ID | G4: Page / Table | H4: Source URL | I4: Notes
A5: Net Interest Income | B5: CAD millions | C5: 25129 | D5: 27953 | E5: 33000 | F5: SUP-24Q4-XLS / SUP-25Q4-XLS | G5: Statements of Income – Page 5, annual columns | H5: https://www.rbc.com/investor-relations/financial-information.html | I5: Reported annual result; CAD millions
A6: Non-Interest Income | B6: CAD millions | C6: 26335 | D6: 29391 | E6: 33605 | F6: SUP-24Q4-XLS / SUP-25Q4-XLS | G6: Statements of Income – Page 5, annual columns | H6: https://www.rbc.com/investor-relations/financial-information.html | I6: Reported annual result; CAD millions
A7: Total Revenue | B7: CAD millions | C7: 51464 | D7: 57344 | E7: 66605 | F7: SUP-24Q4-XLS / SUP-25Q4-XLS | G7: Statements of Income – Page 5, annual columns | H7: https://www.rbc.com/investor-relations/financial-information.html | I7: Reported annual result; CAD millions
A8: Provision for Credit Losses | B8: CAD millions | C8: 2468 | D8: 3232 | E8: 4362 | F8: SUP-24Q4-XLS / SUP-25Q4-XLS | G8: Statements of Income – Page 5, annual columns | H8: https://www.rbc.com/investor-relations/financial-information.html | I8: Reported annual result; CAD millions
A9: Non-Interest Expense | B9: CAD millions | C9: 30813 | D9: 34250 | E9: 36592 | F9: SUP-24Q4-XLS / SUP-25Q4-XLS | G9: Statements of Income – Page 5, annual columns | H9: https://www.rbc.com/investor-relations/financial-information.html | I9: Reported annual result; CAD millions
A10: Income Before Income Taxes | B10: CAD millions | C10: 18183 | D10: 19862 | E10: 25651 | F10: SUP-24Q4-XLS / SUP-25Q4-XLS | G10: Statements of Income – Page 5, annual columns | H10: https://www.rbc.com/investor-relations/financial-information.html | I10: Reported annual result; CAD millions
A11: Income Taxes | B11: CAD millions | C11: 3571 | D11: 3622 | E11: 5282 | F11: SUP-24Q4-XLS / SUP-25Q4-XLS | G11: Statements of Income – Page 5, annual columns | H11: https://www.rbc.com/investor-relations/financial-information.html | I11: Reported annual result; CAD millions
A12: Net Income | B12: CAD millions | C12: 14612 | D12: 16240 | E12: 20369 | F12: SUP-24Q4-XLS / SUP-25Q4-XLS | G12: Statements of Income – Page 5, annual columns | H12: https://www.rbc.com/investor-relations/financial-information.html | I12: Reported annual result; CAD millions
A13: Net Income Available to Common Shareholders | B13: CAD millions | C13: 14369 | D13: 15908 | E13: 19868 | F13: SUP-24Q4-XLS / SUP-25Q4-XLS | G13: Statements of Income – Page 5, annual columns | H13: https://www.rbc.com/investor-relations/financial-information.html | I13: Reported annual result; CAD millions
A14: Diluted EPS | B14: CAD per share | C14: 10.32 | D14: 11.25 | E14: 14.07 | F14: SUP-24Q4-XLS / SUP-25Q4-XLS | G14: Financial Highlights – Page 2, annual columns | H14: https://www.rbc.com/investor-relations/financial-information.html | I14: Reported annual result; CAD per common share
A15: ROE | B15: % | C15: 0.143 | D15: 0.144 | E15: 0.163 | F15: SUP-24Q4-XLS / SUP-25Q4-XLS | G15: Financial Highlights – Page 2, annual columns | H15: https://www.rbc.com/investor-relations/financial-information.html | I15: RBC-reported ratio
A16: Efficiency Ratio | B16: % | C16: 0.599 | D16: 0.597 | E16: 0.549 | F16: SUP-24Q4-XLS / SUP-25Q4-XLS | G16: Financial Highlights – Page 2, annual columns | H16: https://www.rbc.com/investor-relations/financial-information.html | I16: RBC-reported ratio
... A19: Effective Tax Rate | B19: % | C19: 0.19639223 | D19: 0.18235827 | E19: 0.2059179 | F19: Model Calculation | G19: Calculated from Statements of Income | H19: https://www.rbc.com/investor-relations/financial-information.html | I19: Formula: Income taxes ÷ Income before tax

Sheet 06_Raw_Quarterly_Performance
A1: RAW QUARTERLY PERFORMANCE
A4: Metric | B4: Unit | C4: Q1 2024 | D4: Q2 2024 | E4: Q3 2024 | F4: Q4 2024 | G4: Q1 2025 | H4: Q2 2025 | I4: Q3 2025 | J4: Q4 2025 | K4: Q1 2026 | L4: Q2 2026 | M4: Source ID | N4: Page / Table | O4: Notes
A5: Net Interest Income | B5: CAD millions | C5: 6332 | D5: 6623 | E5: 7327 | F5: 7671 | G5: 7948 | H5: 8056 | I5: 8351 | J5: 8645 | K5: 8585 | L5: 8506 | M5: SUP-24Q4-XLS / SUP-25Q4-XLS / SUP-26Q2-XLS | N5: Financial Highlights Page 2 / Statements of Income Page 5 | O5: Single-quarter reported values; PPPT and tax rate are model calculations where applicable
A6: Non-Interest Income | B6: CAD millions | C6: 7153 | D6: 7531 | E6: 7304 | F6: 7403 | G6: 8791 | H6: 7616 | I6: 8634 | J6: 8564 | K6: 9375 | L6: 8947 | M6: SUP-24Q4-XLS / SUP-25Q4-XLS / SUP-26Q2-XLS | N6: Financial Highlights Page 2 / Statements of Income Page 5 | O6: Single-quarter reported values; PPPT and tax rate are model calculations where applicable
A7: Total Revenue | B7: CAD millions | C7: 13485 | D7: 14154 | E7: 14631 | F7: 15074 | G7: 16739 | H7: 15672 | I7: 16985 | J7: 17209 | K7: 17960 | L7: 17453 | M7: SUP-24Q4-XLS / SUP-25Q4-XLS / SUP-26Q2-XLS | N7: Financial Highlights Page 2 / Statements of Income Page 5 | O7: Single-quarter reported values; PPPT and tax rate are model calculations where applicable
A8: Provision for Credit Losses | B8: CAD millions | C8: 813 | D8: 920 | E8: 659 | F8: 840 | G8: 1050 | H8: 1424 | I8: 881 | J8: 1007 | K8: 1090 | L8: 912 | M8: SUP-24Q4-XLS / SUP-25Q4-XLS / SUP-26Q2-XLS | N8: Financial Highlights Page 2 / Statements of Income Page 5 | O8: Single-quarter reported values; PPPT and tax rate are model calculations where applicable
A9: Non-Interest Expense | B9: CAD millions | C9: 8324 | D9: 8308 | E9: 8599 | F9: 9019 | G9: 9256 | H9: 8730 | I9: 9232 | J9: 9374 | K9: 9463 | L9: 9437 | M9: SUP-24Q4-XLS / SUP-25Q4-XLS / SUP-26Q2-XLS | N9: Financial Highlights Page 2 / Statements of Income Page 5 | O9: Single-quarter reported values; PPPT and tax rate are model calculations where applicable
A10: Income Before Income Taxes | B10: CAD millions | C10: 4348 | D10: 4926 | E10: 5373 | F10: 5215 | G10: 6433 | H10: 5518 | I10: 6872 | J10: 6828 | K10: 7407 | L10: 7104 | M10: SUP-24Q4-XLS / SUP-25Q4-XLS / SUP-26Q2-XLS | N10: Financial Highlights Page 2 / Statements of Income Page 5 | O10: Single-quarter reported values; PPPT and tax rate are model calculations where applicable
A11: Income Taxes | B11: CAD millions | C11: 766 | D11: 976 | E11: 887 | F11: 993 | G11: 1302 | H11: 1128 | I11: 1458 | J11: 1394 | K11: 1622 | L11: 1595 | M11: SUP-24Q4-XLS / SUP-25Q4-XLS / SUP-26Q2-XLS | N11: Financial Highlights Page 2 / Statements of Income Page 5 | O11: Single-quarter reported values; PPPT and tax rate are model calculations where applicable
A12: Net Income | B12: CAD millions | C12: 3582 | D12: 3950 | E12: 4486 | F12: 4222 | G12: 5131 | H12: 4390 | I12: 5414 | J12: 5434 | K12: 5785 | L12: 5509 | M12: SUP-24Q4-XLS / SUP-25Q4-XLS / SUP-26Q2-XLS | N12: Financial Highlights Page 2 / Statements of Income Page 5 | O12: Single-quarter reported values; PPPT and tax rate are model calculations where applicable
A13: Net Income Available to Common Shareholders | B13: CAD millions | C13: 3522 | D13: 3881 | E13: 4377 | F13: 4128 | G13: 5011 | H13: 4274 | I13: 5290 | J13: 5293 | K13: 5643 | L13: 5372 | M13: SUP-24Q4-XLS / SUP-25Q4-XLS / SUP-26Q2-XLS | N13: Financial Highlights Page 2 / Statements of Income Page 5 | O13: Single-quarter reported values; PPPT and tax rate are model calculations where applicable
A14: Diluted EPS | B14: CAD per share | C14: 2.5 | D14: 2.74 | E14: 3.09 | F14: 2.91 | G14: 3.54 | H14: 3.02 | I14: 3.75 | J14: 3.76 | K14: 4.03 | L14: 3.85 | M14: SUP-24Q4-XLS / SUP-25Q4-XLS / SUP-26Q2-XLS | N14: Financial Highlights Page 2 / Statements of Income Page 5 | O14: Single-quarter reported values; PPPT and tax rate are model calculations where applicable
A15: ROE | B15: % | C15: 0.131 | D15: 0.145 | E15: 0.155 | F15: 0.143 | G15: 0.168 | H15: 0.142 | I15: 0.173 | J15: 0.168 | K15: 0.176 | L15: 0.172 | M15: SUP-24Q4-XLS / SUP-25Q4-XLS / SUP-26Q2-XLS | N15: Financial Highlights Page 2 / Statements of Income Page 5 | O15: Single-quarter reported values; PPPT and tax rate are model calculations where applicable
A16: Efficiency Ratio | B16: % | C16: 0.617 | D16: 0.587 | E16: 0.588 | F16: 0.598 | G16: 0.553 | H16: 0.557 | I16: 0.544 | J16: 0.545 | K16: 0.527 | L16: 0.541 | M16: SUP-24Q4-XLS / SUP-25Q4-XLS / SUP-26Q2-XLS | N16: Financial Highlights Page 2 / Statements of Income Page 5 | O16: Single-quarter reported values; PPPT and tax rate are model calculations where applicable
... A19: Effective Tax Rate | B19: % | C19: 0.17617295 | D19: 0.19813236 | E19: 0.16508468 | F19: 0.19041227 | G19: 0.20239391 | H19: 0.20442189 | I19: 0.21216531 | J19: 0.20415934 | K19: 0.21898204 | L19: 0.2245214 | M19: SUP-24Q4-XLS / SUP-25Q4-XLS / SUP-26Q2-XLS | N19: Financial Highlights Page 2 / Statements of Income Page 5 | O19: Single-quarter reported values; PPPT and tax rate are model calculations where applicable

Sheet 07_Raw_Balance_Sheet
A1: RAW BALANCE SHEET
A4: Metric | B4: Unit | C4: FY2023 | D4: FY2024 | E4: FY2025 | F4: Q1 2026 | G4: Q2 2026 | H4: Source ID | I4: Page / Table | J4: Source URL | K4: Notes
A5: Total Assets | B5: CAD millions | C5: 2006531 | D5: 2171582 | E5: 2325006 | F5: 2342393 | G5: 2396080 | H5: SUP-24Q4-XLS / SUP-25Q4-XLS / SUP-26Q2-XLS | I5: Balance Sheets Page 15; Loans Page 21 | J5: https://www.rbc.com/investor-relations/financial-information.html | K5: Period-end reported balances
A6: Cash and Due from Banks | B6: CAD millions | C6: 61989 | D6: 56723 | E6: 37024 | F6: 46226 | G6: 59347 | H6: SUP-24Q4-XLS / SUP-25Q4-XLS / SUP-26Q2-XLS | I6: Balance Sheets Page 15; Loans Page 21 | J6: https://www.rbc.com/investor-relations/financial-information.html | K6: Period-end reported balances
A7: Interest-bearing Deposits with Banks | B7: CAD millions | C7: 71086 | D7: 66020 | E7: 50364 | F7: 53073 | G7: 34146 | H7: SUP-24Q4-XLS / SUP-25Q4-XLS / SUP-26Q2-XLS | I7: Balance Sheets Page 15; Loans Page 21 | J7: https://www.rbc.com/investor-relations/financial-information.html | K7: Period-end reported balances
A8: Securities | B8: CAD millions | C8: 409730 | D8: 439918 | E8: 561788 | F8: 588966 | G8: 612364 | H8: SUP-24Q4-XLS / SUP-25Q4-XLS / SUP-26Q2-XLS | I8: Balance Sheets Page 15; Loans Page 21 | J8: https://www.rbc.com/investor-relations/financial-information.html | K8: Period-end reported balances
A9: Loans, Gross | B9: CAD millions | C9: 857777 | D9: 987417 | E9: 1049515 | F9: 1062282 | G9: 1085470 | H9: SUP-24Q4-XLS / SUP-25Q4-XLS / SUP-26Q2-XLS | I9: Balance Sheets Page 15; Loans Page 21 | J9: https://www.rbc.com/investor-relations/financial-information.html | K9: Period-end reported balances
A10: Allowance for Loan Losses | B10: CAD millions | C10: -5004 | D10: -6037 | E10: -7093 | F10: -7401 | G10: -7521 | H10: SUP-24Q4-XLS / SUP-25Q4-XLS / SUP-26Q2-XLS | I10: Balance Sheets Page 15; Loans Page 21 | J10: https://www.rbc.com/investor-relations/financial-information.html | K10: Period-end reported balances
A11: Loans, Net of Allowance | B11: CAD millions | C11: 852773 | D11: 981380 | E11: 1042422 | F11: 1054881 | G11: 1077949 | H11: SUP-24Q4-XLS / SUP-25Q4-XLS / SUP-26Q2-XLS | I11: Balance Sheets Page 15; Loans Page 21 | J11: https://www.rbc.com/investor-relations/financial-information.html | K11: Period-end reported balances
A12: Residential Mortgages | B12: CAD millions | C12: 434501 | D12: 477544 | E12: 493413 | F12: 496529 | G12: 500879 | H12: SUP-24Q4-XLS / SUP-25Q4-XLS / SUP-26Q2-XLS | I12: Balance Sheets Page 15; Loans Page 21 | J12: https://www.rbc.com/investor-relations/financial-information.html | K12: Period-end reported balances
A13: Personal Loans | B13: CAD millions | C13: 98734 | D13: 108338 | E13: 115345 | F13: 115489 | G13: 117720 | H13: SUP-24Q4-XLS / SUP-25Q4-XLS / SUP-26Q2-XLS | I13: Balance Sheets Page 15; Loans Page 21 | J13: https://www.rbc.com/investor-relations/financial-information.html | K13: Period-end reported balances
A14: Credit Cards | B14: CAD millions | C14: 23035 | D14: 25565 | E14: 26789 | F14: 26489 | G14: 27702 | H14: SUP-24Q4-XLS / SUP-25Q4-XLS / SUP-26Q2-XLS | I14: Balance Sheets Page 15; Loans Page 21 | J14: https://www.rbc.com/investor-relations/financial-information.html | K14: Period-end reported balances
A15: Business and Government Loans | B15: CAD millions | C15: 309571 | D15: 360474 | E15: 397190 | F15: 406864 | G15: 422154 | H15: SUP-24Q4-XLS / SUP-25Q4-XLS / SUP-26Q2-XLS | I15: Balance Sheets Page 15; Loans Page 21 | J15: https://www.rbc.com/investor-relations/financial-information.html | K15: Period-end reported balances
A16: Other Assets | B16: CAD millions | C16: 81371 | D16: 92190 | E16: 112893 | F16: 115296 | G16: 111841 | H16: SUP-24Q4-XLS / SUP-25Q4-XLS / SUP-26Q2-XLS | I16: Balance Sheets Page 15; Loans Page 21 | J16: https://www.rbc.com/investor-relations/financial-information.html | K16: Period-end reported balances
... A25: Loans and Acceptances | B25: CAD millions | C25: 879522 | D25: 987452 | E25: 1049534 | F25: 1062298 | G25: 1085510 | H25: SUP-24Q4-XLS / SUP-25Q4-XLS / SUP-26Q2-XLS | I25: Balance Sheets Page 15; Loans Page 21 | J25: https://www.rbc.com/investor-relations/financial-information.html | K25: Period-end reported balances

Sheet 08_Raw_Credit_Quality
A1: RAW CREDIT QUALITY
A4: Metric | B4: Unit | C4: FY2023 | D4: FY2024 | E4: FY2025 | F4: Q1 2026 | G4: Q2 2026 | H4: Source ID | I4: Page / Table | J4: Source URL | K4: Notes
A5: Total PCL | B5: CAD millions | C5: 2468 | D5: 3232 | E5: 4362 | F5: 1090 | G5: 912 | H5: SUP-24Q4-XLS / SUP-25Q4-XLS / SUP-26Q2-XLS | I5: Credit Quality Pages 22, 25, 27 and 29 | J5: https://www.rbc.com/investor-relations/financial-information.html | K5: Reported amount
A6: PCL on Performing Loans | B6: CAD millions | C6: 660 | D6: 627 | E6: 622 | F6: 28 | G6: 18 | H6: SUP-24Q4-XLS / SUP-25Q4-XLS / SUP-26Q2-XLS | I6: Credit Quality Pages 22, 25, 27 and 29 | J6: https://www.rbc.com/investor-relations/financial-information.html | K6: Reported amount
A7: PCL on Impaired Loans | B7: CAD millions | C7: 1836 | D7: 2620 | E7: 3734 | F7: 1068 | G7: 899 | H7: SUP-24Q4-XLS / SUP-25Q4-XLS / SUP-26Q2-XLS | I7: Credit Quality Pages 22, 25, 27 and 29 | J7: https://www.rbc.com/investor-relations/financial-information.html | K7: Reported amount
A8: PCL on Loans Ratio | B8: % | C8: 0.0029 | D8: 0.0035 | E8: 0.0043 | F8: 0.0041 | G8: 0.0035 | H8: SUP-24Q4-XLS / SUP-25Q4-XLS / SUP-26Q2-XLS | I8: Credit Quality Pages 22, 25, 27 and 29 | J8: https://www.rbc.com/investor-relations/financial-information.html | K8: Reported ratio; quarterly ratios are annualized where RBC presents them
A9: Gross Impaired Loans | B9: CAD millions | C9: 3704 | D9: 5867 | E9: 8682 | F9: 9167 | G9: 9790 | H9: SUP-24Q4-XLS / SUP-25Q4-XLS / SUP-26Q2-XLS | I9: Credit Quality Pages 22, 25, 27 and 29 | J9: https://www.rbc.com/investor-relations/financial-information.html | K9: Reported amount
A10: GIL Ratio | B10: % | C10: 0.0042 | D10: 0.0059 | E10: 0.0083 | F10: 0.0086 | G10: 0.009 | H10: SUP-24Q4-XLS / SUP-25Q4-XLS / SUP-26Q2-XLS | I10: Credit Quality Pages 22, 25, 27 and 29 | J10: https://www.rbc.com/investor-relations/financial-information.html | K10: Reported ratio; quarterly ratios are annualized where RBC presents them
A11: Allowance for Credit Losses | B11: CAD millions | C11: 5366 | D11: 6364 | E11: 7470 | F11: 7767 | G11: 7819 | H11: SUP-24Q4-XLS / SUP-25Q4-XLS / SUP-26Q2-XLS | I11: Credit Quality Pages 22, 25, 27 and 29 | J11: https://www.rbc.com/investor-relations/financial-information.html | K11: Reported amount
A12: ACL on Performing Loans | B12: CAD millions | C12: 4200 | D12: 4836 | E12: 5473 | F12: 5471 | G12: 5487 | H12: SUP-24Q4-XLS / SUP-25Q4-XLS / SUP-26Q2-XLS | I12: Credit Quality Pages 22, 25, 27 and 29 | J12: https://www.rbc.com/investor-relations/financial-information.html | K12: Reported amount
A13: ACL on Impaired Loans | B13: CAD millions | C13: 1148 | D13: 1516 | E13: 1986 | F13: 2281 | G13: 2317 | H13: SUP-24Q4-XLS / SUP-25Q4-XLS / SUP-26Q2-XLS | I13: Credit Quality Pages 22, 25, 27 and 29 | J13: https://www.rbc.com/investor-relations/financial-information.html | K13: Reported amount
A14: ACL-to-Loans Ratio | B14: % | C14: 0.0061 | D14: 0.0064 | E14: 0.0071 | F14: 0.0073 | G14: 0.0072 | H14: SUP-24Q4-XLS / SUP-25Q4-XLS / SUP-26Q2-XLS | I14: Credit Quality Pages 22, 25, 27 and 29 | J14: https://www.rbc.com/investor-relations/financial-information.html | K14: Reported ratio; quarterly ratios are annualized where RBC presents them
A15: Stage 3 ACL / GIL | B15: % | C15: 0.31 | D15: 0.2585 | E15: 0.2288 | F15: 0.2488 | G15: 0.2367 | H15: SUP-24Q4-XLS / SUP-25Q4-XLS / SUP-26Q2-XLS | I15: Credit Quality Pages 22, 25, 27 and 29 | J15: https://www.rbc.com/investor-relations/financial-information.html | K15: Reported ratio; quarterly ratios are annualized where RBC presents them
A16: Net Write-Off Ratio | B16: % | C16: 0.0014 | D16: 0.0022 | E16: 0.0028 | F16: 0.0024 | G16: 0.0028 | H16: SUP-24Q4-XLS / SUP-25Q4-XLS / SUP-26Q2-XLS | I16: Credit Quality Pages 22, 25, 27 and 29 | J16: https://www.rbc.com/investor-relations/financial-information.html | K16: Corrected to RBC-reported FY2023 annual net write-off ratio of 0.14%

Sheet 09_Raw_Capital_Liquidity
A1: RAW CAPITAL AND LIQUIDITY
A4: Metric | B4: Unit | C4: FY2023 | D4: FY2024 | E4: FY2025 | F4: Q1 2026 | G4: Q2 2026 | H4: Source ID | I4: Page / Table | J4: Source URL | K4: Notes
A5: CET1 Capital | B5: CAD millions | C5: 86611 | D5: 88936 | E5: 98748 | F5: 100415 | G5: 101313 | H5: AR-25 / SUP-26Q2-XLS / P3-26Q2-XLS | I5: Capital Pages 19–20; Annual Report liquidity pages 96–99; Pillar 3 KM1 | J5: https://www.rbc.com/investor-relations/financial-information.html | K5: Blank where a comparable period was not consistently collected
A6: Tier 1 Capital | B6: CAD millions | C6: 93904 | D6: 97952 | E6: 110393 | F6: 111549 | G6: 112453 | H6: AR-25 / SUP-26Q2-XLS / P3-26Q2-XLS | I6: Capital Pages 19–20; Annual Report liquidity pages 96–99; Pillar 3 KM1 | J6: https://www.rbc.com/investor-relations/financial-information.html | K6: Blank where a comparable period was not consistently collected
A7: Total Capital | B7: CAD millions | C7: 104952 | D7: 110487 | E7: 122399 | F7: 123732 | G7: 126286 | H7: AR-25 / SUP-26Q2-XLS / P3-26Q2-XLS | I7: Capital Pages 19–20; Annual Report liquidity pages 96–99; Pillar 3 KM1 | J7: https://www.rbc.com/investor-relations/financial-information.html | K7: Blank where a comparable period was not consistently collected
A8: Total Risk-Weighted Assets | B8: CAD millions | C8: 596223 | D8: 672282 | E8: 730225 | F8: 734693 | G8: 748590 | H8: AR-25 / SUP-26Q2-XLS / P3-26Q2-XLS | I8: Capital Pages 19–20; Annual Report liquidity pages 96–99; Pillar 3 KM1 | J8: https://www.rbc.com/investor-relations/financial-information.html | K8: Blank where a comparable period was not consistently collected
A9: CET1 Ratio | B9: % | C9: 0.145 | D9: 0.132 | E9: 0.135 | F9: 0.137 | G9: 0.135 | H9: AR-25 / SUP-26Q2-XLS / P3-26Q2-XLS | I9: Capital Pages 19–20; Annual Report liquidity pages 96–99; Pillar 3 KM1 | J9: https://www.rbc.com/investor-relations/financial-information.html | K9: Blank where a comparable period was not consistently collected
A10: Tier 1 Capital Ratio | B10: % | C10: 0.157 | D10: 0.146 | E10: 0.151 | F10: 0.152 | G10: 0.15 | H10: AR-25 / SUP-26Q2-XLS / P3-26Q2-XLS | I10: Capital Pages 19–20; Annual Report liquidity pages 96–99; Pillar 3 KM1 | J10: https://www.rbc.com/investor-relations/financial-information.html | K10: Blank where a comparable period was not consistently collected
A11: Total Capital Ratio | B11: % | C11: 0.176 | D11: 0.164 | E11: 0.168 | F11: 0.168 | G11: 0.169 | H11: AR-25 / SUP-26Q2-XLS / P3-26Q2-XLS | I11: Capital Pages 19–20; Annual Report liquidity pages 96–99; Pillar 3 KM1 | J11: https://www.rbc.com/investor-relations/financial-information.html | K11: Blank where a comparable period was not consistently collected
A12: Leverage Ratio | B12: % | C12: 0.043 | D12: 0.042 | E12: 0.044 | F12: 0.044 | G12: 0.043 | H12: AR-25 / SUP-26Q2-XLS / P3-26Q2-XLS | I12: Capital Pages 19–20; Annual Report liquidity pages 96–99; Pillar 3 KM1 | J12: https://www.rbc.com/investor-relations/financial-information.html | K12: Blank where a comparable period was not consistently collected
A13: Liquidity Coverage Ratio | B13: % | D13: 1.28 | E13: 1.27 | F13: 1.24 | G13: 1.26 | H13: AR-25 / SUP-26Q2-XLS / P3-26Q2-XLS | I13: Capital Pages 19–20; Annual Report liquidity pages 96–99; Pillar 3 KM1 | J13: https://www.rbc.com/investor-relations/financial-information.html | K13: FY2024–FY2025 are annual average LCRs; Q1–Q2 2026 are quarterly average LCRs
A14: Net Stable Funding Ratio | B14: % | D14: 1.14 | E14: 1.12 | F14: 1.11 | G14: 1.11 | H14: AR-25 / SUP-26Q2-XLS / P3-26Q2-XLS | I14: Capital Pages 19–20; Annual Report liquidity pages 96–99; Pillar 3 KM1 | J14: https://www.rbc.com/investor-relations/financial-information.html | K14: FY2024–FY2025 are annual average NSFRs; Q1–Q2 2026 are quarter-end NSFRs
A15: Common Shareholders' Equity | B15: CAD millions | C15: 107734 | D15: 118058 | E15: 127417 | F15: 128670 | G15: 129579 | H15: AR-25 / SUP-26Q2-XLS / P3-26Q2-XLS | I15: Capital Pages 19–20; Annual Report liquidity pages 96–99; Pillar 3 KM1 | J15: https://www.rbc.com/investor-relations/financial-information.html | K15: Blank where a comparable period was not consistently collected
A16: Dividends Per Common Share | B16: CAD per share | C16: 5.4 | D16: 5.6 | E16: 6.04 | F16: 1.64 | G16: 1.64 | H16: AR-25 / SUP-26Q2-XLS / P3-26Q2-XLS | I16: Capital Pages 19–20; Annual Report liquidity pages 96–99; Pillar 3 KM1 | J16: https://www.rbc.com/investor-relations/financial-information.html | K16: Annual dividends declared per share for FY2023–FY2025; quarterly declarations for Q1–Q2 2026

Sheet 10_Raw_Segment_Results
A1: RAW SEGMENT RESULTS
A4: Period | B4: Segment | C4: Total Revenue | D4: Net Interest Income | E4: Non-Interest Income | F4: PCL | G4: Non-Interest Expense | H4: Net Income | I4: ROE | J4: Efficiency Ratio | K4: Source ID | L4: Notes
A5: FY2023 | B5: Personal Banking | C5: 15471 | D5: 10945 | E5: 4526 | F5: 1264 | G5: 6813 | H5: 5418 | I5: 0.289 | J5: 0.44 | K5: SUP-24Q4-XLS / SUP-25Q4-XLS / SUP-26Q2-XLS | L5: Verified against the relevant RBC segment schedule; TEB presentation applies to Capital Markets and Corporate Support
A6: FY2023 | B6: Commercial Banking | C6: 6032 | D6: 4771 | E6: 1261 | F6: 315 | G6: 2143 | H6: 2582 | I6: 0.237 | J6: 0.355 | K6: SUP-24Q4-XLS / SUP-25Q4-XLS / SUP-26Q2-XLS | L6: Verified against the relevant RBC segment schedule; TEB presentation applies to Capital Markets and Corporate Support
A7: FY2023 | B7: Wealth Management | C7: 18161 | D7: 4853 | E7: 13308 | F7: 328 | G7: 14387 | H7: 2693 | I7: 0.109 | K7: SUP-24Q4-XLS / SUP-25Q4-XLS / SUP-26Q2-XLS | L7: Verified against the relevant RBC segment schedule; TEB presentation applies to Capital Markets and Corporate Support
A8: FY2023 | B8: Insurance | C8: 1010 | F8: 0 | G8: 293 | H8: 549 | I8: 0.253 | K8: SUP-24Q4-XLS / SUP-25Q4-XLS / SUP-26Q2-XLS | L8: Verified against the relevant RBC segment schedule; TEB presentation applies to Capital Markets and Corporate Support
A9: FY2023 | B9: Capital Markets | C9: 11051 | D9: 3379 | E9: 7672 | F9: 561 | G9: 6509 | H9: 4139 | I9: 0.146 | K9: SUP-24Q4-XLS / SUP-25Q4-XLS / SUP-26Q2-XLS | L9: Verified against the relevant RBC segment schedule; TEB presentation applies to Capital Markets and Corporate Support
A10: FY2023 | B10: Corporate Support | C10: -261 | D10: 1181 | E10: -1553 | F10: 0 | G10: 559 | H10: -769 | K10: SUP-24Q4-XLS / SUP-25Q4-XLS / SUP-26Q2-XLS | L10: Verified against the relevant RBC segment schedule; TEB presentation applies to Capital Markets and Corporate Support
A11: FY2024 | B11: Personal Banking | C11: 17342 | D11: 12438 | E11: 4904 | F11: 1802 | G11: 7485 | H11: 5921 | I11: 0.248 | J11: 0.432 | K11: SUP-24Q4-XLS / SUP-25Q4-XLS / SUP-26Q2-XLS | L11: Verified against the relevant RBC segment schedule; TEB presentation applies to Capital Markets and Corporate Support
A12: FY2024 | B12: Commercial Banking | C12: 7382 | D12: 6061 | E12: 1321 | F12: 975 | G12: 2512 | H12: 2818 | I12: 0.185 | J12: 0.34 | K12: SUP-24Q4-XLS / SUP-25Q4-XLS / SUP-26Q2-XLS | L12: Verified against the relevant RBC segment schedule; TEB presentation applies to Capital Markets and Corporate Support
A13: FY2024 | B13: Wealth Management | C13: 19626 | D13: 4979 | E13: 14647 | F13: 29 | G13: 15312 | H13: 3422 | I13: 0.144 | K13: SUP-24Q4-XLS / SUP-25Q4-XLS / SUP-26Q2-XLS | L13: Verified against the relevant RBC segment schedule; TEB presentation applies to Capital Markets and Corporate Support
A14: FY2024 | B14: Insurance | C14: 1224 | F14: 0 | G14: 285 | H14: 729 | I14: 0.353 | K14: SUP-24Q4-XLS / SUP-25Q4-XLS / SUP-26Q2-XLS | L14: Verified against the relevant RBC segment schedule; TEB presentation applies to Capital Markets and Corporate Support
A15: FY2024 | B15: Capital Markets | C15: 12012 | D15: 3183 | E15: 8829 | F15: 424 | G15: 7016 | H15: 4573 | I15: 0.142 | K15: SUP-24Q4-XLS / SUP-25Q4-XLS / SUP-26Q2-XLS | L15: Verified against the relevant RBC segment schedule; TEB presentation applies to Capital Markets and Corporate Support
A16: FY2024 | B16: Corporate Support | C16: -242 | D16: 1292 | E16: -2033 | F16: 0 | G16: 1167 | H16: -1223 | K16: SUP-24Q4-XLS / SUP-25Q4-XLS / SUP-26Q2-XLS | L16: Verified against the relevant RBC segment schedule; TEB presentation applies to Capital Markets and Corporate Support
A17: FY2025 | B17: Personal Banking | C17: 19854 | D17: 14496 | E17: 5358 | F17: 2105 | G17: 8001 | H17: 7105 | I17: 0.249 | J17: 0.403 | K17: SUP-24Q4-XLS / SUP-25Q4-XLS / SUP-26Q2-XLS | L17: Verified against the relevant RBC segment schedule; TEB presentation applies to Capital Markets and Corporate Support
A18: FY2025 | B18: Commercial Banking | C18: 8562 | D18: 7268 | E18: 1294 | F18: 1550 | G18: 2833 | H18: 3020 | I18: 0.149 | J18: 0.331 | K18: SUP-24Q4-XLS / SUP-25Q4-XLS / SUP-26Q2-XLS | L18: Verified against the relevant RBC segment schedule; TEB presentation applies to Capital Markets and Corporate Support
A19: FY2025 | B19: Wealth Management | C19: 22378 | D19: 5459 | E19: 16919 | F19: 120 | G19: 16769 | H19: 4289 | I19: 0.166 | K19: SUP-24Q4-XLS / SUP-25Q4-XLS / SUP-26Q2-XLS | L19: Verified against the relevant RBC segment schedule; TEB presentation applies to Capital Markets and Corporate Support
A20: FY2025 | B20: Insurance | C20: 1321 | F20: 0 | G20: 315 | H20: 828 | I20: 0.407 | K20: SUP-24Q4-XLS / SUP-25Q4-XLS / SUP-26Q2-XLS | L20: Verified against the relevant RBC segment schedule; TEB presentation applies to Capital Markets and Corporate Support
A21: FY2025 | B21: Capital Markets | C21: 14426 | D21: 4789 | E21: 9637 | F21: 587 | G21: 7966 | H21: 5393 | I21: 0.137 | K21: SUP-24Q4-XLS / SUP-25Q4-XLS / SUP-26Q2-XLS | L21: Verified against the relevant RBC segment schedule; TEB presentation applies to Capital Markets and Corporate Support
A22: FY2025 | B22: Corporate Support | C22: 64 | D22: 988 | E22: -1329 | F22: 0 | G22: 317 | H22: -266 | K22: SUP-24Q4-XLS / SUP-25Q4-XLS / SUP-26Q2-XLS | L22: Verified against the relevant RBC segment schedule; TEB presentation applies to Capital Markets and Corporate Support
A23: Q1 2026 | B23: Personal Banking | C23: 5238 | D23: 3831 | E23: 1407 | F23: 531 | G23: 2020 | H23: 1962 | I23: 0.263 | J23: 0.386 | K23: SUP-24Q4-XLS / SUP-25Q4-XLS / SUP-26Q2-XLS | L23: Verified against the relevant RBC segment schedule; TEB presentation applies to Capital Markets and Corporate Support
A24: Q1 2026 | B24: Commercial Banking | C24: 2207 | D24: 1895 | E24: 312 | F24: 286 | G24: 725 | H24: 863 | I24: 0.169 | J24: 0.329 | K24: SUP-24Q4-XLS / SUP-25Q4-XLS / SUP-26Q2-XLS | L24: Verified against the relevant RBC segment schedule; TEB presentation applies to Capital Markets and Corporate Support
A25: Q1 2026 | B25: Wealth Management | C25: 6084 | D25: 1454 | E25: 4630 | F25: 18 | G25: 4384 | H25: 1295 | I25: 0.196 | K25: SUP-24Q4-XLS / SUP-25Q4-XLS / SUP-26Q2-XLS | L25: Verified against the relevant RBC segment schedule; TEB presentation applies to Capital Markets and Corporate Support
A26: Q1 2026 | B26: Insurance | C26: 338 | F26: 0 | G26: 78 | H26: 213 | I26: 0.249 | K26: SUP-24Q4-XLS / SUP-25Q4-XLS / SUP-26Q2-XLS | L26: Verified against the relevant RBC segment schedule; TEB presentation applies to Capital Markets and Corporate Support
A27: Q1 2026 | B27: Capital Markets | C27: 4018 | D27: 1218 | E27: 2800 | F27: 256 | G27: 2119 | H27: 1478 | I27: 0.144 | K27: SUP-24Q4-XLS / SUP-25Q4-XLS / SUP-26Q2-XLS | L27: Verified against the relevant RBC segment schedule; TEB presentation applies to Capital Markets and Corporate Support
A28: Q1 2026 | B28: Corporate Support | C28: 75 | D28: 187 | E28: -202 | F28: -1 | G28: 51 | H28: -26 | K28: SUP-24Q4-XLS / SUP-25Q4-XLS / SUP-26Q2-XLS | L28: Verified against the relevant RBC segment schedule; TEB presentation applies to Capital Markets and Corporate Support
A29: Q2 2026 | B29: Personal Banking | C29: 5049 | D29: 3715 | E29: 1334 | F29: 492 | G29: 1987 | H29: 1870 | I29: 0.254 | J29: 0.394 | K29: SUP-24Q4-XLS / SUP-25Q4-XLS / SUP-26Q2-XLS | L29: Verified against the relevant RBC segment schedule; TEB presentation applies to Capital Markets and Corporate Support
A30: Q2 2026 | B30: Commercial Banking | C30: 2159 | D30: 1844 | E30: 315 | F30: 247 | G30: 730 | H30: 854 | I30: 0.174 | J30: 0.338 | K30: SUP-24Q4-XLS / SUP-25Q4-XLS / SUP-26Q2-XLS | L30: Verified against the relevant RBC segment schedule; TEB presentation applies to Capital Markets and Corporate Support
A31: Q2 2026 | B31: Wealth Management | C31: 5954 | D31: 1429 | E31: 4525 | F31: 55 | G31: 4379 | H31: 1185 | I31: 0.186 | K31: SUP-24Q4-XLS / SUP-25Q4-XLS / SUP-26Q2-XLS | L31: Verified against the relevant RBC segment schedule; TEB presentation applies to Capital Markets and Corporate Support
A32: Q2 2026 | B32: Insurance | C32: 345 | F32: 0 | G32: 75 | H32: 218 | I32: 0.259 | K32: SUP-24Q4-XLS / SUP-25Q4-XLS / SUP-26Q2-XLS | L32: Verified against the relevant RBC segment schedule; TEB presentation applies to Capital Markets and Corporate Support
A33: Q2 2026 | B33: Capital Markets | C33: 3943 | D33: 1315 | E33: 2628 | F33: 117 | G33: 2097 | H33: 1484 | I33: 0.148 | K33: SUP-24Q4-XLS / SUP-25Q4-XLS / SUP-26Q2-XLS | L33: Verified against the relevant RBC segment schedule; TEB presentation applies to Capital Markets and Corporate Support
A34: Q2 2026 | B34: Corporate Support | C34: 3 | D34: 203 | E34: -279 | F34: 1 | G34: 95 | H34: -102 | K34: SUP-24Q4-XLS / SUP-25Q4-XLS / SUP-26Q2-XLS | L34: Verified against the relevant RBC segment schedule; TEB presentation applies to Capital Markets and Corporate Support

Sheet 11_STD_Performance
A1: STANDARDIZED PERFORMANCE
A4: Metric | B4: FY2023 | C4: FY2024 | D4: FY2025
A5: Net Interest Income | B5: =IFERROR(INDEX('05_Raw_Annual_Performance'!$C$5:$E$100,MATCH($A5,'05_Raw_Annual_Performance'!$A$5:$A$100,0),MATCH(B$4,'05_Raw_Annual_Performance'!$C$4:$E$4,0)),"") -> 25129 | C5: =IFERROR(INDEX('05_Raw_Annual_Performance'!$C$5:$E$100,MATCH($A5,'05_Raw_Annual_Performance'!$A$5:$A$100,0),MATCH(C$4,'05_Raw_Annual_Performance'!$C$4:$E$4,0)),"") -> 27953 | D5: =IFERROR(INDEX('05_Raw_Annual_Performance'!$C$5:$E$100,MATCH($A5,'05_Raw_Annual_Performance'!$A$5:$A$100,0),MATCH(D$4,'05_Raw_Annual_Performance'!$C$4:$E$4,0)),"") -> 33000
A6: Non-Interest Income | B6: =IFERROR(INDEX('05_Raw_Annual_Performance'!$C$5:$E$100,MATCH($A6,'05_Raw_Annual_Performance'!$A$5:$A$100,0),MATCH(B$4,'05_Raw_Annual_Performance'!$C$4:$E$4,0)),"") -> 26335 | C6: =IFERROR(INDEX('05_Raw_Annual_Performance'!$C$5:$E$100,MATCH($A6,'05_Raw_Annual_Performance'!$A$5:$A$100,0),MATCH(C$4,'05_Raw_Annual_Performance'!$C$4:$E$4,0)),"") -> 29391 | D6: =IFERROR(INDEX('05_Raw_Annual_Performance'!$C$5:$E$100,MATCH($A6,'05_Raw_Annual_Performance'!$A$5:$A$100,0),MATCH(D$4,'05_Raw_Annual_Performance'!$C$4:$E$4,0)),"") -> 33605
A7: Total Revenue | B7: =IFERROR(INDEX('05_Raw_Annual_Performance'!$C$5:$E$100,MATCH($A7,'05_Raw_Annual_Performance'!$A$5:$A$100,0),MATCH(B$4,'05_Raw_Annual_Performance'!$C$4:$E$4,0)),"") -> 51464 | C7: =IFERROR(INDEX('05_Raw_Annual_Performance'!$C$5:$E$100,MATCH($A7,'05_Raw_Annual_Performance'!$A$5:$A$100,0),MATCH(C$4,'05_Raw_Annual_Performance'!$C$4:$E$4,0)),"") -> 57344 | D7: =IFERROR(INDEX('05_Raw_Annual_Performance'!$C$5:$E$100,MATCH($A7,'05_Raw_Annual_Performance'!$A$5:$A$100,0),MATCH(D$4,'05_Raw_Annual_Performance'!$C$4:$E$4,0)),"") -> 66605
A8: Provision for Credit Losses | B8: =IFERROR(INDEX('05_Raw_Annual_Performance'!$C$5:$E$100,MATCH($A8,'05_Raw_Annual_Performance'!$A$5:$A$100,0),MATCH(B$4,'05_Raw_Annual_Performance'!$C$4:$E$4,0)),"") -> 2468 | C8: =IFERROR(INDEX('05_Raw_Annual_Performance'!$C$5:$E$100,MATCH($A8,'05_Raw_Annual_Performance'!$A$5:$A$100,0),MATCH(C$4,'05_Raw_Annual_Performance'!$C$4:$E$4,0)),"") -> 3232 | D8: =IFERROR(INDEX('05_Raw_Annual_Performance'!$C$5:$E$100,MATCH($A8,'05_Raw_Annual_Performance'!$A$5:$A$100,0),MATCH(D$4,'05_Raw_Annual_Performance'!$C$4:$E$4,0)),"") -> 4362
A9: Non-Interest Expense | B9: =IFERROR(INDEX('05_Raw_Annual_Performance'!$C$5:$E$100,MATCH($A9,'05_Raw_Annual_Performance'!$A$5:$A$100,0),MATCH(B$4,'05_Raw_Annual_Performance'!$C$4:$E$4,0)),"") -> 30813 | C9: =IFERROR(INDEX('05_Raw_Annual_Performance'!$C$5:$E$100,MATCH($A9,'05_Raw_Annual_Performance'!$A$5:$A$100,0),MATCH(C$4,'05_Raw_Annual_Performance'!$C$4:$E$4,0)),"") -> 34250 | D9: =IFERROR(INDEX('05_Raw_Annual_Performance'!$C$5:$E$100,MATCH($A9,'05_Raw_Annual_Performance'!$A$5:$A$100,0),MATCH(D$4,'05_Raw_Annual_Performance'!$C$4:$E$4,0)),"") -> 36592
A10: Income Before Income Taxes | B10: =IFERROR(INDEX('05_Raw_Annual_Performance'!$C$5:$E$100,MATCH($A10,'05_Raw_Annual_Performance'!$A$5:$A$100,0),MATCH(B$4,'05_Raw_Annual_Performance'!$C$4:$E$4,0)),"") -> 18183 | C10: =IFERROR(INDEX('05_Raw_Annual_Performance'!$C$5:$E$100,MATCH($A10,'05_Raw_Annual_Performance'!$A$5:$A$100,0),MATCH(C$4,'05_Raw_Annual_Performance'!$C$4:$E$4,0)),"") -> 19862 | D10: =IFERROR(INDEX('05_Raw_Annual_Performance'!$C$5:$E$100,MATCH($A10,'05_Raw_Annual_Performance'!$A$5:$A$100,0),MATCH(D$4,'05_Raw_Annual_Performance'!$C$4:$E$4,0)),"") -> 25651
A11: Income Taxes | B11: =IFERROR(INDEX('05_Raw_Annual_Performance'!$C$5:$E$100,MATCH($A11,'05_Raw_Annual_Performance'!$A$5:$A$100,0),MATCH(B$4,'05_Raw_Annual_Performance'!$C$4:$E$4,0)),"") -> 3571 | C11: =IFERROR(INDEX('05_Raw_Annual_Performance'!$C$5:$E$100,MATCH($A11,'05_Raw_Annual_Performance'!$A$5:$A$100,0),MATCH(C$4,'05_Raw_Annual_Performance'!$C$4:$E$4,0)),"") -> 3622 | D11: =IFERROR(INDEX('05_Raw_Annual_Performance'!$C$5:$E$100,MATCH($A11,'05_Raw_Annual_Performance'!$A$5:$A$100,0),MATCH(D$4,'05_Raw_Annual_Performance'!$C$4:$E$4,0)),"") -> 5282
A12: Net Income | B12: =IFERROR(INDEX('05_Raw_Annual_Performance'!$C$5:$E$100,MATCH($A12,'05_Raw_Annual_Performance'!$A$5:$A$100,0),MATCH(B$4,'05_Raw_Annual_Performance'!$C$4:$E$4,0)),"") -> 14612 | C12: =IFERROR(INDEX('05_Raw_Annual_Performance'!$C$5:$E$100,MATCH($A12,'05_Raw_Annual_Performance'!$A$5:$A$100,0),MATCH(C$4,'05_Raw_Annual_Performance'!$C$4:$E$4,0)),"") -> 16240 | D12: =IFERROR(INDEX('05_Raw_Annual_Performance'!$C$5:$E$100,MATCH($A12,'05_Raw_Annual_Performance'!$A$5:$A$100,0),MATCH(D$4,'05_Raw_Annual_Performance'!$C$4:$E$4,0)),"") -> 20369
A13: Net Income Available to Common Shareholders | B13: =IFERROR(INDEX('05_Raw_Annual_Performance'!$C$5:$E$100,MATCH($A13,'05_Raw_Annual_Performance'!$A$5:$A$100,0),MATCH(B$4,'05_Raw_Annual_Performance'!$C$4:$E$4,0)),"") -> 14369 | C13: =IFERROR(INDEX('05_Raw_Annual_Performance'!$C$5:$E$100,MATCH($A13,'05_Raw_Annual_Performance'!$A$5:$A$100,0),MATCH(C$4,'05_Raw_Annual_Performance'!$C$4:$E$4,0)),"") -> 15908 | D13: =IFERROR(INDEX('05_Raw_Annual_Performance'!$C$5:$E$100,MATCH($A13,'05_Raw_Annual_Performance'!$A$5:$A$100,0),MATCH(D$4,'05_Raw_Annual_Performance'!$C$4:$E$4,0)),"") -> 19868
A14: Diluted EPS | B14: =IFERROR(INDEX('05_Raw_Annual_Performance'!$C$5:$E$100,MATCH($A14,'05_Raw_Annual_Performance'!$A$5:$A$100,0),MATCH(B$4,'05_Raw_Annual_Performance'!$C$4:$E$4,0)),"") -> 10.32 | C14: =IFERROR(INDEX('05_Raw_Annual_Performance'!$C$5:$E$100,MATCH($A14,'05_Raw_Annual_Performance'!$A$5:$A$100,0),MATCH(C$4,'05_Raw_Annual_Performance'!$C$4:$E$4,0)),"") -> 11.25 | D14: =IFERROR(INDEX('05_Raw_Annual_Performance'!$C$5:$E$100,MATCH($A14,'05_Raw_Annual_Performance'!$A$5:$A$100,0),MATCH(D$4,'05_Raw_Annual_Performance'!$C$4:$E$4,0)),"") -> 14.07
A15: ROE | B15: =IFERROR(INDEX('05_Raw_Annual_Performance'!$C$5:$E$100,MATCH($A15,'05_Raw_Annual_Performance'!$A$5:$A$100,0),MATCH(B$4,'05_Raw_Annual_Performance'!$C$4:$E$4,0)),"") -> 0.143 | C15: =IFERROR(INDEX('05_Raw_Annual_Performance'!$C$5:$E$100,MATCH($A15,'05_Raw_Annual_Performance'!$A$5:$A$100,0),MATCH(C$4,'05_Raw_Annual_Performance'!$C$4:$E$4,0)),"") -> 0.144 | D15: =IFERROR(INDEX('05_Raw_Annual_Performance'!$C$5:$E$100,MATCH($A15,'05_Raw_Annual_Performance'!$A$5:$A$100,0),MATCH(D$4,'05_Raw_Annual_Performance'!$C$4:$E$4,0)),"") -> 0.163
A16: Efficiency Ratio | B16: =IFERROR(INDEX('05_Raw_Annual_Performance'!$C$5:$E$100,MATCH($A16,'05_Raw_Annual_Performance'!$A$5:$A$100,0),MATCH(B$4,'05_Raw_Annual_Performance'!$C$4:$E$4,0)),"") -> 0.599 | C16: =IFERROR(INDEX('05_Raw_Annual_Performance'!$C$5:$E$100,MATCH($A16,'05_Raw_Annual_Performance'!$A$5:$A$100,0),MATCH(C$4,'05_Raw_Annual_Performance'!$C$4:$E$4,0)),"") -> 0.597 | D16: =IFERROR(INDEX('05_Raw_Annual_Performance'!$C$5:$E$100,MATCH($A16,'05_Raw_Annual_Performance'!$A$5:$A$100,0),MATCH(D$4,'05_Raw_Annual_Performance'!$C$4:$E$4,0)),"") -> 0.549
... A19: Effective Tax Rate | B19: =IFERROR(INDEX('05_Raw_Annual_Performance'!$C$5:$E$100,MATCH($A19,'05_Raw_Annual_Performance'!$A$5:$A$100,0),MATCH(B$4,'05_Raw_Annual_Performance'!$C$4:$E$4,0)),"") -> 0.19639223 | C19: =IFERROR(INDEX('05_Raw_Annual_Performance'!$C$5:$E$100,MATCH($A19,'05_Raw_Annual_Performance'!$A$5:$A$100,0),MATCH(C$4,'05_Raw_Annual_Performance'!$C$4:$E$4,0)),"") -> 0.18235827 | D19: =IFERROR(INDEX('05_Raw_Annual_Performance'!$C$5:$E$100,MATCH($A19,'05_Raw_Annual_Performance'!$A$5:$A$100,0),MATCH(D$4,'05_Raw_Annual_Performance'!$C$4:$E$4,0)),"") -> 0.2059179

Sheet 12_STD_Balance_Sheet
A1: STANDARDIZED BALANCE SHEET
A4: Metric | B4: FY2023 | C4: FY2024 | D4: FY2025 | E4: Q1 2026 | F4: Q2 2026
A5: Total Assets | B5: =IFERROR(INDEX('07_Raw_Balance_Sheet'!$C$5:$G$100,MATCH($A5,'07_Raw_Balance_Sheet'!$A$5:$A$100,0),MATCH(B$4,'07_Raw_Balance_Sheet'!$C$4:$G$4,0)),"") -> 2006531 | C5: =IFERROR(INDEX('07_Raw_Balance_Sheet'!$C$5:$G$100,MATCH($A5,'07_Raw_Balance_Sheet'!$A$5:$A$100,0),MATCH(C$4,'07_Raw_Balance_Sheet'!$C$4:$G$4,0)),"") -> 2171582 | D5: =IFERROR(INDEX('07_Raw_Balance_Sheet'!$C$5:$G$100,MATCH($A5,'07_Raw_Balance_Sheet'!$A$5:$A$100,0),MATCH(D$4,'07_Raw_Balance_Sheet'!$C$4:$G$4,0)),"") -> 2325006 | E5: =IFERROR(INDEX('07_Raw_Balance_Sheet'!$C$5:$G$100,MATCH($A5,'07_Raw_Balance_Sheet'!$A$5:$A$100,0),MATCH(E$4,'07_Raw_Balance_Sheet'!$C$4:$G$4,0)),"") -> 2342393 | F5: =IFERROR(INDEX('07_Raw_Balance_Sheet'!$C$5:$G$100,MATCH($A5,'07_Raw_Balance_Sheet'!$A$5:$A$100,0),MATCH(F$4,'07_Raw_Balance_Sheet'!$C$4:$G$4,0)),"") -> 2396080
A6: Cash and Due from Banks | B6: =IFERROR(INDEX('07_Raw_Balance_Sheet'!$C$5:$G$100,MATCH($A6,'07_Raw_Balance_Sheet'!$A$5:$A$100,0),MATCH(B$4,'07_Raw_Balance_Sheet'!$C$4:$G$4,0)),"") -> 61989 | C6: =IFERROR(INDEX('07_Raw_Balance_Sheet'!$C$5:$G$100,MATCH($A6,'07_Raw_Balance_Sheet'!$A$5:$A$100,0),MATCH(C$4,'07_Raw_Balance_Sheet'!$C$4:$G$4,0)),"") -> 56723 | D6: =IFERROR(INDEX('07_Raw_Balance_Sheet'!$C$5:$G$100,MATCH($A6,'07_Raw_Balance_Sheet'!$A$5:$A$100,0),MATCH(D$4,'07_Raw_Balance_Sheet'!$C$4:$G$4,0)),"") -> 37024 | E6: =IFERROR(INDEX('07_Raw_Balance_Sheet'!$C$5:$G$100,MATCH($A6,'07_Raw_Balance_Sheet'!$A$5:$A$100,0),MATCH(E$4,'07_Raw_Balance_Sheet'!$C$4:$G$4,0)),"") -> 46226 | F6: =IFERROR(INDEX('07_Raw_Balance_Sheet'!$C$5:$G$100,MATCH($A6,'07_Raw_Balance_Sheet'!$A$5:$A$100,0),MATCH(F$4,'07_Raw_Balance_Sheet'!$C$4:$G$4,0)),"") -> 59347
A7: Interest-bearing Deposits with Banks | B7: =IFERROR(INDEX('07_Raw_Balance_Sheet'!$C$5:$G$100,MATCH($A7,'07_Raw_Balance_Sheet'!$A$5:$A$100,0),MATCH(B$4,'07_Raw_Balance_Sheet'!$C$4:$G$4,0)),"") -> 71086 | C7: =IFERROR(INDEX('07_Raw_Balance_Sheet'!$C$5:$G$100,MATCH($A7,'07_Raw_Balance_Sheet'!$A$5:$A$100,0),MATCH(C$4,'07_Raw_Balance_Sheet'!$C$4:$G$4,0)),"") -> 66020 | D7: =IFERROR(INDEX('07_Raw_Balance_Sheet'!$C$5:$G$100,MATCH($A7,'07_Raw_Balance_Sheet'!$A$5:$A$100,0),MATCH(D$4,'07_Raw_Balance_Sheet'!$C$4:$G$4,0)),"") -> 50364 | E7: =IFERROR(INDEX('07_Raw_Balance_Sheet'!$C$5:$G$100,MATCH($A7,'07_Raw_Balance_Sheet'!$A$5:$A$100,0),MATCH(E$4,'07_Raw_Balance_Sheet'!$C$4:$G$4,0)),"") -> 53073 | F7: =IFERROR(INDEX('07_Raw_Balance_Sheet'!$C$5:$G$100,MATCH($A7,'07_Raw_Balance_Sheet'!$A$5:$A$100,0),MATCH(F$4,'07_Raw_Balance_Sheet'!$C$4:$G$4,0)),"") -> 34146
A8: Securities | B8: =IFERROR(INDEX('07_Raw_Balance_Sheet'!$C$5:$G$100,MATCH($A8,'07_Raw_Balance_Sheet'!$A$5:$A$100,0),MATCH(B$4,'07_Raw_Balance_Sheet'!$C$4:$G$4,0)),"") -> 409730 | C8: =IFERROR(INDEX('07_Raw_Balance_Sheet'!$C$5:$G$100,MATCH($A8,'07_Raw_Balance_Sheet'!$A$5:$A$100,0),MATCH(C$4,'07_Raw_Balance_Sheet'!$C$4:$G$4,0)),"") -> 439918 | D8: =IFERROR(INDEX('07_Raw_Balance_Sheet'!$C$5:$G$100,MATCH($A8,'07_Raw_Balance_Sheet'!$A$5:$A$100,0),MATCH(D$4,'07_Raw_Balance_Sheet'!$C$4:$G$4,0)),"") -> 561788 | E8: =IFERROR(INDEX('07_Raw_Balance_Sheet'!$C$5:$G$100,MATCH($A8,'07_Raw_Balance_Sheet'!$A$5:$A$100,0),MATCH(E$4,'07_Raw_Balance_Sheet'!$C$4:$G$4,0)),"") -> 588966 | F8: =IFERROR(INDEX('07_Raw_Balance_Sheet'!$C$5:$G$100,MATCH($A8,'07_Raw_Balance_Sheet'!$A$5:$A$100,0),MATCH(F$4,'07_Raw_Balance_Sheet'!$C$4:$G$4,0)),"") -> 612364
A9: Loans, Gross | B9: =IFERROR(INDEX('07_Raw_Balance_Sheet'!$C$5:$G$100,MATCH($A9,'07_Raw_Balance_Sheet'!$A$5:$A$100,0),MATCH(B$4,'07_Raw_Balance_Sheet'!$C$4:$G$4,0)),"") -> 857777 | C9: =IFERROR(INDEX('07_Raw_Balance_Sheet'!$C$5:$G$100,MATCH($A9,'07_Raw_Balance_Sheet'!$A$5:$A$100,0),MATCH(C$4,'07_Raw_Balance_Sheet'!$C$4:$G$4,0)),"") -> 987417 | D9: =IFERROR(INDEX('07_Raw_Balance_Sheet'!$C$5:$G$100,MATCH($A9,'07_Raw_Balance_Sheet'!$A$5:$A$100,0),MATCH(D$4,'07_Raw_Balance_Sheet'!$C$4:$G$4,0)),"") -> 1049515 | E9: =IFERROR(INDEX('07_Raw_Balance_Sheet'!$C$5:$G$100,MATCH($A9,'07_Raw_Balance_Sheet'!$A$5:$A$100,0),MATCH(E$4,'07_Raw_Balance_Sheet'!$C$4:$G$4,0)),"") -> 1062282 | F9: =IFERROR(INDEX('07_Raw_Balance_Sheet'!$C$5:$G$100,MATCH($A9,'07_Raw_Balance_Sheet'!$A$5:$A$100,0),MATCH(F$4,'07_Raw_Balance_Sheet'!$C$4:$G$4,0)),"") -> 1085470
A10: Allowance for Loan Losses | B10: =IFERROR(INDEX('07_Raw_Balance_Sheet'!$C$5:$G$100,MATCH($A10,'07_Raw_Balance_Sheet'!$A$5:$A$100,0),MATCH(B$4,'07_Raw_Balance_Sheet'!$C$4:$G$4,0)),"") -> -5004 | C10: =IFERROR(INDEX('07_Raw_Balance_Sheet'!$C$5:$G$100,MATCH($A10,'07_Raw_Balance_Sheet'!$A$5:$A$100,0),MATCH(C$4,'07_Raw_Balance_Sheet'!$C$4:$G$4,0)),"") -> -6037 | D10: =IFERROR(INDEX('07_Raw_Balance_Sheet'!$C$5:$G$100,MATCH($A10,'07_Raw_Balance_Sheet'!$A$5:$A$100,0),MATCH(D$4,'07_Raw_Balance_Sheet'!$C$4:$G$4,0)),"") -> -7093 | E10: =IFERROR(INDEX('07_Raw_Balance_Sheet'!$C$5:$G$100,MATCH($A10,'07_Raw_Balance_Sheet'!$A$5:$A$100,0),MATCH(E$4,'07_Raw_Balance_Sheet'!$C$4:$G$4,0)),"") -> -7401 | F10: =IFERROR(INDEX('07_Raw_Balance_Sheet'!$C$5:$G$100,MATCH($A10,'07_Raw_Balance_Sheet'!$A$5:$A$100,0),MATCH(F$4,'07_Raw_Balance_Sheet'!$C$4:$G$4,0)),"") -> -7521
A11: Loans, Net of Allowance | B11: =IFERROR(INDEX('07_Raw_Balance_Sheet'!$C$5:$G$100,MATCH($A11,'07_Raw_Balance_Sheet'!$A$5:$A$100,0),MATCH(B$4,'07_Raw_Balance_Sheet'!$C$4:$G$4,0)),"") -> 852773 | C11: =IFERROR(INDEX('07_Raw_Balance_Sheet'!$C$5:$G$100,MATCH($A11,'07_Raw_Balance_Sheet'!$A$5:$A$100,0),MATCH(C$4,'07_Raw_Balance_Sheet'!$C$4:$G$4,0)),"") -> 981380 | D11: =IFERROR(INDEX('07_Raw_Balance_Sheet'!$C$5:$G$100,MATCH($A11,'07_Raw_Balance_Sheet'!$A$5:$A$100,0),MATCH(D$4,'07_Raw_Balance_Sheet'!$C$4:$G$4,0)),"") -> 1042422 | E11: =IFERROR(INDEX('07_Raw_Balance_Sheet'!$C$5:$G$100,MATCH($A11,'07_Raw_Balance_Sheet'!$A$5:$A$100,0),MATCH(E$4,'07_Raw_Balance_Sheet'!$C$4:$G$4,0)),"") -> 1054881 | F11: =IFERROR(INDEX('07_Raw_Balance_Sheet'!$C$5:$G$100,MATCH($A11,'07_Raw_Balance_Sheet'!$A$5:$A$100,0),MATCH(F$4,'07_Raw_Balance_Sheet'!$C$4:$G$4,0)),"") -> 1077949
A12: Residential Mortgages | B12: =IFERROR(INDEX('07_Raw_Balance_Sheet'!$C$5:$G$100,MATCH($A12,'07_Raw_Balance_Sheet'!$A$5:$A$100,0),MATCH(B$4,'07_Raw_Balance_Sheet'!$C$4:$G$4,0)),"") -> 434501 | C12: =IFERROR(INDEX('07_Raw_Balance_Sheet'!$C$5:$G$100,MATCH($A12,'07_Raw_Balance_Sheet'!$A$5:$A$100,0),MATCH(C$4,'07_Raw_Balance_Sheet'!$C$4:$G$4,0)),"") -> 477544 | D12: =IFERROR(INDEX('07_Raw_Balance_Sheet'!$C$5:$G$100,MATCH($A12,'07_Raw_Balance_Sheet'!$A$5:$A$100,0),MATCH(D$4,'07_Raw_Balance_Sheet'!$C$4:$G$4,0)),"") -> 493413 | E12: =IFERROR(INDEX('07_Raw_Balance_Sheet'!$C$5:$G$100,MATCH($A12,'07_Raw_Balance_Sheet'!$A$5:$A$100,0),MATCH(E$4,'07_Raw_Balance_Sheet'!$C$4:$G$4,0)),"") -> 496529 | F12: =IFERROR(INDEX('07_Raw_Balance_Sheet'!$C$5:$G$100,MATCH($A12,'07_Raw_Balance_Sheet'!$A$5:$A$100,0),MATCH(F$4,'07_Raw_Balance_Sheet'!$C$4:$G$4,0)),"") -> 500879
A13: Personal Loans | B13: =IFERROR(INDEX('07_Raw_Balance_Sheet'!$C$5:$G$100,MATCH($A13,'07_Raw_Balance_Sheet'!$A$5:$A$100,0),MATCH(B$4,'07_Raw_Balance_Sheet'!$C$4:$G$4,0)),"") -> 98734 | C13: =IFERROR(INDEX('07_Raw_Balance_Sheet'!$C$5:$G$100,MATCH($A13,'07_Raw_Balance_Sheet'!$A$5:$A$100,0),MATCH(C$4,'07_Raw_Balance_Sheet'!$C$4:$G$4,0)),"") -> 108338 | D13: =IFERROR(INDEX('07_Raw_Balance_Sheet'!$C$5:$G$100,MATCH($A13,'07_Raw_Balance_Sheet'!$A$5:$A$100,0),MATCH(D$4,'07_Raw_Balance_Sheet'!$C$4:$G$4,0)),"") -> 115345 | E13: =IFERROR(INDEX('07_Raw_Balance_Sheet'!$C$5:$G$100,MATCH($A13,'07_Raw_Balance_Sheet'!$A$5:$A$100,0),MATCH(E$4,'07_Raw_Balance_Sheet'!$C$4:$G$4,0)),"") -> 115489 | F13: =IFERROR(INDEX('07_Raw_Balance_Sheet'!$C$5:$G$100,MATCH($A13,'07_Raw_Balance_Sheet'!$A$5:$A$100,0),MATCH(F$4,'07_Raw_Balance_Sheet'!$C$4:$G$4,0)),"") -> 117720
A14: Credit Cards | B14: =IFERROR(INDEX('07_Raw_Balance_Sheet'!$C$5:$G$100,MATCH($A14,'07_Raw_Balance_Sheet'!$A$5:$A$100,0),MATCH(B$4,'07_Raw_Balance_Sheet'!$C$4:$G$4,0)),"") -> 23035 | C14: =IFERROR(INDEX('07_Raw_Balance_Sheet'!$C$5:$G$100,MATCH($A14,'07_Raw_Balance_Sheet'!$A$5:$A$100,0),MATCH(C$4,'07_Raw_Balance_Sheet'!$C$4:$G$4,0)),"") -> 25565 | D14: =IFERROR(INDEX('07_Raw_Balance_Sheet'!$C$5:$G$100,MATCH($A14,'07_Raw_Balance_Sheet'!$A$5:$A$100,0),MATCH(D$4,'07_Raw_Balance_Sheet'!$C$4:$G$4,0)),"") -> 26789 | E14: =IFERROR(INDEX('07_Raw_Balance_Sheet'!$C$5:$G$100,MATCH($A14,'07_Raw_Balance_Sheet'!$A$5:$A$100,0),MATCH(E$4,'07_Raw_Balance_Sheet'!$C$4:$G$4,0)),"") -> 26489 | F14: =IFERROR(INDEX('07_Raw_Balance_Sheet'!$C$5:$G$100,MATCH($A14,'07_Raw_Balance_Sheet'!$A$5:$A$100,0),MATCH(F$4,'07_Raw_Balance_Sheet'!$C$4:$G$4,0)),"") -> 27702
A15: Business and Government Loans | B15: =IFERROR(INDEX('07_Raw_Balance_Sheet'!$C$5:$G$100,MATCH($A15,'07_Raw_Balance_Sheet'!$A$5:$A$100,0),MATCH(B$4,'07_Raw_Balance_Sheet'!$C$4:$G$4,0)),"") -> 309571 | C15: =IFERROR(INDEX('07_Raw_Balance_Sheet'!$C$5:$G$100,MATCH($A15,'07_Raw_Balance_Sheet'!$A$5:$A$100,0),MATCH(C$4,'07_Raw_Balance_Sheet'!$C$4:$G$4,0)),"") -> 360474 | D15: =IFERROR(INDEX('07_Raw_Balance_Sheet'!$C$5:$G$100,MATCH($A15,'07_Raw_Balance_Sheet'!$A$5:$A$100,0),MATCH(D$4,'07_Raw_Balance_Sheet'!$C$4:$G$4,0)),"") -> 397190 | E15: =IFERROR(INDEX('07_Raw_Balance_Sheet'!$C$5:$G$100,MATCH($A15,'07_Raw_Balance_Sheet'!$A$5:$A$100,0),MATCH(E$4,'07_Raw_Balance_Sheet'!$C$4:$G$4,0)),"") -> 406864 | F15: =IFERROR(INDEX('07_Raw_Balance_Sheet'!$C$5:$G$100,MATCH($A15,'07_Raw_Balance_Sheet'!$A$5:$A$100,0),MATCH(F$4,'07_Raw_Balance_Sheet'!$C$4:$G$4,0)),"") -> 422154
A16: Other Assets | B16: =IFERROR(INDEX('07_Raw_Balance_Sheet'!$C$5:$G$100,MATCH($A16,'07_Raw_Balance_Sheet'!$A$5:$A$100,0),MATCH(B$4,'07_Raw_Balance_Sheet'!$C$4:$G$4,0)),"") -> 81371 | C16: =IFERROR(INDEX('07_Raw_Balance_Sheet'!$C$5:$G$100,MATCH($A16,'07_Raw_Balance_Sheet'!$A$5:$A$100,0),MATCH(C$4,'07_Raw_Balance_Sheet'!$C$4:$G$4,0)),"") -> 92190 | D16: =IFERROR(INDEX('07_Raw_Balance_Sheet'!$C$5:$G$100,MATCH($A16,'07_Raw_Balance_Sheet'!$A$5:$A$100,0),MATCH(D$4,'07_Raw_Balance_Sheet'!$C$4:$G$4,0)),"") -> 112893 | E16: =IFERROR(INDEX('07_Raw_Balance_Sheet'!$C$5:$G$100,MATCH($A16,'07_Raw_Balance_Sheet'!$A$5:$A$100,0),MATCH(E$4,'07_Raw_Balance_Sheet'!$C$4:$G$4,0)),"") -> 115296 | F16: =IFERROR(INDEX('07_Raw_Balance_Sheet'!$C$5:$G$100,MATCH($A16,'07_Raw_Balance_Sheet'!$A$5:$A$100,0),MATCH(F$4,'07_Raw_Balance_Sheet'!$C$4:$G$4,0)),"") -> 111841
... A25: Loans and Acceptances | B25: =IFERROR(INDEX('07_Raw_Balance_Sheet'!$C$5:$G$100,MATCH($A25,'07_Raw_Balance_Sheet'!$A$5:$A$100,0),MATCH(B$4,'07_Raw_Balance_Sheet'!$C$4:$G$4,0)),"") -> 879522 | C25: =IFERROR(INDEX('07_Raw_Balance_Sheet'!$C$5:$G$100,MATCH($A25,'07_Raw_Balance_Sheet'!$A$5:$A$100,0),MATCH(C$4,'07_Raw_Balance_Sheet'!$C$4:$G$4,0)),"") -> 987452 | D25: =IFERROR(INDEX('07_Raw_Balance_Sheet'!$C$5:$G$100,MATCH($A25,'07_Raw_Balance_Sheet'!$A$5:$A$100,0),MATCH(D$4,'07_Raw_Balance_Sheet'!$C$4:$G$4,0)),"") -> 1049534 | E25: =IFERROR(INDEX('07_Raw_Balance_Sheet'!$C$5:$G$100,MATCH($A25,'07_Raw_Balance_Sheet'!$A$5:$A$100,0),MATCH(E$4,'07_Raw_Balance_Sheet'!$C$4:$G$4,0)),"") -> 1062298 | F25: =IFERROR(INDEX('07_Raw_Balance_Sheet'!$C$5:$G$100,MATCH($A25,'07_Raw_Balance_Sheet'!$A$5:$A$100,0),MATCH(F$4,'07_Raw_Balance_Sheet'!$C$4:$G$4,0)),"") -> 1085510

Sheet 13_STD_Credit_Risk
A1: STANDARDIZED CREDIT RISK
A4: Metric | B4: FY2023 | C4: FY2024 | D4: FY2025 | E4: Q1 2026 | F4: Q2 2026
A5: Total PCL | B5: =IFERROR(INDEX('08_Raw_Credit_Quality'!$C$5:$G$100,MATCH($A5,'08_Raw_Credit_Quality'!$A$5:$A$100,0),MATCH(B$4,'08_Raw_Credit_Quality'!$C$4:$G$4,0)),"") -> 2468 | C5: =IFERROR(INDEX('08_Raw_Credit_Quality'!$C$5:$G$100,MATCH($A5,'08_Raw_Credit_Quality'!$A$5:$A$100,0),MATCH(C$4,'08_Raw_Credit_Quality'!$C$4:$G$4,0)),"") -> 3232 | D5: =IFERROR(INDEX('08_Raw_Credit_Quality'!$C$5:$G$100,MATCH($A5,'08_Raw_Credit_Quality'!$A$5:$A$100,0),MATCH(D$4,'08_Raw_Credit_Quality'!$C$4:$G$4,0)),"") -> 4362 | E5: =IFERROR(INDEX('08_Raw_Credit_Quality'!$C$5:$G$100,MATCH($A5,'08_Raw_Credit_Quality'!$A$5:$A$100,0),MATCH(E$4,'08_Raw_Credit_Quality'!$C$4:$G$4,0)),"") -> 1090 | F5: =IFERROR(INDEX('08_Raw_Credit_Quality'!$C$5:$G$100,MATCH($A5,'08_Raw_Credit_Quality'!$A$5:$A$100,0),MATCH(F$4,'08_Raw_Credit_Quality'!$C$4:$G$4,0)),"") -> 912
A6: PCL on Performing Loans | B6: =IFERROR(INDEX('08_Raw_Credit_Quality'!$C$5:$G$100,MATCH($A6,'08_Raw_Credit_Quality'!$A$5:$A$100,0),MATCH(B$4,'08_Raw_Credit_Quality'!$C$4:$G$4,0)),"") -> 660 | C6: =IFERROR(INDEX('08_Raw_Credit_Quality'!$C$5:$G$100,MATCH($A6,'08_Raw_Credit_Quality'!$A$5:$A$100,0),MATCH(C$4,'08_Raw_Credit_Quality'!$C$4:$G$4,0)),"") -> 627 | D6: =IFERROR(INDEX('08_Raw_Credit_Quality'!$C$5:$G$100,MATCH($A6,'08_Raw_Credit_Quality'!$A$5:$A$100,0),MATCH(D$4,'08_Raw_Credit_Quality'!$C$4:$G$4,0)),"") -> 622 | E6: =IFERROR(INDEX('08_Raw_Credit_Quality'!$C$5:$G$100,MATCH($A6,'08_Raw_Credit_Quality'!$A$5:$A$100,0),MATCH(E$4,'08_Raw_Credit_Quality'!$C$4:$G$4,0)),"") -> 28 | F6: =IFERROR(INDEX('08_Raw_Credit_Quality'!$C$5:$G$100,MATCH($A6,'08_Raw_Credit_Quality'!$A$5:$A$100,0),MATCH(F$4,'08_Raw_Credit_Quality'!$C$4:$G$4,0)),"") -> 18
A7: PCL on Impaired Loans | B7: =IFERROR(INDEX('08_Raw_Credit_Quality'!$C$5:$G$100,MATCH($A7,'08_Raw_Credit_Quality'!$A$5:$A$100,0),MATCH(B$4,'08_Raw_Credit_Quality'!$C$4:$G$4,0)),"") -> 1836 | C7: =IFERROR(INDEX('08_Raw_Credit_Quality'!$C$5:$G$100,MATCH($A7,'08_Raw_Credit_Quality'!$A$5:$A$100,0),MATCH(C$4,'08_Raw_Credit_Quality'!$C$4:$G$4,0)),"") -> 2620 | D7: =IFERROR(INDEX('08_Raw_Credit_Quality'!$C$5:$G$100,MATCH($A7,'08_Raw_Credit_Quality'!$A$5:$A$100,0),MATCH(D$4,'08_Raw_Credit_Quality'!$C$4:$G$4,0)),"") -> 3734 | E7: =IFERROR(INDEX('08_Raw_Credit_Quality'!$C$5:$G$100,MATCH($A7,'08_Raw_Credit_Quality'!$A$5:$A$100,0),MATCH(E$4,'08_Raw_Credit_Quality'!$C$4:$G$4,0)),"") -> 1068 | F7: =IFERROR(INDEX('08_Raw_Credit_Quality'!$C$5:$G$100,MATCH($A7,'08_Raw_Credit_Quality'!$A$5:$A$100,0),MATCH(F$4,'08_Raw_Credit_Quality'!$C$4:$G$4,0)),"") -> 899
A8: PCL on Loans Ratio | B8: =IFERROR(INDEX('08_Raw_Credit_Quality'!$C$5:$G$100,MATCH($A8,'08_Raw_Credit_Quality'!$A$5:$A$100,0),MATCH(B$4,'08_Raw_Credit_Quality'!$C$4:$G$4,0)),"") -> 0.0029 | C8: =IFERROR(INDEX('08_Raw_Credit_Quality'!$C$5:$G$100,MATCH($A8,'08_Raw_Credit_Quality'!$A$5:$A$100,0),MATCH(C$4,'08_Raw_Credit_Quality'!$C$4:$G$4,0)),"") -> 0.0035 | D8: =IFERROR(INDEX('08_Raw_Credit_Quality'!$C$5:$G$100,MATCH($A8,'08_Raw_Credit_Quality'!$A$5:$A$100,0),MATCH(D$4,'08_Raw_Credit_Quality'!$C$4:$G$4,0)),"") -> 0.0043 | E8: =IFERROR(INDEX('08_Raw_Credit_Quality'!$C$5:$G$100,MATCH($A8,'08_Raw_Credit_Quality'!$A$5:$A$100,0),MATCH(E$4,'08_Raw_Credit_Quality'!$C$4:$G$4,0)),"") -> 0.0041 | F8: =IFERROR(INDEX('08_Raw_Credit_Quality'!$C$5:$G$100,MATCH($A8,'08_Raw_Credit_Quality'!$A$5:$A$100,0),MATCH(F$4,'08_Raw_Credit_Quality'!$C$4:$G$4,0)),"") -> 0.0035
A9: Gross Impaired Loans | B9: =IFERROR(INDEX('08_Raw_Credit_Quality'!$C$5:$G$100,MATCH($A9,'08_Raw_Credit_Quality'!$A$5:$A$100,0),MATCH(B$4,'08_Raw_Credit_Quality'!$C$4:$G$4,0)),"") -> 3704 | C9: =IFERROR(INDEX('08_Raw_Credit_Quality'!$C$5:$G$100,MATCH($A9,'08_Raw_Credit_Quality'!$A$5:$A$100,0),MATCH(C$4,'08_Raw_Credit_Quality'!$C$4:$G$4,0)),"") -> 5867 | D9: =IFERROR(INDEX('08_Raw_Credit_Quality'!$C$5:$G$100,MATCH($A9,'08_Raw_Credit_Quality'!$A$5:$A$100,0),MATCH(D$4,'08_Raw_Credit_Quality'!$C$4:$G$4,0)),"") -> 8682 | E9: =IFERROR(INDEX('08_Raw_Credit_Quality'!$C$5:$G$100,MATCH($A9,'08_Raw_Credit_Quality'!$A$5:$A$100,0),MATCH(E$4,'08_Raw_Credit_Quality'!$C$4:$G$4,0)),"") -> 9167 | F9: =IFERROR(INDEX('08_Raw_Credit_Quality'!$C$5:$G$100,MATCH($A9,'08_Raw_Credit_Quality'!$A$5:$A$100,0),MATCH(F$4,'08_Raw_Credit_Quality'!$C$4:$G$4,0)),"") -> 9790
A10: GIL Ratio | B10: =IFERROR(INDEX('08_Raw_Credit_Quality'!$C$5:$G$100,MATCH($A10,'08_Raw_Credit_Quality'!$A$5:$A$100,0),MATCH(B$4,'08_Raw_Credit_Quality'!$C$4:$G$4,0)),"") -> 0.0042 | C10: =IFERROR(INDEX('08_Raw_Credit_Quality'!$C$5:$G$100,MATCH($A10,'08_Raw_Credit_Quality'!$A$5:$A$100,0),MATCH(C$4,'08_Raw_Credit_Quality'!$C$4:$G$4,0)),"") -> 0.0059 | D10: =IFERROR(INDEX('08_Raw_Credit_Quality'!$C$5:$G$100,MATCH($A10,'08_Raw_Credit_Quality'!$A$5:$A$100,0),MATCH(D$4,'08_Raw_Credit_Quality'!$C$4:$G$4,0)),"") -> 0.0083 | E10: =IFERROR(INDEX('08_Raw_Credit_Quality'!$C$5:$G$100,MATCH($A10,'08_Raw_Credit_Quality'!$A$5:$A$100,0),MATCH(E$4,'08_Raw_Credit_Quality'!$C$4:$G$4,0)),"") -> 0.0086 | F10: =IFERROR(INDEX('08_Raw_Credit_Quality'!$C$5:$G$100,MATCH($A10,'08_Raw_Credit_Quality'!$A$5:$A$100,0),MATCH(F$4,'08_Raw_Credit_Quality'!$C$4:$G$4,0)),"") -> 0.009
A11: Allowance for Credit Losses | B11: =IFERROR(INDEX('08_Raw_Credit_Quality'!$C$5:$G$100,MATCH($A11,'08_Raw_Credit_Quality'!$A$5:$A$100,0),MATCH(B$4,'08_Raw_Credit_Quality'!$C$4:$G$4,0)),"") -> 5366 | C11: =IFERROR(INDEX('08_Raw_Credit_Quality'!$C$5:$G$100,MATCH($A11,'08_Raw_Credit_Quality'!$A$5:$A$100,0),MATCH(C$4,'08_Raw_Credit_Quality'!$C$4:$G$4,0)),"") -> 6364 | D11: =IFERROR(INDEX('08_Raw_Credit_Quality'!$C$5:$G$100,MATCH($A11,'08_Raw_Credit_Quality'!$A$5:$A$100,0),MATCH(D$4,'08_Raw_Credit_Quality'!$C$4:$G$4,0)),"") -> 7470 | E11: =IFERROR(INDEX('08_Raw_Credit_Quality'!$C$5:$G$100,MATCH($A11,'08_Raw_Credit_Quality'!$A$5:$A$100,0),MATCH(E$4,'08_Raw_Credit_Quality'!$C$4:$G$4,0)),"") -> 7767 | F11: =IFERROR(INDEX('08_Raw_Credit_Quality'!$C$5:$G$100,MATCH($A11,'08_Raw_Credit_Quality'!$A$5:$A$100,0),MATCH(F$4,'08_Raw_Credit_Quality'!$C$4:$G$4,0)),"") -> 7819
A12: ACL on Performing Loans | B12: =IFERROR(INDEX('08_Raw_Credit_Quality'!$C$5:$G$100,MATCH($A12,'08_Raw_Credit_Quality'!$A$5:$A$100,0),MATCH(B$4,'08_Raw_Credit_Quality'!$C$4:$G$4,0)),"") -> 4200 | C12: =IFERROR(INDEX('08_Raw_Credit_Quality'!$C$5:$G$100,MATCH($A12,'08_Raw_Credit_Quality'!$A$5:$A$100,0),MATCH(C$4,'08_Raw_Credit_Quality'!$C$4:$G$4,0)),"") -> 4836 | D12: =IFERROR(INDEX('08_Raw_Credit_Quality'!$C$5:$G$100,MATCH($A12,'08_Raw_Credit_Quality'!$A$5:$A$100,0),MATCH(D$4,'08_Raw_Credit_Quality'!$C$4:$G$4,0)),"") -> 5473 | E12: =IFERROR(INDEX('08_Raw_Credit_Quality'!$C$5:$G$100,MATCH($A12,'08_Raw_Credit_Quality'!$A$5:$A$100,0),MATCH(E$4,'08_Raw_Credit_Quality'!$C$4:$G$4,0)),"") -> 5471 | F12: =IFERROR(INDEX('08_Raw_Credit_Quality'!$C$5:$G$100,MATCH($A12,'08_Raw_Credit_Quality'!$A$5:$A$100,0),MATCH(F$4,'08_Raw_Credit_Quality'!$C$4:$G$4,0)),"") -> 5487
A13: ACL on Impaired Loans | B13: =IFERROR(INDEX('08_Raw_Credit_Quality'!$C$5:$G$100,MATCH($A13,'08_Raw_Credit_Quality'!$A$5:$A$100,0),MATCH(B$4,'08_Raw_Credit_Quality'!$C$4:$G$4,0)),"") -> 1148 | C13: =IFERROR(INDEX('08_Raw_Credit_Quality'!$C$5:$G$100,MATCH($A13,'08_Raw_Credit_Quality'!$A$5:$A$100,0),MATCH(C$4,'08_Raw_Credit_Quality'!$C$4:$G$4,0)),"") -> 1516 | D13: =IFERROR(INDEX('08_Raw_Credit_Quality'!$C$5:$G$100,MATCH($A13,'08_Raw_Credit_Quality'!$A$5:$A$100,0),MATCH(D$4,'08_Raw_Credit_Quality'!$C$4:$G$4,0)),"") -> 1986 | E13: =IFERROR(INDEX('08_Raw_Credit_Quality'!$C$5:$G$100,MATCH($A13,'08_Raw_Credit_Quality'!$A$5:$A$100,0),MATCH(E$4,'08_Raw_Credit_Quality'!$C$4:$G$4,0)),"") -> 2281 | F13: =IFERROR(INDEX('08_Raw_Credit_Quality'!$C$5:$G$100,MATCH($A13,'08_Raw_Credit_Quality'!$A$5:$A$100,0),MATCH(F$4,'08_Raw_Credit_Quality'!$C$4:$G$4,0)),"") -> 2317
A14: ACL-to-Loans Ratio | B14: =IFERROR(INDEX('08_Raw_Credit_Quality'!$C$5:$G$100,MATCH($A14,'08_Raw_Credit_Quality'!$A$5:$A$100,0),MATCH(B$4,'08_Raw_Credit_Quality'!$C$4:$G$4,0)),"") -> 0.0061 | C14: =IFERROR(INDEX('08_Raw_Credit_Quality'!$C$5:$G$100,MATCH($A14,'08_Raw_Credit_Quality'!$A$5:$A$100,0),MATCH(C$4,'08_Raw_Credit_Quality'!$C$4:$G$4,0)),"") -> 0.0064 | D14: =IFERROR(INDEX('08_Raw_Credit_Quality'!$C$5:$G$100,MATCH($A14,'08_Raw_Credit_Quality'!$A$5:$A$100,0),MATCH(D$4,'08_Raw_Credit_Quality'!$C$4:$G$4,0)),"") -> 0.0071 | E14: =IFERROR(INDEX('08_Raw_Credit_Quality'!$C$5:$G$100,MATCH($A14,'08_Raw_Credit_Quality'!$A$5:$A$100,0),MATCH(E$4,'08_Raw_Credit_Quality'!$C$4:$G$4,0)),"") -> 0.0073 | F14: =IFERROR(INDEX('08_Raw_Credit_Quality'!$C$5:$G$100,MATCH($A14,'08_Raw_Credit_Quality'!$A$5:$A$100,0),MATCH(F$4,'08_Raw_Credit_Quality'!$C$4:$G$4,0)),"") -> 0.0072
A15: Stage 3 ACL / GIL | B15: =IFERROR(INDEX('08_Raw_Credit_Quality'!$C$5:$G$100,MATCH($A15,'08_Raw_Credit_Quality'!$A$5:$A$100,0),MATCH(B$4,'08_Raw_Credit_Quality'!$C$4:$G$4,0)),"") -> 0.31 | C15: =IFERROR(INDEX('08_Raw_Credit_Quality'!$C$5:$G$100,MATCH($A15,'08_Raw_Credit_Quality'!$A$5:$A$100,0),MATCH(C$4,'08_Raw_Credit_Quality'!$C$4:$G$4,0)),"") -> 0.2585 | D15: =IFERROR(INDEX('08_Raw_Credit_Quality'!$C$5:$G$100,MATCH($A15,'08_Raw_Credit_Quality'!$A$5:$A$100,0),MATCH(D$4,'08_Raw_Credit_Quality'!$C$4:$G$4,0)),"") -> 0.2288 | E15: =IFERROR(INDEX('08_Raw_Credit_Quality'!$C$5:$G$100,MATCH($A15,'08_Raw_Credit_Quality'!$A$5:$A$100,0),MATCH(E$4,'08_Raw_Credit_Quality'!$C$4:$G$4,0)),"") -> 0.2488 | F15: =IFERROR(INDEX('08_Raw_Credit_Quality'!$C$5:$G$100,MATCH($A15,'08_Raw_Credit_Quality'!$A$5:$A$100,0),MATCH(F$4,'08_Raw_Credit_Quality'!$C$4:$G$4,0)),"") -> 0.2367
A16: Net Write-Off Ratio | B16: =IFERROR(INDEX('08_Raw_Credit_Quality'!$C$5:$G$100,MATCH($A16,'08_Raw_Credit_Quality'!$A$5:$A$100,0),MATCH(B$4,'08_Raw_Credit_Quality'!$C$4:$G$4,0)),"") -> 0.0014 | C16: =IFERROR(INDEX('08_Raw_Credit_Quality'!$C$5:$G$100,MATCH($A16,'08_Raw_Credit_Quality'!$A$5:$A$100,0),MATCH(C$4,'08_Raw_Credit_Quality'!$C$4:$G$4,0)),"") -> 0.0022 | D16: =IFERROR(INDEX('08_Raw_Credit_Quality'!$C$5:$G$100,MATCH($A16,'08_Raw_Credit_Quality'!$A$5:$A$100,0),MATCH(D$4,'08_Raw_Credit_Quality'!$C$4:$G$4,0)),"") -> 0.0028 | E16: =IFERROR(INDEX('08_Raw_Credit_Quality'!$C$5:$G$100,MATCH($A16,'08_Raw_Credit_Quality'!$A$5:$A$100,0),MATCH(E$4,'08_Raw_Credit_Quality'!$C$4:$G$4,0)),"") -> 0.0024 | F16: =IFERROR(INDEX('08_Raw_Credit_Quality'!$C$5:$G$100,MATCH($A16,'08_Raw_Credit_Quality'!$A$5:$A$100,0),MATCH(F$4,'08_Raw_Credit_Quality'!$C$4:$G$4,0)),"") -> 0.0028

Sheet 14_STD_Capital_Liquidity
A1: STANDARDIZED CAPITAL AND LIQUIDITY
A4: Metric | B4: FY2023 | C4: FY2024 | D4: FY2025 | E4: Q1 2026 | F4: Q2 2026
A5: CET1 Capital | B5: =IFERROR(INDEX('09_Raw_Capital_Liquidity'!$C$5:$G$100,MATCH($A5,'09_Raw_Capital_Liquidity'!$A$5:$A$100,0),MATCH(B$4,'09_Raw_Capital_Liquidity'!$C$4:$G$4,0)),"") -> 86611 | C5: =IFERROR(INDEX('09_Raw_Capital_Liquidity'!$C$5:$G$100,MATCH($A5,'09_Raw_Capital_Liquidity'!$A$5:$A$100,0),MATCH(C$4,'09_Raw_Capital_Liquidity'!$C$4:$G$4,0)),"") -> 88936 | D5: =IFERROR(INDEX('09_Raw_Capital_Liquidity'!$C$5:$G$100,MATCH($A5,'09_Raw_Capital_Liquidity'!$A$5:$A$100,0),MATCH(D$4,'09_Raw_Capital_Liquidity'!$C$4:$G$4,0)),"") -> 98748 | E5: =IFERROR(INDEX('09_Raw_Capital_Liquidity'!$C$5:$G$100,MATCH($A5,'09_Raw_Capital_Liquidity'!$A$5:$A$100,0),MATCH(E$4,'09_Raw_Capital_Liquidity'!$C$4:$G$4,0)),"") -> 100415 | F5: =IFERROR(INDEX('09_Raw_Capital_Liquidity'!$C$5:$G$100,MATCH($A5,'09_Raw_Capital_Liquidity'!$A$5:$A$100,0),MATCH(F$4,'09_Raw_Capital_Liquidity'!$C$4:$G$4,0)),"") -> 101313
A6: Tier 1 Capital | B6: =IFERROR(INDEX('09_Raw_Capital_Liquidity'!$C$5:$G$100,MATCH($A6,'09_Raw_Capital_Liquidity'!$A$5:$A$100,0),MATCH(B$4,'09_Raw_Capital_Liquidity'!$C$4:$G$4,0)),"") -> 93904 | C6: =IFERROR(INDEX('09_Raw_Capital_Liquidity'!$C$5:$G$100,MATCH($A6,'09_Raw_Capital_Liquidity'!$A$5:$A$100,0),MATCH(C$4,'09_Raw_Capital_Liquidity'!$C$4:$G$4,0)),"") -> 97952 | D6: =IFERROR(INDEX('09_Raw_Capital_Liquidity'!$C$5:$G$100,MATCH($A6,'09_Raw_Capital_Liquidity'!$A$5:$A$100,0),MATCH(D$4,'09_Raw_Capital_Liquidity'!$C$4:$G$4,0)),"") -> 110393 | E6: =IFERROR(INDEX('09_Raw_Capital_Liquidity'!$C$5:$G$100,MATCH($A6,'09_Raw_Capital_Liquidity'!$A$5:$A$100,0),MATCH(E$4,'09_Raw_Capital_Liquidity'!$C$4:$G$4,0)),"") -> 111549 | F6: =IFERROR(INDEX('09_Raw_Capital_Liquidity'!$C$5:$G$100,MATCH($A6,'09_Raw_Capital_Liquidity'!$A$5:$A$100,0),MATCH(F$4,'09_Raw_Capital_Liquidity'!$C$4:$G$4,0)),"") -> 112453
A7: Total Capital | B7: =IFERROR(INDEX('09_Raw_Capital_Liquidity'!$C$5:$G$100,MATCH($A7,'09_Raw_Capital_Liquidity'!$A$5:$A$100,0),MATCH(B$4,'09_Raw_Capital_Liquidity'!$C$4:$G$4,0)),"") -> 104952 | C7: =IFERROR(INDEX('09_Raw_Capital_Liquidity'!$C$5:$G$100,MATCH($A7,'09_Raw_Capital_Liquidity'!$A$5:$A$100,0),MATCH(C$4,'09_Raw_Capital_Liquidity'!$C$4:$G$4,0)),"") -> 110487 | D7: =IFERROR(INDEX('09_Raw_Capital_Liquidity'!$C$5:$G$100,MATCH($A7,'09_Raw_Capital_Liquidity'!$A$5:$A$100,0),MATCH(D$4,'09_Raw_Capital_Liquidity'!$C$4:$G$4,0)),"") -> 122399 | E7: =IFERROR(INDEX('09_Raw_Capital_Liquidity'!$C$5:$G$100,MATCH($A7,'09_Raw_Capital_Liquidity'!$A$5:$A$100,0),MATCH(E$4,'09_Raw_Capital_Liquidity'!$C$4:$G$4,0)),"") -> 123732 | F7: =IFERROR(INDEX('09_Raw_Capital_Liquidity'!$C$5:$G$100,MATCH($A7,'09_Raw_Capital_Liquidity'!$A$5:$A$100,0),MATCH(F$4,'09_Raw_Capital_Liquidity'!$C$4:$G$4,0)),"") -> 126286
A8: Total Risk-Weighted Assets | B8: =IFERROR(INDEX('09_Raw_Capital_Liquidity'!$C$5:$G$100,MATCH($A8,'09_Raw_Capital_Liquidity'!$A$5:$A$100,0),MATCH(B$4,'09_Raw_Capital_Liquidity'!$C$4:$G$4,0)),"") -> 596223 | C8: =IFERROR(INDEX('09_Raw_Capital_Liquidity'!$C$5:$G$100,MATCH($A8,'09_Raw_Capital_Liquidity'!$A$5:$A$100,0),MATCH(C$4,'09_Raw_Capital_Liquidity'!$C$4:$G$4,0)),"") -> 672282 | D8: =IFERROR(INDEX('09_Raw_Capital_Liquidity'!$C$5:$G$100,MATCH($A8,'09_Raw_Capital_Liquidity'!$A$5:$A$100,0),MATCH(D$4,'09_Raw_Capital_Liquidity'!$C$4:$G$4,0)),"") -> 730225 | E8: =IFERROR(INDEX('09_Raw_Capital_Liquidity'!$C$5:$G$100,MATCH($A8,'09_Raw_Capital_Liquidity'!$A$5:$A$100,0),MATCH(E$4,'09_Raw_Capital_Liquidity'!$C$4:$G$4,0)),"") -> 734693 | F8: =IFERROR(INDEX('09_Raw_Capital_Liquidity'!$C$5:$G$100,MATCH($A8,'09_Raw_Capital_Liquidity'!$A$5:$A$100,0),MATCH(F$4,'09_Raw_Capital_Liquidity'!$C$4:$G$4,0)),"") -> 748590
A9: CET1 Ratio | B9: =IFERROR(INDEX('09_Raw_Capital_Liquidity'!$C$5:$G$100,MATCH($A9,'09_Raw_Capital_Liquidity'!$A$5:$A$100,0),MATCH(B$4,'09_Raw_Capital_Liquidity'!$C$4:$G$4,0)),"") -> 0.145 | C9: =IFERROR(INDEX('09_Raw_Capital_Liquidity'!$C$5:$G$100,MATCH($A9,'09_Raw_Capital_Liquidity'!$A$5:$A$100,0),MATCH(C$4,'09_Raw_Capital_Liquidity'!$C$4:$G$4,0)),"") -> 0.132 | D9: =IFERROR(INDEX('09_Raw_Capital_Liquidity'!$C$5:$G$100,MATCH($A9,'09_Raw_Capital_Liquidity'!$A$5:$A$100,0),MATCH(D$4,'09_Raw_Capital_Liquidity'!$C$4:$G$4,0)),"") -> 0.135 | E9: =IFERROR(INDEX('09_Raw_Capital_Liquidity'!$C$5:$G$100,MATCH($A9,'09_Raw_Capital_Liquidity'!$A$5:$A$100,0),MATCH(E$4,'09_Raw_Capital_Liquidity'!$C$4:$G$4,0)),"") -> 0.137 | F9: =IFERROR(INDEX('09_Raw_Capital_Liquidity'!$C$5:$G$100,MATCH($A9,'09_Raw_Capital_Liquidity'!$A$5:$A$100,0),MATCH(F$4,'09_Raw_Capital_Liquidity'!$C$4:$G$4,0)),"") -> 0.135
A10: Tier 1 Capital Ratio | B10: =IFERROR(INDEX('09_Raw_Capital_Liquidity'!$C$5:$G$100,MATCH($A10,'09_Raw_Capital_Liquidity'!$A$5:$A$100,0),MATCH(B$4,'09_Raw_Capital_Liquidity'!$C$4:$G$4,0)),"") -> 0.157 | C10: =IFERROR(INDEX('09_Raw_Capital_Liquidity'!$C$5:$G$100,MATCH($A10,'09_Raw_Capital_Liquidity'!$A$5:$A$100,0),MATCH(C$4,'09_Raw_Capital_Liquidity'!$C$4:$G$4,0)),"") -> 0.146 | D10: =IFERROR(INDEX('09_Raw_Capital_Liquidity'!$C$5:$G$100,MATCH($A10,'09_Raw_Capital_Liquidity'!$A$5:$A$100,0),MATCH(D$4,'09_Raw_Capital_Liquidity'!$C$4:$G$4,0)),"") -> 0.151 | E10: =IFERROR(INDEX('09_Raw_Capital_Liquidity'!$C$5:$G$100,MATCH($A10,'09_Raw_Capital_Liquidity'!$A$5:$A$100,0),MATCH(E$4,'09_Raw_Capital_Liquidity'!$C$4:$G$4,0)),"") -> 0.152 | F10: =IFERROR(INDEX('09_Raw_Capital_Liquidity'!$C$5:$G$100,MATCH($A10,'09_Raw_Capital_Liquidity'!$A$5:$A$100,0),MATCH(F$4,'09_Raw_Capital_Liquidity'!$C$4:$G$4,0)),"") -> 0.15
A11: Total Capital Ratio | B11: =IFERROR(INDEX('09_Raw_Capital_Liquidity'!$C$5:$G$100,MATCH($A11,'09_Raw_Capital_Liquidity'!$A$5:$A$100,0),MATCH(B$4,'09_Raw_Capital_Liquidity'!$C$4:$G$4,0)),"") -> 0.176 | C11: =IFERROR(INDEX('09_Raw_Capital_Liquidity'!$C$5:$G$100,MATCH($A11,'09_Raw_Capital_Liquidity'!$A$5:$A$100,0),MATCH(C$4,'09_Raw_Capital_Liquidity'!$C$4:$G$4,0)),"") -> 0.164 | D11: =IFERROR(INDEX('09_Raw_Capital_Liquidity'!$C$5:$G$100,MATCH($A11,'09_Raw_Capital_Liquidity'!$A$5:$A$100,0),MATCH(D$4,'09_Raw_Capital_Liquidity'!$C$4:$G$4,0)),"") -> 0.168 | E11: =IFERROR(INDEX('09_Raw_Capital_Liquidity'!$C$5:$G$100,MATCH($A11,'09_Raw_Capital_Liquidity'!$A$5:$A$100,0),MATCH(E$4,'09_Raw_Capital_Liquidity'!$C$4:$G$4,0)),"") -> 0.168 | F11: =IFERROR(INDEX('09_Raw_Capital_Liquidity'!$C$5:$G$100,MATCH($A11,'09_Raw_Capital_Liquidity'!$A$5:$A$100,0),MATCH(F$4,'09_Raw_Capital_Liquidity'!$C$4:$G$4,0)),"") -> 0.169
A12: Leverage Ratio | B12: =IFERROR(INDEX('09_Raw_Capital_Liquidity'!$C$5:$G$100,MATCH($A12,'09_Raw_Capital_Liquidity'!$A$5:$A$100,0),MATCH(B$4,'09_Raw_Capital_Liquidity'!$C$4:$G$4,0)),"") -> 0.043 | C12: =IFERROR(INDEX('09_Raw_Capital_Liquidity'!$C$5:$G$100,MATCH($A12,'09_Raw_Capital_Liquidity'!$A$5:$A$100,0),MATCH(C$4,'09_Raw_Capital_Liquidity'!$C$4:$G$4,0)),"") -> 0.042 | D12: =IFERROR(INDEX('09_Raw_Capital_Liquidity'!$C$5:$G$100,MATCH($A12,'09_Raw_Capital_Liquidity'!$A$5:$A$100,0),MATCH(D$4,'09_Raw_Capital_Liquidity'!$C$4:$G$4,0)),"") -> 0.044 | E12: =IFERROR(INDEX('09_Raw_Capital_Liquidity'!$C$5:$G$100,MATCH($A12,'09_Raw_Capital_Liquidity'!$A$5:$A$100,0),MATCH(E$4,'09_Raw_Capital_Liquidity'!$C$4:$G$4,0)),"") -> 0.044 | F12: =IFERROR(INDEX('09_Raw_Capital_Liquidity'!$C$5:$G$100,MATCH($A12,'09_Raw_Capital_Liquidity'!$A$5:$A$100,0),MATCH(F$4,'09_Raw_Capital_Liquidity'!$C$4:$G$4,0)),"") -> 0.043
A13: Liquidity Coverage Ratio | B13: =IFERROR(INDEX('09_Raw_Capital_Liquidity'!$C$5:$G$100,MATCH($A13,'09_Raw_Capital_Liquidity'!$A$5:$A$100,0),MATCH(B$4,'09_Raw_Capital_Liquidity'!$C$4:$G$4,0)),"") -> 0 | C13: =IFERROR(INDEX('09_Raw_Capital_Liquidity'!$C$5:$G$100,MATCH($A13,'09_Raw_Capital_Liquidity'!$A$5:$A$100,0),MATCH(C$4,'09_Raw_Capital_Liquidity'!$C$4:$G$4,0)),"") -> 1.28 | D13: =IFERROR(INDEX('09_Raw_Capital_Liquidity'!$C$5:$G$100,MATCH($A13,'09_Raw_Capital_Liquidity'!$A$5:$A$100,0),MATCH(D$4,'09_Raw_Capital_Liquidity'!$C$4:$G$4,0)),"") -> 1.27 | E13: =IFERROR(INDEX('09_Raw_Capital_Liquidity'!$C$5:$G$100,MATCH($A13,'09_Raw_Capital_Liquidity'!$A$5:$A$100,0),MATCH(E$4,'09_Raw_Capital_Liquidity'!$C$4:$G$4,0)),"") -> 1.24 | F13: =IFERROR(INDEX('09_Raw_Capital_Liquidity'!$C$5:$G$100,MATCH($A13,'09_Raw_Capital_Liquidity'!$A$5:$A$100,0),MATCH(F$4,'09_Raw_Capital_Liquidity'!$C$4:$G$4,0)),"") -> 1.26
A14: Net Stable Funding Ratio | B14: =IFERROR(INDEX('09_Raw_Capital_Liquidity'!$C$5:$G$100,MATCH($A14,'09_Raw_Capital_Liquidity'!$A$5:$A$100,0),MATCH(B$4,'09_Raw_Capital_Liquidity'!$C$4:$G$4,0)),"") -> 0 | C14: =IFERROR(INDEX('09_Raw_Capital_Liquidity'!$C$5:$G$100,MATCH($A14,'09_Raw_Capital_Liquidity'!$A$5:$A$100,0),MATCH(C$4,'09_Raw_Capital_Liquidity'!$C$4:$G$4,0)),"") -> 1.14 | D14: =IFERROR(INDEX('09_Raw_Capital_Liquidity'!$C$5:$G$100,MATCH($A14,'09_Raw_Capital_Liquidity'!$A$5:$A$100,0),MATCH(D$4,'09_Raw_Capital_Liquidity'!$C$4:$G$4,0)),"") -> 1.12 | E14: =IFERROR(INDEX('09_Raw_Capital_Liquidity'!$C$5:$G$100,MATCH($A14,'09_Raw_Capital_Liquidity'!$A$5:$A$100,0),MATCH(E$4,'09_Raw_Capital_Liquidity'!$C$4:$G$4,0)),"") -> 1.11 | F14: =IFERROR(INDEX('09_Raw_Capital_Liquidity'!$C$5:$G$100,MATCH($A14,'09_Raw_Capital_Liquidity'!$A$5:$A$100,0),MATCH(F$4,'09_Raw_Capital_Liquidity'!$C$4:$G$4,0)),"") -> 1.11
A15: Common Shareholders' Equity | B15: =IFERROR(INDEX('09_Raw_Capital_Liquidity'!$C$5:$G$100,MATCH($A15,'09_Raw_Capital_Liquidity'!$A$5:$A$100,0),MATCH(B$4,'09_Raw_Capital_Liquidity'!$C$4:$G$4,0)),"") -> 107734 | C15: =IFERROR(INDEX('09_Raw_Capital_Liquidity'!$C$5:$G$100,MATCH($A15,'09_Raw_Capital_Liquidity'!$A$5:$A$100,0),MATCH(C$4,'09_Raw_Capital_Liquidity'!$C$4:$G$4,0)),"") -> 118058 | D15: =IFERROR(INDEX('09_Raw_Capital_Liquidity'!$C$5:$G$100,MATCH($A15,'09_Raw_Capital_Liquidity'!$A$5:$A$100,0),MATCH(D$4,'09_Raw_Capital_Liquidity'!$C$4:$G$4,0)),"") -> 127417 | E15: =IFERROR(INDEX('09_Raw_Capital_Liquidity'!$C$5:$G$100,MATCH($A15,'09_Raw_Capital_Liquidity'!$A$5:$A$100,0),MATCH(E$4,'09_Raw_Capital_Liquidity'!$C$4:$G$4,0)),"") -> 128670 | F15: =IFERROR(INDEX('09_Raw_Capital_Liquidity'!$C$5:$G$100,MATCH($A15,'09_Raw_Capital_Liquidity'!$A$5:$A$100,0),MATCH(F$4,'09_Raw_Capital_Liquidity'!$C$4:$G$4,0)),"") -> 129579
A16: Dividends Per Common Share | B16: =IFERROR(INDEX('09_Raw_Capital_Liquidity'!$C$5:$G$100,MATCH($A16,'09_Raw_Capital_Liquidity'!$A$5:$A$100,0),MATCH(B$4,'09_Raw_Capital_Liquidity'!$C$4:$G$4,0)),"") -> 5.4 | C16: =IFERROR(INDEX('09_Raw_Capital_Liquidity'!$C$5:$G$100,MATCH($A16,'09_Raw_Capital_Liquidity'!$A$5:$A$100,0),MATCH(C$4,'09_Raw_Capital_Liquidity'!$C$4:$G$4,0)),"") -> 5.6 | D16: =IFERROR(INDEX('09_Raw_Capital_Liquidity'!$C$5:$G$100,MATCH($A16,'09_Raw_Capital_Liquidity'!$A$5:$A$100,0),MATCH(D$4,'09_Raw_Capital_Liquidity'!$C$4:$G$4,0)),"") -> 6.04 | E16: =IFERROR(INDEX('09_Raw_Capital_Liquidity'!$C$5:$G$100,MATCH($A16,'09_Raw_Capital_Liquidity'!$A$5:$A$100,0),MATCH(E$4,'09_Raw_Capital_Liquidity'!$C$4:$G$4,0)),"") -> 1.64 | F16: =IFERROR(INDEX('09_Raw_Capital_Liquidity'!$C$5:$G$100,MATCH($A16,'09_Raw_Capital_Liquidity'!$A$5:$A$100,0),MATCH(F$4,'09_Raw_Capital_Liquidity'!$C$4:$G$4,0)),"") -> 1.64

Sheet 15_KPI_Analysis
A1: BANKING KPI ANALYSIS
A4: KPI | B4: FY2023 | C4: FY2024 | D4: FY2025 | E4: FY23–FY25 Change | F4: Assessment | G4: Trend Meaning | H4: Analyst Note
A5: Total Revenue | B5: 51464 | C5: 57344 | D5: 66605 | E5: =IFERROR(D5/B5-1,"") -> 0.29420566 | F5: =IF(E5="","",IF(E5>0,"Favourable","Unfavourable")) -> Favourable | G5: Higher is generally better | H5: Revenue increased strongly, supported by growth across RBC’s diversified businesses and the inclusion of HSBC Canada after March 2024.
A6: Net Income | B6: 14612 | C6: 16240 | D6: 20369 | E6: =IFERROR(D6/B6-1,"") -> 0.39399124 | F6: =IF(E6="","",IF(E6>0,"Favourable","Unfavourable")) -> Favourable | G6: Higher is generally better | H6: Net income rose materially through FY2025, demonstrating stronger earnings capacity despite higher credit costs.
A7: Diluted EPS | B7: 10.32 | C7: 11.25 | D7: 14.07 | E7: =IFERROR(D7/B7-1,"") -> 0.36337209 | F7: =IF(E7="","",IF(E7>0,"Favourable","Unfavourable")) -> Favourable | G7: Higher is generally better | H7: EPS growth outpaced net income growth, supporting stronger per-share profitability.
A8: ROE | B8: 0.143 | C8: 0.144 | D8: 0.163 | E8: =IFERROR(D8/B8-1,"") -> 0.13986014 | F8: =IF(E8="","",IF(E8>0,"Favourable","Unfavourable")) -> Favourable | G8: Higher is generally better | H8: ROE improved to 16.3% in FY2025, above FY2023 and FY2024 levels.
A9: Efficiency Ratio | B9: 0.599 | C9: 0.597 | D9: 0.549 | E9: =IFERROR(D9/B9-1,"") -> -0.083472454 | F9: =IF(E9="","",IF(E9<0,"Favourable","Unfavourable")) -> Favourable | G9: Lower is generally better | H9: The ratio improved to 54.9% in FY2025; the decline indicates stronger expense efficiency.
A10: Operating Leverage | B10: -0.107 | C10: 0.002 | D10: 0.093 | E10: =IFERROR(D10/B10-1,"") -> -1.8691589 | F10: =IF(E10="","",IF(E10>0,"Favourable","Unfavourable")) -> Unfavourable | G10: Higher is generally better | H10: Operating leverage moved from negative in FY2023 to strongly positive in FY2025 as revenue growth exceeded expense growth.
A11: PPPT Earnings | B11: 20651 | C11: 23094 | D11: 30013 | E11: =IFERROR(D11/B11-1,"") -> 0.45334366 | F11: =IF(E11="","",IF(E11>0,"Favourable","Unfavourable")) -> Favourable | G11: Higher is generally better | H11: Pre-provision, pre-tax earnings expanded significantly, showing stronger core earnings before credit costs.
A12: Total PCL | B12: 2468 | C12: 3232 | D12: 4362 | E12: =IFERROR(D12/B12-1,"") -> 0.76742301 | F12: =IF(E12="","",IF(E12<0,"Favourable","Unfavourable")) -> Unfavourable | G12: Lower is generally better | H12: PCL rose sharply over the three-year period, indicating a more normalized and challenging credit cycle.
A13: PCL on Loans Ratio | B13: 0.0029 | C13: 0.0035 | D13: 0.0043 | E13: =IFERROR(D13/B13-1,"") -> 0.48275862 | F13: =IF(E13="","",IF(E13<0,"Favourable","Unfavourable")) -> Unfavourable | G13: Lower is generally better | H13: The ratio increased from 29 bps to 43 bps, signalling higher credit costs relative to average loans.
A14: Gross Impaired Loans | B14: 3704 | C14: 5867 | D14: 8682 | E14: =IFERROR(D14/B14-1,"") -> 1.3439525 | F14: =IF(E14="","",IF(E14<0,"Favourable","Unfavourable")) -> Unfavourable | G14: Lower is generally better | H14: Impaired loans increased substantially, with deterioration concentrated across selected wholesale and retail portfolios.
A15: GIL Ratio | B15: 0.0042 | C15: 0.0059 | D15: 0.0083 | E15: =IFERROR(D15/B15-1,"") -> 0.97619048 | F15: =IF(E15="","",IF(E15<0,"Favourable","Unfavourable")) -> Unfavourable | G15: Lower is generally better | H15: The GIL ratio nearly doubled from FY2023 to FY2025, a key risk to monitor.
A16: Allowance for Credit Losses | B16: 5366 | C16: 6364 | D16: 7470 | E16: =IFERROR(D16/B16-1,"") -> 0.3920984 | F16: =IF(E16="","",IF(E16>0,"Favourable","Unfavourable")) -> Favourable | G16: Higher is generally better | H16: ACL increased alongside credit deterioration, strengthening the reserve available for expected losses.
A17: CET1 Ratio | B17: 0.145 | C17: 0.132 | D17: 0.135 | E17: =IFERROR(D17/B17-1,"") -> -0.068965517 | F17: =IF(E17="","",IF(E17>0,"Favourable","Unfavourable")) -> Unfavourable | G17: Higher is generally better | H17: CET1 remained strong at 13.5% in FY2025, although below the unusually high FY2023 level.
A18: Total Capital Ratio | B18: 0.176 | C18: 0.164 | D18: 0.168 | E18: =IFERROR(D18/B18-1,"") -> -0.045454545 | F18: =IF(E18="","",IF(E18>0,"Favourable","Unfavourable")) -> Unfavourable | G18: Higher is generally better | H18: The total capital ratio remained robust and above regulatory requirements.
A19: Liquidity Coverage Ratio | D19: 1.27 | E19: =IFERROR(D19/B19-1,"") | F19: =IF(E19="","",IF(E19>0,"Favourable","Unfavourable")) | G19: Higher is generally better | H19: FY2025 LCR of 127% remained above the 100% regulatory minimum.
A20: Loans and Acceptances | B20: 879522 | C20: 987452 | D20: 1049534 | E20: =IFERROR(D20/B20-1,"") -> 0.19330045 | F20: =IF(E20="","",IF(E20>0,"Favourable","Unfavourable")) -> Favourable | G20: Higher is generally better | H20: Loan growth supported revenue but also increased credit exposure and capital requirements.
A21: Deposits | B21: 1231687 | C21: 1409531 | D21: 1515616 | E21: =IFERROR(D21/B21-1,"") -> 0.23052042 | F21: =IF(E21="","",IF(E21>0,"Favourable","Unfavourable")) -> Favourable | G21: Higher is generally better | H21: Deposit growth provided a larger and stable funding base.
A22: Loan-to-Deposit Ratio | B22: 0.71407915 | C22: 0.70055359 | D22: 0.69248015 | E22: =IFERROR(D22/B22-1,"") -> -0.030247336 | F22: =IF(E22="","",IF(E22>0,"Favourable","Unfavourable")) -> Unfavourable | G22: Higher is generally better | H22: The consolidated loan-to-deposit ratio remained below 1.0x, indicating deposits exceeded gross loans and acceptances.

Sheet 16_Quarterly_Trends
A1: QUARTERLY TREND ANALYSIS
A4: Quarter | B4: Total Revenue | C4: Net Income | D4: Diluted EPS | E4: ROE | F4: Efficiency Ratio | G4: Total PCL | H4: PCL on Loans Ratio | I4: QoQ Net Income | J4: YoY Net Income
A5: Q1 2024 | B5: 13485 | C5: 3582 | D5: 2.5 | E5: 0.131 | F5: 0.617 | G5: 813 | H5: 0.0042
A6: Q2 2024 | B6: 14154 | C6: 3950 | D6: 2.74 | E6: 0.145 | F6: 0.587 | G6: 920 | H6: 0.0041 | I6: =IFERROR(C6/C5-1,"") -> 0.1027359
A7: Q3 2024 | B7: 14631 | C7: 4486 | D7: 3.09 | E7: 0.155 | F7: 0.588 | G7: 659 | H7: 0.0027 | I7: =IFERROR(C7/C6-1,"") -> 0.1356962
A8: Q4 2024 | B8: 15074 | C8: 4222 | D8: 2.91 | E8: 0.143 | F8: 0.598 | G8: 840 | H8: 0.0035 | I8: =IFERROR(C8/C7-1,"") -> -0.058849755
A9: Q1 2025 | B9: 16739 | C9: 5131 | D9: 3.54 | E9: 0.168 | F9: 0.553 | G9: 1050 | H9: 0.0042 | I9: =IFERROR(C9/C8-1,"") -> 0.21530081 | J9: =IFERROR(C9/C5-1,"") -> 0.43243998
A10: Q2 2025 | B10: 15672 | C10: 4390 | D10: 3.02 | E10: 0.142 | F10: 0.557 | G10: 1424 | H10: 0.0058 | I10: =IFERROR(C10/C9-1,"") -> -0.14441629 | J10: =IFERROR(C10/C6-1,"") -> 0.11139241
A11: Q3 2025 | B11: 16985 | C11: 5414 | D11: 3.75 | E11: 0.173 | F11: 0.544 | G11: 881 | H11: 0.0035 | I11: =IFERROR(C11/C10-1,"") -> 0.2332574 | J11: =IFERROR(C11/C7-1,"") -> 0.2068658
A12: Q4 2025 | B12: 17209 | C12: 5434 | D12: 3.76 | E12: 0.168 | F12: 0.545 | G12: 1007 | H12: 0.0039 | I12: =IFERROR(C12/C11-1,"") -> 0.0036941263 | J12: =IFERROR(C12/C8-1,"") -> 0.28706774
A13: Q1 2026 | B13: 17960 | C13: 5785 | D13: 4.03 | E13: 0.176 | F13: 0.527 | G13: 1090 | H13: 0.0041 | I13: =IFERROR(C13/C12-1,"") -> 0.064593301 | J13: =IFERROR(C13/C9-1,"") -> 0.12746053
A14: Q2 2026 | B14: 17453 | C14: 5509 | D14: 3.85 | E14: 0.172 | F14: 0.541 | G14: 912 | H14: 0.0035 | I14: =IFERROR(C14/C13-1,"") -> -0.047709594 | J14: =IFERROR(C14/C10-1,"") -> 0.25489749
A17: Quarterly Analyst Commentary
A18: Q2 2026 net income of $5.509 billion increased 25% year over year but declined 5% from Q1 2026. The year-over-year improvement reflected growth across all business segments and lower provisions on performing loans. The quarter-over-quarter decline reflected lower results in Wealth Management, Personal Banking and Commercial Banking, partly offset by stronger Capital Markets and Insurance. Total PCL declined to $912 million and the PCL-on-loans ratio improved to 35 bps, while ROE remained strong at 17.2%.

Sheet 17_Segment_Analysis
A1: SEGMENT ANALYSIS
A4: Selected Period | B4: FY2025
A6: Segment | B6: Total Revenue | C6: Net Income | D6: PCL | E6: ROE | F6: Efficiency Ratio | G6: Revenue Share | H6: Analyst Note
A7: Personal Banking | B7: =IFERROR(SUMIFS('10_Raw_Segment_Results'!$C:$C,'10_Raw_Segment_Results'!$A:$A,$B$4,'10_Raw_Segment_Results'!$B:$B,$A7),"") -> 19854 | C7: =IFERROR(SUMIFS('10_Raw_Segment_Results'!$H:$H,'10_Raw_Segment_Results'!$A:$A,$B$4,'10_Raw_Segment_Results'!$B:$B,$A7),"") -> 7105 | D7: =IFERROR(SUMIFS('10_Raw_Segment_Results'!$F:$F,'10_Raw_Segment_Results'!$A:$A,$B$4,'10_Raw_Segment_Results'!$B:$B,$A7),"") -> 2105 | E7: =IF(COUNTIFS('10_Raw_Segment_Results'!$A$5:$A$34,$B$4,'10_Raw_Segment_Results'!$B$5:$B$34,$A7,'10_Raw_Segment_Results'!$I$5:$I$34,"<>")=0,"",SUMIFS('10_Raw_Segment_Results'!$I$5:$I$34,'10_Raw_Segment_Results'!$A$5:$A$34,$B$4,'10_Raw_Segment_Results'!$B$5:$B$34,$A7)) -> 0.249 | F7: =IF(COUNTIFS('10_Raw_Segment_Results'!$A$5:$A$34,$B$4,'10_Raw_Segment_Results'!$B$5:$B$34,$A7,'10_Raw_Segment_Results'!$J$5:$J$34,"<>")=0,"",SUMIFS('10_Raw_Segment_Results'!$J$5:$J$34,'10_Raw_Segment_Results'!$A$5:$A$34,$B$4,'10_Raw_Segment_Results'!$B$5:$B$34,$A7)) -> 0.403 | G7: =IFERROR(B7/SUM($B$7:$B$12),"") -> 0.29808573 | H7: Largest domestic earnings contributor; benefits from scale and strong client franchise.
A8: Commercial Banking | B8: =IFERROR(SUMIFS('10_Raw_Segment_Results'!$C:$C,'10_Raw_Segment_Results'!$A:$A,$B$4,'10_Raw_Segment_Results'!$B:$B,$A8),"") -> 8562 | C8: =IFERROR(SUMIFS('10_Raw_Segment_Results'!$H:$H,'10_Raw_Segment_Results'!$A:$A,$B$4,'10_Raw_Segment_Results'!$B:$B,$A8),"") -> 3020 | D8: =IFERROR(SUMIFS('10_Raw_Segment_Results'!$F:$F,'10_Raw_Segment_Results'!$A:$A,$B$4,'10_Raw_Segment_Results'!$B:$B,$A8),"") -> 1550 | E8: =IF(COUNTIFS('10_Raw_Segment_Results'!$A$5:$A$34,$B$4,'10_Raw_Segment_Results'!$B$5:$B$34,$A8,'10_Raw_Segment_Results'!$I$5:$I$34,"<>")=0,"",SUMIFS('10_Raw_Segment_Results'!$I$5:$I$34,'10_Raw_Segment_Results'!$A$5:$A$34,$B$4,'10_Raw_Segment_Results'!$B$5:$B$34,$A8)) -> 0.149 | F8: =IF(COUNTIFS('10_Raw_Segment_Results'!$A$5:$A$34,$B$4,'10_Raw_Segment_Results'!$B$5:$B$34,$A8,'10_Raw_Segment_Results'!$J$5:$J$34,"<>")=0,"",SUMIFS('10_Raw_Segment_Results'!$J$5:$J$34,'10_Raw_Segment_Results'!$A$5:$A$34,$B$4,'10_Raw_Segment_Results'!$B$5:$B$34,$A8)) -> 0.331 | G8: =IFERROR(B8/SUM($B$7:$B$12),"") -> 0.12854891 | H8: Strong margins and efficient cost base, but credit quality remains cyclical.
A9: Wealth Management | B9: =IFERROR(SUMIFS('10_Raw_Segment_Results'!$C:$C,'10_Raw_Segment_Results'!$A:$A,$B$4,'10_Raw_Segment_Results'!$B:$B,$A9),"") -> 22378 | C9: =IFERROR(SUMIFS('10_Raw_Segment_Results'!$H:$H,'10_Raw_Segment_Results'!$A:$A,$B$4,'10_Raw_Segment_Results'!$B:$B,$A9),"") -> 4289 | D9: =IFERROR(SUMIFS('10_Raw_Segment_Results'!$F:$F,'10_Raw_Segment_Results'!$A:$A,$B$4,'10_Raw_Segment_Results'!$B:$B,$A9),"") -> 120 | E9: =IF(COUNTIFS('10_Raw_Segment_Results'!$A$5:$A$34,$B$4,'10_Raw_Segment_Results'!$B$5:$B$34,$A9,'10_Raw_Segment_Results'!$I$5:$I$34,"<>")=0,"",SUMIFS('10_Raw_Segment_Results'!$I$5:$I$34,'10_Raw_Segment_Results'!$A$5:$A$34,$B$4,'10_Raw_Segment_Results'!$B$5:$B$34,$A9)) -> 0.166 | F9: =IF(COUNTIFS('10_Raw_Segment_Results'!$A$5:$A$34,$B$4,'10_Raw_Segment_Results'!$B$5:$B$34,$A9,'10_Raw_Segment_Results'!$J$5:$J$34,"<>")=0,"",SUMIFS('10_Raw_Segment_Results'!$J$5:$J$34,'10_Raw_Segment_Results'!$A$5:$A$34,$B$4,'10_Raw_Segment_Results'!$B$5:$B$34,$A9)) | G9: =IFERROR(B9/SUM($B$7:$B$12),"") -> 0.33598078 | H9: Fee-based growth and market appreciation support revenue; earnings are market-sensitive.
A10: Insurance | B10: =IFERROR(SUMIFS('10_Raw_Segment_Results'!$C:$C,'10_Raw_Segment_Results'!$A:$A,$B$4,'10_Raw_Segment_Results'!$B:$B,$A10),"") -> 1321 | C10: =IFERROR(SUMIFS('10_Raw_Segment_Results'!$H:$H,'10_Raw_Segment_Results'!$A:$A,$B$4,'10_Raw_Segment_Results'!$B:$B,$A10),"") -> 828 | D10: =IFERROR(SUMIFS('10_Raw_Segment_Results'!$F:$F,'10_Raw_Segment_Results'!$A:$A,$B$4,'10_Raw_Segment_Results'!$B:$B,$A10),"") -> 0 | E10: =IF(COUNTIFS('10_Raw_Segment_Results'!$A$5:$A$34,$B$4,'10_Raw_Segment_Results'!$B$5:$B$34,$A10,'10_Raw_Segment_Results'!$I$5:$I$34,"<>")=0,"",SUMIFS('10_Raw_Segment_Results'!$I$5:$I$34,'10_Raw_Segment_Results'!$A$5:$A$34,$B$4,'10_Raw_Segment_Results'!$B$5:$B$34,$A10)) -> 0.407 | F10: =IF(COUNTIFS('10_Raw_Segment_Results'!$A$5:$A$34,$B$4,'10_Raw_Segment_Results'!$B$5:$B$34,$A10,'10_Raw_Segment_Results'!$J$5:$J$34,"<>")=0,"",SUMIFS('10_Raw_Segment_Results'!$J$5:$J$34,'10_Raw_Segment_Results'!$A$5:$A$34,$B$4,'10_Raw_Segment_Results'!$B$5:$B$34,$A10)) | G10: =IFERROR(B10/SUM($B$7:$B$12),"") -> 0.019833346 | H10: Smaller but capital-efficient earnings contributor with results sensitive to actuarial and market assumptions.
A11: Capital Markets | B11: =IFERROR(SUMIFS('10_Raw_Segment_Results'!$C:$C,'10_Raw_Segment_Results'!$A:$A,$B$4,'10_Raw_Segment_Results'!$B:$B,$A11),"") -> 14426 | C11: =IFERROR(SUMIFS('10_Raw_Segment_Results'!$H:$H,'10_Raw_Segment_Results'!$A:$A,$B$4,'10_Raw_Segment_Results'!$B:$B,$A11),"") -> 5393 | D11: =IFERROR(SUMIFS('10_Raw_Segment_Results'!$F:$F,'10_Raw_Segment_Results'!$A:$A,$B$4,'10_Raw_Segment_Results'!$B:$B,$A11),"") -> 587 | E11: =IF(COUNTIFS('10_Raw_Segment_Results'!$A$5:$A$34,$B$4,'10_Raw_Segment_Results'!$B$5:$B$34,$A11,'10_Raw_Segment_Results'!$I$5:$I$34,"<>")=0,"",SUMIFS('10_Raw_Segment_Results'!$I$5:$I$34,'10_Raw_Segment_Results'!$A$5:$A$34,$B$4,'10_Raw_Segment_Results'!$B$5:$B$34,$A11)) -> 0.137 | F11: =IF(COUNTIFS('10_Raw_Segment_Results'!$A$5:$A$34,$B$4,'10_Raw_Segment_Results'!$B$5:$B$34,$A11,'10_Raw_Segment_Results'!$J$5:$J$34,"<>")=0,"",SUMIFS('10_Raw_Segment_Results'!$J$5:$J$34,'10_Raw_Segment_Results'!$A$5:$A$34,$B$4,'10_Raw_Segment_Results'!$B$5:$B$34,$A11)) | G11: =IFERROR(B11/SUM($B$7:$B$12),"") -> 0.21659035 | H11: Diversified fee and trading revenue, with higher earnings volatility and market-risk exposure.
A12: Corporate Support | B12: =IFERROR(SUMIFS('10_Raw_Segment_Results'!$C:$C,'10_Raw_Segment_Results'!$A:$A,$B$4,'10_Raw_Segment_Results'!$B:$B,$A12),"") -> 64 | C12: =IFERROR(SUMIFS('10_Raw_Segment_Results'!$H:$H,'10_Raw_Segment_Results'!$A:$A,$B$4,'10_Raw_Segment_Results'!$B:$B,$A12),"") -> -266 | D12: =IFERROR(SUMIFS('10_Raw_Segment_Results'!$F:$F,'10_Raw_Segment_Results'!$A:$A,$B$4,'10_Raw_Segment_Results'!$B:$B,$A12),"") -> 0 | E12: =IF(COUNTIFS('10_Raw_Segment_Results'!$A$5:$A$34,$B$4,'10_Raw_Segment_Results'!$B$5:$B$34,$A12,'10_Raw_Segment_Results'!$I$5:$I$34,"<>")=0,"",SUMIFS('10_Raw_Segment_Results'!$I$5:$I$34,'10_Raw_Segment_Results'!$A$5:$A$34,$B$4,'10_Raw_Segment_Results'!$B$5:$B$34,$A12)) | F12: =IF(COUNTIFS('10_Raw_Segment_Results'!$A$5:$A$34,$B$4,'10_Raw_Segment_Results'!$B$5:$B$34,$A12,'10_Raw_Segment_Results'!$J$5:$J$34,"<>")=0,"",SUMIFS('10_Raw_Segment_Results'!$J$5:$J$34,'10_Raw_Segment_Results'!$A$5:$A$34,$B$4,'10_Raw_Segment_Results'!$B$5:$B$34,$A12)) | G12: =IFERROR(B12/SUM($B$7:$B$12),"") -> 0.00096088882 | H12: Includes treasury, technology, functions and consolidation items; results may be negative and volatile.

Sheet 18_Dashboard_Data
A1: DASHBOARD DATA — AUDITED
A4: Latest KPI (Q2 2026) | B4: Value | D4: Metric | E4: FY2023 | F4: FY2024 | G4: FY2025 | I4: Metric | J4: FY2023 | K4: FY2024 | L4: FY2025
A5: Net Income | B5: 5509 | D5: Total Revenue | E5: 51464 | F5: 57344 | G5: 66605 | I5: ROE | J5: 0.143 | K5: 0.144 | L5: 0.163
A6: Diluted EPS | B6: 3.85 | D6: Net Income | E6: 14612 | F6: 16240 | G6: 20369 | I6: Efficiency Ratio | J6: 0.599 | K6: 0.597 | L6: 0.549
A7: ROE | B7: 0.172
A8: Efficiency Ratio | B8: 0.541
A9: CET1 Ratio | B9: 0.135
A10: Total PCL | B10: 912
A13: Quarter | B13: Net Income | C13: Total PCL | E13: Quarter | F13: ROE | G13: Efficiency Ratio | I13: Period | J13: PCL Ratio | K13: GIL Ratio | L13: CET1 Ratio | M13: Total Capital Ratio
A14: Q1 2024 | B14: 3582 | C14: 813 | E14: Q1 2024 | F14: 0.131 | G14: 0.617 | I14: FY2023 | J14: 0.0029 | K14: 0.0042 | L14: 0.145 | M14: 0.176
A15: Q2 2024 | B15: 3950 | C15: 920 | E15: Q2 2024 | F15: 0.145 | G15: 0.587 | I15: FY2024 | J15: 0.0035 | K15: 0.0059 | L15: 0.132 | M15: 0.164
A16: Q3 2024 | B16: 4486 | C16: 659 | E16: Q3 2024 | F16: 0.155 | G16: 0.588 | I16: FY2025 | J16: 0.0043 | K16: 0.0083 | L16: 0.135 | M16: 0.168
A17: Q4 2024 | B17: 4222 | C17: 840 | E17: Q4 2024 | F17: 0.143 | G17: 0.598 | I17: Q1 2026 | J17: 0.0041 | K17: 0.0086 | L17: 0.137 | M17: 0.168
A18: Q1 2025 | B18: 5131 | C18: 1050 | E18: Q1 2025 | F18: 0.168 | G18: 0.553 | I18: Q2 2026 | J18: 0.0035 | K18: 0.009 | L18: 0.135 | M18: 0.169
A19: Q2 2025 | B19: 4390 | C19: 1424 | E19: Q2 2025 | F19: 0.142 | G19: 0.557
A20: Q3 2025 | B20: 5414 | C20: 881 | E20: Q3 2025 | F20: 0.173 | G20: 0.544
A21: Q4 2025 | B21: 5434 | C21: 1007 | E21: Q4 2025 | F21: 0.168 | G21: 0.545
A22: Q1 2026 | B22: 5785 | C22: 1090 | E22: Q1 2026 | F22: 0.176 | G22: 0.527
A23: Q2 2026 | B23: 5509 | C23: 912 | E23: Q2 2026 | F23: 0.172 | G23: 0.541
A27: Segment | B27: FY2025 Revenue | C27: FY2025 Net Income
A28: Personal Banking | B28: 19854 | C28: 7105
A29: Commercial Banking | B29: 8562 | C29: 3020
A30: Wealth Management | B30: 22378 | C30: 4289
A31: Insurance | B31: 1321 | C31: 828
A32: Capital Markets | B32: 14426 | C32: 5393
A33: Corporate Support | B33: 64 | C33: -266

Sheet 19_Dashboard
A1: RBC FINANCIAL PERFORMANCE, CREDIT RISK & CAPITAL DASHBOARD
A3: FY2023–FY2025 Annual Analysis | Quarterly Trends through Q2 2026 | CAD millions unless stated
A5: Net Income | C5: Diluted EPS | E5: ROE | G5: Efficiency Ratio | I5: CET1 Ratio | K5: Total PCL
A7: ='18_Dashboard_Data'!B5 -> 5509 | C7: ='18_Dashboard_Data'!B6 -> 3.85 | E7: ='18_Dashboard_Data'!B7 -> 0.172 | G7: ='18_Dashboard_Data'!B8 -> 0.541 | I7: ='18_Dashboard_Data'!B9 -> 0.135 | K7: ='18_Dashboard_Data'!B10 -> 912
H46: Key Financial Insights
H47: • FY2025 revenue reached $66.6 billion, an increase of 29.4% from FY2023; net income rose 39.4% to $20.4 billion. • Profitability improved: diluted EPS reached $14.07, ROE increased to 16.3%, and the efficiency ratio improved to 54.9%. • Credit risk increased through FY2025: total PCL rose to $4.36 billion and the GIL ratio reached 0.83%. • Q2 2026 remained profitable with $5.51 billion of net income and 17.2% ROE. PCL improved to $912 million and 35 bps. • Capital and liquidity remained resilient: CET1 was 13.5%, total capital was 16.9%, LCR was 126%, and NSFR was 111%.

Sheet 20_Analyst_Commentary
A1: ANALYST COMMENTARY
A4: Executive Summary
A5: RBC delivered strong earnings growth through FY2025 and maintained robust profitability into Q2 2026. FY2025 revenue increased to $66.6 billion and net income to $20.4 billion, supported by diversified contributions from Personal Banking, Commercial Banking, Wealth Management and Capital Markets. ROE improved to 16.3% and the efficiency ratio declined to 54.9%, indicating stronger operating productivity. Credit risk, however, moved higher through FY2025 as PCL and impaired loans increased. Q2 2026 showed an improvement in quarterly credit costs, while capital and liquidity remained above regulatory requirements.
A11: Financial Performance
A12: Revenue grew 29.4% between FY2023 and FY2025, while net income increased 39.4%. Diluted EPS rose from $10.32 to $14.07, and PPPT earnings increased from $20.7 billion to $30.0 billion. Positive operating leverage of 9.3% in FY2025 and a lower efficiency ratio demonstrate that revenue grew faster than non-interest expense. Q2 2026 net income was $5.5 billion, up 25% year over year but down 5% sequentially.
A18: Credit Risk
A19: Total PCL increased from $2.47 billion in FY2023 to $4.36 billion in FY2025, and the PCL-on-loans ratio increased from 29 bps to 43 bps. Gross impaired loans rose to $8.68 billion and the GIL ratio reached 0.83% in FY2025. RBC increased total ACL to $7.47 billion as reserves expanded with the risk profile. In Q2 2026, total PCL declined to $912 million and the PCL ratio improved to 35 bps, although GIL continued to rise to $9.79 billion.
A25: Capital and Liquidity
A26: RBC maintained a strong regulatory position. The CET1 ratio was 13.5% at FY2025 and Q2 2026, while the total capital ratio increased to 16.9% in Q2 2026. The Q2 2026 CET1 ratio was lower than Q1 because internal capital generation was more than offset by share repurchases, RWA growth and model updates. The LCR improved to 126% from 124% in Q1 2026 and remained comfortably above the 100% regulatory minimum.
A32: Segment Performance
A33: Personal Banking remained the largest domestic earnings contributor, while Wealth Management and Capital Markets provided material fee-based and market-linked diversification. Commercial Banking maintained a low efficiency ratio but remained exposed to the credit cycle. Insurance was a smaller but capital-efficient contributor. Capital Markets showed strong Q2 2026 momentum, supported by Global Markets and Corporate & Investment Banking activity.
A39: Key Strengths
... A54: RBC entered Q2 2026 from a position of strong profitability, diversified earnings and substantial capital strength. The main analytical tension is between accelerating earnings and a more normalized credit cycle. Current capital and liquidity provide meaningful resilience, but impaired-loan trends and credit-loss provisions should remain key monitoring priorities.

Sheet 21_Interactive_Analysis
A1: INTERACTIVE RBC ANALYSIS
A4: Control | B4: Selection
A5: Selected Annual KPI | B5: Net Income
A6: Selected Segment Period | B6: FY2025
A8: Selected Annual KPI | G8: Selected Segment Performance
A9: KPI | B9: FY2023 | C9: FY2024 | D9: FY2025 | E9: FY23–FY25 Change | G9: Segment | H9: Revenue | I9: Net Income | J9: PCL | K9: ROE | L9: Efficiency | M9: Revenue Share | N9: Comment
A10: =$B$5 -> Net Income | B10: =IFERROR(INDEX('05_Raw_Annual_Performance'!$C$5:$C$19,MATCH($A10,'05_Raw_Annual_Performance'!$A$5:$A$19,0)),"") -> 14612 | C10: =IFERROR(INDEX('05_Raw_Annual_Performance'!$D$5:$D$19,MATCH($A10,'05_Raw_Annual_Performance'!$A$5:$A$19,0)),"") -> 16240 | D10: =IFERROR(INDEX('05_Raw_Annual_Performance'!$E$5:$E$19,MATCH($A10,'05_Raw_Annual_Performance'!$A$5:$A$19,0)),"") -> 20369 | E10: =IFERROR(D10/B10-1,"") -> 0.39399124 | G10: Personal Banking | H10: =IFERROR(SUMIFS('10_Raw_Segment_Results'!$C$5:$C$34,'10_Raw_Segment_Results'!$A$5:$A$34,$B$6,'10_Raw_Segment_Results'!$B$5:$B$34,$G10),"") -> 19854 | I10: =IFERROR(SUMIFS('10_Raw_Segment_Results'!$H$5:$H$34,'10_Raw_Segment_Results'!$A$5:$A$34,$B$6,'10_Raw_Segment_Results'!$B$5:$B$34,$G10),"") -> 7105 | J10: =IFERROR(SUMIFS('10_Raw_Segment_Results'!$F$5:$F$34,'10_Raw_Segment_Results'!$A$5:$A$34,$B$6,'10_Raw_Segment_Results'!$B$5:$B$34,$G10),"") -> 2105 | K10: =IF(COUNTIFS('10_Raw_Segment_Results'!$A$5:$A$34,$B$6,'10_Raw_Segment_Results'!$B$5:$B$34,$G10,'10_Raw_Segment_Results'!$I$5:$I$34,"<>")=0,"",SUMIFS('10_Raw_Segment_Results'!$I$5:$I$34,'10_Raw_Segment_Results'!$A$5:$A$34,$B$6,'10_Raw_Segment_Results'!$B$5:$B$34,$G10)) -> 0.249 | L10: =IF(COUNTIFS('10_Raw_Segment_Results'!$A$5:$A$34,$B$6,'10_Raw_Segment_Results'!$B$5:$B$34,$G10,'10_Raw_Segment_Results'!$J$5:$J$34,"<>")=0,"",SUMIFS('10_Raw_Segment_Results'!$J$5:$J$34,'10_Raw_Segment_Results'!$A$5:$A$34,$B$6,'10_Raw_Segment_Results'!$B$5:$B$34,$G10)) -> 0.403 | M10: =IFERROR(H10/SUM($H$10:$H$15),"") -> 0.29808573 | N10: Largest domestic banking franchise.
G11: Commercial Banking | H11: =IFERROR(SUMIFS('10_Raw_Segment_Results'!$C$5:$C$34,'10_Raw_Segment_Results'!$A$5:$A$34,$B$6,'10_Raw_Segment_Results'!$B$5:$B$34,$G11),"") -> 8562 | I11: =IFERROR(SUMIFS('10_Raw_Segment_Results'!$H$5:$H$34,'10_Raw_Segment_Results'!$A$5:$A$34,$B$6,'10_Raw_Segment_Results'!$B$5:$B$34,$G11),"") -> 3020 | J11: =IFERROR(SUMIFS('10_Raw_Segment_Results'!$F$5:$F$34,'10_Raw_Segment_Results'!$A$5:$A$34,$B$6,'10_Raw_Segment_Results'!$B$5:$B$34,$G11),"") -> 1550 | K11: =IF(COUNTIFS('10_Raw_Segment_Results'!$A$5:$A$34,$B$6,'10_Raw_Segment_Results'!$B$5:$B$34,$G11,'10_Raw_Segment_Results'!$I$5:$I$34,"<>")=0,"",SUMIFS('10_Raw_Segment_Results'!$I$5:$I$34,'10_Raw_Segment_Results'!$A$5:$A$34,$B$6,'10_Raw_Segment_Results'!$B$5:$B$34,$G11)) -> 0.149 | L11: =IF(COUNTIFS('10_Raw_Segment_Results'!$A$5:$A$34,$B$6,'10_Raw_Segment_Results'!$B$5:$B$34,$G11,'10_Raw_Segment_Results'!$J$5:$J$34,"<>")=0,"",SUMIFS('10_Raw_Segment_Results'!$J$5:$J$34,'10_Raw_Segment_Results'!$A$5:$A$34,$B$6,'10_Raw_Segment_Results'!$B$5:$B$34,$G11)) -> 0.331 | M11: =IFERROR(H11/SUM($H$10:$H$15),"") -> 0.12854891 | N11: Efficient but credit-cycle sensitive.
G12: Wealth Management | H12: =IFERROR(SUMIFS('10_Raw_Segment_Results'!$C$5:$C$34,'10_Raw_Segment_Results'!$A$5:$A$34,$B$6,'10_Raw_Segment_Results'!$B$5:$B$34,$G12),"") -> 22378 | I12: =IFERROR(SUMIFS('10_Raw_Segment_Results'!$H$5:$H$34,'10_Raw_Segment_Results'!$A$5:$A$34,$B$6,'10_Raw_Segment_Results'!$B$5:$B$34,$G12),"") -> 4289 | J12: =IFERROR(SUMIFS('10_Raw_Segment_Results'!$F$5:$F$34,'10_Raw_Segment_Results'!$A$5:$A$34,$B$6,'10_Raw_Segment_Results'!$B$5:$B$34,$G12),"") -> 120 | K12: =IF(COUNTIFS('10_Raw_Segment_Results'!$A$5:$A$34,$B$6,'10_Raw_Segment_Results'!$B$5:$B$34,$G12,'10_Raw_Segment_Results'!$I$5:$I$34,"<>")=0,"",SUMIFS('10_Raw_Segment_Results'!$I$5:$I$34,'10_Raw_Segment_Results'!$A$5:$A$34,$B$6,'10_Raw_Segment_Results'!$B$5:$B$34,$G12)) -> 0.166 | L12: =IF(COUNTIFS('10_Raw_Segment_Results'!$A$5:$A$34,$B$6,'10_Raw_Segment_Results'!$B$5:$B$34,$G12,'10_Raw_Segment_Results'!$J$5:$J$34,"<>")=0,"",SUMIFS('10_Raw_Segment_Results'!$J$5:$J$34,'10_Raw_Segment_Results'!$A$5:$A$34,$B$6,'10_Raw_Segment_Results'!$B$5:$B$34,$G12)) | M12: =IFERROR(H12/SUM($H$10:$H$15),"") -> 0.33598078 | N12: Fee-based and market-sensitive.
G13: Insurance | H13: =IFERROR(SUMIFS('10_Raw_Segment_Results'!$C$5:$C$34,'10_Raw_Segment_Results'!$A$5:$A$34,$B$6,'10_Raw_Segment_Results'!$B$5:$B$34,$G13),"") -> 1321 | I13: =IFERROR(SUMIFS('10_Raw_Segment_Results'!$H$5:$H$34,'10_Raw_Segment_Results'!$A$5:$A$34,$B$6,'10_Raw_Segment_Results'!$B$5:$B$34,$G13),"") -> 828 | J13: =IFERROR(SUMIFS('10_Raw_Segment_Results'!$F$5:$F$34,'10_Raw_Segment_Results'!$A$5:$A$34,$B$6,'10_Raw_Segment_Results'!$B$5:$B$34,$G13),"") -> 0 | K13: =IF(COUNTIFS('10_Raw_Segment_Results'!$A$5:$A$34,$B$6,'10_Raw_Segment_Results'!$B$5:$B$34,$G13,'10_Raw_Segment_Results'!$I$5:$I$34,"<>")=0,"",SUMIFS('10_Raw_Segment_Results'!$I$5:$I$34,'10_Raw_Segment_Results'!$A$5:$A$34,$B$6,'10_Raw_Segment_Results'!$B$5:$B$34,$G13)) -> 0.407 | L13: =IF(COUNTIFS('10_Raw_Segment_Results'!$A$5:$A$34,$B$6,'10_Raw_Segment_Results'!$B$5:$B$34,$G13,'10_Raw_Segment_Results'!$J$5:$J$34,"<>")=0,"",SUMIFS('10_Raw_Segment_Results'!$J$5:$J$34,'10_Raw_Segment_Results'!$A$5:$A$34,$B$6,'10_Raw_Segment_Results'!$B$5:$B$34,$G13)) | M13: =IFERROR(H13/SUM($H$10:$H$15),"") -> 0.019833346 | N13: Smaller, capital-efficient contributor.
G14: Capital Markets | H14: =IFERROR(SUMIFS('10_Raw_Segment_Results'!$C$5:$C$34,'10_Raw_Segment_Results'!$A$5:$A$34,$B$6,'10_Raw_Segment_Results'!$B$5:$B$34,$G14),"") -> 14426 | I14: =IFERROR(SUMIFS('10_Raw_Segment_Results'!$H$5:$H$34,'10_Raw_Segment_Results'!$A$5:$A$34,$B$6,'10_Raw_Segment_Results'!$B$5:$B$34,$G14),"") -> 5393 | J14: =IFERROR(SUMIFS('10_Raw_Segment_Results'!$F$5:$F$34,'10_Raw_Segment_Results'!$A$5:$A$34,$B$6,'10_Raw_Segment_Results'!$B$5:$B$34,$G14),"") -> 587 | K14: =IF(COUNTIFS('10_Raw_Segment_Results'!$A$5:$A$34,$B$6,'10_Raw_Segment_Results'!$B$5:$B$34,$G14,'10_Raw_Segment_Results'!$I$5:$I$34,"<>")=0,"",SUMIFS('10_Raw_Segment_Results'!$I$5:$I$34,'10_Raw_Segment_Results'!$A$5:$A$34,$B$6,'10_Raw_Segment_Results'!$B$5:$B$34,$G14)) -> 0.137 | L14: =IF(COUNTIFS('10_Raw_Segment_Results'!$A$5:$A$34,$B$6,'10_Raw_Segment_Results'!$B$5:$B$34,$G14,'10_Raw_Segment_Results'!$J$5:$J$34,"<>")=0,"",SUMIFS('10_Raw_Segment_Results'!$J$5:$J$34,'10_Raw_Segment_Results'!$A$5:$A$34,$B$6,'10_Raw_Segment_Results'!$B$5:$B$34,$G14)) | M14: =IFERROR(H14/SUM($H$10:$H$15),"") -> 0.21659035 | N14: Strong earnings with market volatility.
G15: Corporate Support | H15: =IFERROR(SUMIFS('10_Raw_Segment_Results'!$C$5:$C$34,'10_Raw_Segment_Results'!$A$5:$A$34,$B$6,'10_Raw_Segment_Results'!$B$5:$B$34,$G15),"") -> 64 | I15: =IFERROR(SUMIFS('10_Raw_Segment_Results'!$H$5:$H$34,'10_Raw_Segment_Results'!$A$5:$A$34,$B$6,'10_Raw_Segment_Results'!$B$5:$B$34,$G15),"") -> -266 | J15: =IFERROR(SUMIFS('10_Raw_Segment_Results'!$F$5:$F$34,'10_Raw_Segment_Results'!$A$5:$A$34,$B$6,'10_Raw_Segment_Results'!$B$5:$B$34,$G15),"") -> 0 | K15: =IF(COUNTIFS('10_Raw_Segment_Results'!$A$5:$A$34,$B$6,'10_Raw_Segment_Results'!$B$5:$B$34,$G15,'10_Raw_Segment_Results'!$I$5:$I$34,"<>")=0,"",SUMIFS('10_Raw_Segment_Results'!$I$5:$I$34,'10_Raw_Segment_Results'!$A$5:$A$34,$B$6,'10_Raw_Segment_Results'!$B$5:$B$34,$G15)) | L15: =IF(COUNTIFS('10_Raw_Segment_Results'!$A$5:$A$34,$B$6,'10_Raw_Segment_Results'!$B$5:$B$34,$G15,'10_Raw_Segment_Results'!$J$5:$J$34,"<>")=0,"",SUMIFS('10_Raw_Segment_Results'!$J$5:$J$34,'10_Raw_Segment_Results'!$A$5:$A$34,$B$6,'10_Raw_Segment_Results'!$B$5:$B$34,$G15)) | M15: =IFERROR(H15/SUM($H$10:$H$15),"") -> 0.00096088882 | N15: Treasury and consolidation items.

Sheet 22_Advanced_Excel
A1: ADVANCED EXCEL FORMULA SHOWCASE
A3: Compatible formula layer using INDEX/MATCH, SUMIFS, IFERROR, RANK and COUNTIF. These provide the same analytical outcomes as newer functions while improving workbook compatibility.
A5: Control | B5: Selection | E5: Function | F5: Used In | G5: Formula Pattern | H5: Purpose
A6: Selected Quarterly KPI | B6: Net Income | E6: INDEX + MATCH | F6: B10 | G6: =INDEX(data,MATCH(metric,metric_list,0),MATCH(period,period_list,0)) | H6: Two-way KPI lookup
A7: Selected Quarter | B7: Q2 2026 | E7: INDEX + MATCH | F7: B11 | G7: =INDEX(data,MATCH(metric,metric_list,0),MATCH(period,period_list,0)-1) | H7: Previous-quarter comparison
E8: IFERROR | F8: B12:B13 | G8: =IFERROR(current_value/prior_value-1,"") | H8: Clean variance calculations
A9: Output | B9: Result | C9: Unit / Meaning | E9: Nested IF | F9: B14 | G9: =IF(lower_is_better,IF(current<prior,"Favourable","Unfavourable"),...) | H9: Metric-aware assessment
A10: Current Period Value | B10: =IFERROR(INDEX('06_Raw_Quarterly_Performance'!$C$5:$L$19,MATCH($B$6,'06_Raw_Quarterly_Performance'!$A$5:$A$19,0),MATCH($B$7,'06_Raw_Quarterly_Performance'!$C$4:$L$4,0)),"") -> 5509 | C10: =IFERROR(INDEX('06_Raw_Quarterly_Performance'!$B$5:$B$19,MATCH($B$6,'06_Raw_Quarterly_Performance'!$A$5:$A$19,0)),"") -> CAD millions | E10: RANK | F10: B15 | G10: =RANK(current_value,quarterly_trend_range,0) | H10: Quarterly performance ranking
A11: Previous Quarter Value | B11: =IFERROR(INDEX('06_Raw_Quarterly_Performance'!$C$5:$L$19,MATCH($B$6,'06_Raw_Quarterly_Performance'!$A$5:$A$19,0),MATCH($B$7,'06_Raw_Quarterly_Performance'!$C$4:$L$4,0)-1),"") -> 5785 | C11: =C10 -> CAD millions | E11: SUMIFS | F11: Segment helper | G11: =SUMIFS(value_range,period_range,period,segment_range,segment) | H11: Multi-criteria aggregation
A12: Quarter-over-Quarter Change | B12: =IFERROR(B10/B11-1,"") -> -0.047709594 | C12: % change | E12: COUNTIF | F12: Segment helper | G12: =RANK(value,range,0)+COUNTIF(first_cell:value,value)-1 | H12: Tie-safe unique ranking
A13: Year-over-Year Change | B13: =IFERROR(B10/INDEX('06_Raw_Quarterly_Performance'!$C$5:$L$19,MATCH($B$6,'06_Raw_Quarterly_Performance'!$A$5:$A$19,0),MATCH($B$7,'06_Raw_Quarterly_Performance'!$C$4:$L$4,0)-4)-1,"") -> 0.25489749 | C13: % change
A14: Performance Assessment | B14: =IF(B11="","Not available",IF(OR(B6="Provision for Credit Losses",B6="Non-Interest Expense",B6="Efficiency Ratio"),IF(B10<B11,"Favourable","Unfavourable"),IF(B10>B11,"Favourable","Unfavourable"))) -> Unfavourable | C14: Metric-aware
A15: Rank Across 10 Quarters | B15: =IFERROR(RANK(B10,B18:K18,0),"") -> 2 | C15: 1 = highest
A17: Selected KPI Trend | B17: Q1 2024 | C17: Q2 2024 | D17: Q3 2024 | E17: Q4 2024 | F17: Q1 2025 | G17: Q2 2025 | H17: Q3 2025 | I17: Q4 2025 | J17: Q1 2026 | K17: Q2 2026 | L17: Trend
A18: =$B$6 -> Net Income | B18: =IFERROR(INDEX('06_Raw_Quarterly_Performance'!$C$5:$L$19,MATCH($B$6,'06_Raw_Quarterly_Performance'!$A$5:$A$19,0),MATCH(B$17,'06_Raw_Quarterly_Performance'!$C$4:$L$4,0)),"") -> 3582 | C18: =IFERROR(INDEX('06_Raw_Quarterly_Performance'!$C$5:$L$19,MATCH($B$6,'06_Raw_Quarterly_Performance'!$A$5:$A$19,0),MATCH(C$17,'06_Raw_Quarterly_Performance'!$C$4:$L$4,0)),"") -> 3950 | D18: =IFERROR(INDEX('06_Raw_Quarterly_Performance'!$C$5:$L$19,MATCH($B$6,'06_Raw_Quarterly_Performance'!$A$5:$A$19,0),MATCH(D$17,'06_Raw_Quarterly_Performance'!$C$4:$L$4,0)),"") -> 4486 | E18: =IFERROR(INDEX('06_Raw_Quarterly_Performance'!$C$5:$L$19,MATCH($B$6,'06_Raw_Quarterly_Performance'!$A$5:$A$19,0),MATCH(E$17,'06_Raw_Quarterly_Performance'!$C$4:$L$4,0)),"") -> 4222 | F18: =IFERROR(INDEX('06_Raw_Quarterly_Performance'!$C$5:$L$19,MATCH($B$6,'06_Raw_Quarterly_Performance'!$A$5:$A$19,0),MATCH(F$17,'06_Raw_Quarterly_Performance'!$C$4:$L$4,0)),"") -> 5131 | G18: =IFERROR(INDEX('06_Raw_Quarterly_Performance'!$C$5:$L$19,MATCH($B$6,'06_Raw_Quarterly_Performance'!$A$5:$A$19,0),MATCH(G$17,'06_Raw_Quarterly_Performance'!$C$4:$L$4,0)),"") -> 4390 | H18: =IFERROR(INDEX('06_Raw_Quarterly_Performance'!$C$5:$L$19,MATCH($B$6,'06_Raw_Quarterly_Performance'!$A$5:$A$19,0),MATCH(H$17,'06_Raw_Quarterly_Performance'!$C$4:$L$4,0)),"") -> 5414 | I18: =IFERROR(INDEX('06_Raw_Quarterly_Performance'!$C$5:$L$19,MATCH($B$6,'06_Raw_Quarterly_Performance'!$A$5:$A$19,0),MATCH(I$17,'06_Raw_Quarterly_Performance'!$C$4:$L$4,0)),"") -> 5434 | ... K18: =IFERROR(INDEX('06_Raw_Quarterly_Performance'!$C$5:$L$19,MATCH($B$6,'06_Raw_Quarterly_Performance'!$A$5:$A$19,0),MATCH(K$17,'06_Raw_Quarterly_Performance'!$C$4:$L$4,0)),"") -> 5509
A21: Segment Ranking Control | B21: Selection
A22: Selected Segment Period | B22: FY2025
A23: Selected Segment Metric | B23: Net Income
A25: Rank | B25: Segment | C25: Selected Metric Value | N25: Segment Helper | O25: Metric Value | P25: Unique Rank
A26: 1 | B26: {=IFERROR(INDEX($N$26:$N$31,MATCH($A26,$P$26:$P$31,0)),"")} -> Personal Banking | C26: {=IFERROR(INDEX($O$26:$O$31,MATCH($A26,$P$26:$P$31,0)),"")} -> 7105 | N26: Personal Banking | O26: =IF(COUNTIFS('23_Pivot_Source'!$A$5:$A$439,"Segment",'23_Pivot_Source'!$B$5:$B$439,$B$22,'23_Pivot_Source'!$D$5:$D$439,$N26,'23_Pivot_Source'!$E$5:$E$439,$B$23,'23_Pivot_Source'!$G$5:$G$439,"<>")=0,"",SUMIFS('23_Pivot_Source'!$G$5:$G$439,'23_Pivot_Source'!$A$5:$A$439,"Segment",'23_Pivot_Source'!$B$5:$B$439,$B$22,'23_Pivot_Source'!$D$5:$D$439,$N26,'23_Pivot_Source'!$E$5:$E$439,$B$23)) -> 7105 | P26: =IF(O26="","",COUNTIF($O$26:$O$31,">"&O26)+COUNTIF($O$26:O26,O26)) -> 1
A27: 2 | B27: Personal Banking | C27: 7105 | N27: Commercial Banking | O27: =IF(COUNTIFS('23_Pivot_Source'!$A$5:$A$439,"Segment",'23_Pivot_Source'!$B$5:$B$439,$B$22,'23_Pivot_Source'!$D$5:$D$439,$N27,'23_Pivot_Source'!$E$5:$E$439,$B$23,'23_Pivot_Source'!$G$5:$G$439,"<>")=0,"",SUMIFS('23_Pivot_Source'!$G$5:$G$439,'23_Pivot_Source'!$A$5:$A$439,"Segment",'23_Pivot_Source'!$B$5:$B$439,$B$22,'23_Pivot_Source'!$D$5:$D$439,$N27,'23_Pivot_Source'!$E$5:$E$439,$B$23)) -> 3020 | P27: =IF(O27="","",COUNTIF($O$26:$O$31,">"&O27)+COUNTIF($O$26:O27,O27)) -> 4
A28: 3 | B28: Personal Banking | C28: 7105 | N28: Wealth Management | O28: =IF(COUNTIFS('23_Pivot_Source'!$A$5:$A$439,"Segment",'23_Pivot_Source'!$B$5:$B$439,$B$22,'23_Pivot_Source'!$D$5:$D$439,$N28,'23_Pivot_Source'!$E$5:$E$439,$B$23,'23_Pivot_Source'!$G$5:$G$439,"<>")=0,"",SUMIFS('23_Pivot_Source'!$G$5:$G$439,'23_Pivot_Source'!$A$5:$A$439,"Segment",'23_Pivot_Source'!$B$5:$B$439,$B$22,'23_Pivot_Source'!$D$5:$D$439,$N28,'23_Pivot_Source'!$E$5:$E$439,$B$23)) -> 4289 | P28: =IF(O28="","",COUNTIF($O$26:$O$31,">"&O28)+COUNTIF($O$26:O28,O28)) -> 3
A29: 4 | B29: Personal Banking | C29: 7105 | N29: Insurance | O29: =IF(COUNTIFS('23_Pivot_Source'!$A$5:$A$439,"Segment",'23_Pivot_Source'!$B$5:$B$439,$B$22,'23_Pivot_Source'!$D$5:$D$439,$N29,'23_Pivot_Source'!$E$5:$E$439,$B$23,'23_Pivot_Source'!$G$5:$G$439,"<>")=0,"",SUMIFS('23_Pivot_Source'!$G$5:$G$439,'23_Pivot_Source'!$A$5:$A$439,"Segment",'23_Pivot_Source'!$B$5:$B$439,$B$22,'23_Pivot_Source'!$D$5:$D$439,$N29,'23_Pivot_Source'!$E$5:$E$439,$B$23)) -> 828 | P29: =IF(O29="","",COUNTIF($O$26:$O$31,">"&O29)+COUNTIF($O$26:O29,O29)) -> 5
A30: 5 | B30: Personal Banking | C30: 7105 | N30: Capital Markets | O30: =IF(COUNTIFS('23_Pivot_Source'!$A$5:$A$439,"Segment",'23_Pivot_Source'!$B$5:$B$439,$B$22,'23_Pivot_Source'!$D$5:$D$439,$N30,'23_Pivot_Source'!$E$5:$E$439,$B$23,'23_Pivot_Source'!$G$5:$G$439,"<>")=0,"",SUMIFS('23_Pivot_Source'!$G$5:$G$439,'23_Pivot_Source'!$A$5:$A$439,"Segment",'23_Pivot_Source'!$B$5:$B$439,$B$22,'23_Pivot_Source'!$D$5:$D$439,$N30,'23_Pivot_Source'!$E$5:$E$439,$B$23)) -> 5393 | P30: =IF(O30="","",COUNTIF($O$26:$O$31,">"&O30)+COUNTIF($O$26:O30,O30)) -> 2
A31: 6 | B31: Personal Banking | C31: 7105 | N31: Corporate Support | O31: =IF(COUNTIFS('23_Pivot_Source'!$A$5:$A$439,"Segment",'23_Pivot_Source'!$B$5:$B$439,$B$22,'23_Pivot_Source'!$D$5:$D$439,$N31,'23_Pivot_Source'!$E$5:$E$439,$B$23,'23_Pivot_Source'!$G$5:$G$439,"<>")=0,"",SUMIFS('23_Pivot_Source'!$G$5:$G$439,'23_Pivot_Source'!$A$5:$A$439,"Segment",'23_Pivot_Source'!$B$5:$B$439,$B$22,'23_Pivot_Source'!$D$5:$D$439,$N31,'23_Pivot_Source'!$E$5:$E$439,$B$23)) -> -266 | P31: =IF(O31="","",COUNTIF($O$26:$O$31,">"&O31)+COUNTIF($O$26:O31,O31)) -> 6

Sheet 23_Pivot_Source
A1: NORMALIZED ANALYSIS DATA — PIVOT SOURCE
A3: Formula-linked long-format table for PivotTables, SUMIFS analysis, charts and Power BI import.
A4: Analysis Type | B4: Period | C4: Period Order | D4: Segment | E4: Metric | F4: Unit | G4: Value | H4: Source Sheet | I4: Source Cell
A5: Consolidated Annual | B5: FY2023 | C5: 1 | D5: Total RBC | E5: Net Interest Income | F5: CAD millions | G5: ='05_Raw_Annual_Performance'!C5 -> 25129 | H5: 05_Raw_Annual_Performance | I5: C5
A6: Consolidated Annual | B6: FY2024 | C6: 2 | D6: Total RBC | E6: Net Interest Income | F6: CAD millions | G6: ='05_Raw_Annual_Performance'!D5 -> 27953 | H6: 05_Raw_Annual_Performance | I6: D5
A7: Consolidated Annual | B7: FY2025 | C7: 3 | D7: Total RBC | E7: Net Interest Income | F7: CAD millions | G7: ='05_Raw_Annual_Performance'!E5 -> 33000 | H7: 05_Raw_Annual_Performance | I7: E5
A8: Consolidated Annual | B8: FY2023 | C8: 1 | D8: Total RBC | E8: Non-Interest Income | F8: CAD millions | G8: ='05_Raw_Annual_Performance'!C6 -> 26335 | H8: 05_Raw_Annual_Performance | I8: C6
A9: Consolidated Annual | B9: FY2024 | C9: 2 | D9: Total RBC | E9: Non-Interest Income | F9: CAD millions | G9: ='05_Raw_Annual_Performance'!D6 -> 29391 | H9: 05_Raw_Annual_Performance | I9: D6
A10: Consolidated Annual | B10: FY2025 | C10: 3 | D10: Total RBC | E10: Non-Interest Income | F10: CAD millions | G10: ='05_Raw_Annual_Performance'!E6 -> 33605 | H10: 05_Raw_Annual_Performance | I10: E6
A11: Consolidated Annual | B11: FY2023 | C11: 1 | D11: Total RBC | E11: Total Revenue | F11: CAD millions | G11: ='05_Raw_Annual_Performance'!C7 -> 51464 | H11: 05_Raw_Annual_Performance | I11: C7
A12: Consolidated Annual | B12: FY2024 | C12: 2 | D12: Total RBC | E12: Total Revenue | F12: CAD millions | G12: ='05_Raw_Annual_Performance'!D7 -> 57344 | H12: 05_Raw_Annual_Performance | I12: D7
A13: Consolidated Annual | B13: FY2025 | C13: 3 | D13: Total RBC | E13: Total Revenue | F13: CAD millions | G13: ='05_Raw_Annual_Performance'!E7 -> 66605 | H13: 05_Raw_Annual_Performance | I13: E7
A14: Consolidated Annual | B14: FY2023 | C14: 1 | D14: Total RBC | E14: Provision for Credit Losses | F14: CAD millions | G14: ='05_Raw_Annual_Performance'!C8 -> 2468 | H14: 05_Raw_Annual_Performance | I14: C8
A15: Consolidated Annual | B15: FY2024 | C15: 2 | D15: Total RBC | E15: Provision for Credit Losses | F15: CAD millions | G15: ='05_Raw_Annual_Performance'!D8 -> 3232 | H15: 05_Raw_Annual_Performance | I15: D8
A16: Consolidated Annual | B16: FY2025 | C16: 3 | D16: Total RBC | E16: Provision for Credit Losses | F16: CAD millions | G16: ='05_Raw_Annual_Performance'!E8 -> 4362 | H16: 05_Raw_Annual_Performance | I16: E8
A17: Consolidated Annual | B17: FY2023 | C17: 1 | D17: Total RBC | E17: Non-Interest Expense | F17: CAD millions | G17: ='05_Raw_Annual_Performance'!C9 -> 30813 | H17: 05_Raw_Annual_Performance | I17: C9
A18: Consolidated Annual | B18: FY2024 | C18: 2 | D18: Total RBC | E18: Non-Interest Expense | F18: CAD millions | G18: ='05_Raw_Annual_Performance'!D9 -> 34250 | H18: 05_Raw_Annual_Performance | I18: D9
A19: Consolidated Annual | B19: FY2025 | C19: 3 | D19: Total RBC | E19: Non-Interest Expense | F19: CAD millions | G19: ='05_Raw_Annual_Performance'!E9 -> 36592 | H19: 05_Raw_Annual_Performance | I19: E9
A20: Consolidated Annual | B20: FY2023 | C20: 1 | D20: Total RBC | E20: Income Before Income Taxes | F20: CAD millions | G20: ='05_Raw_Annual_Performance'!C10 -> 18183 | H20: 05_Raw_Annual_Performance | I20: C10
A21: Consolidated Annual | B21: FY2024 | C21: 2 | D21: Total RBC | E21: Income Before Income Taxes | F21: CAD millions | G21: ='05_Raw_Annual_Performance'!D10 -> 19862 | H21: 05_Raw_Annual_Performance | I21: D10
A22: Consolidated Annual | B22: FY2025 | C22: 3 | D22: Total RBC | E22: Income Before Income Taxes | F22: CAD millions | G22: ='05_Raw_Annual_Performance'!E10 -> 25651 | H22: 05_Raw_Annual_Performance | I22: E10
A23: Consolidated Annual | B23: FY2023 | C23: 1 | D23: Total RBC | E23: Income Taxes | F23: CAD millions | G23: ='05_Raw_Annual_Performance'!C11 -> 3571 | H23: 05_Raw_Annual_Performance | I23: C11
A24: Consolidated Annual | B24: FY2024 | C24: 2 | D24: Total RBC | E24: Income Taxes | F24: CAD millions | G24: ='05_Raw_Annual_Performance'!D11 -> 3622 | H24: 05_Raw_Annual_Performance | I24: D11
A25: Consolidated Annual | B25: FY2025 | C25: 3 | D25: Total RBC | E25: Income Taxes | F25: CAD millions | G25: ='05_Raw_Annual_Performance'!E11 -> 5282 | H25: 05_Raw_Annual_Performance | I25: E11
A26: Consolidated Annual | B26: FY2023 | C26: 1 | D26: Total RBC | E26: Net Income | F26: CAD millions | G26: ='05_Raw_Annual_Performance'!C12 -> 14612 | H26: 05_Raw_Annual_Performance | I26: C12
A27: Consolidated Annual | B27: FY2024 | C27: 2 | D27: Total RBC | E27: Net Income | F27: CAD millions | G27: ='05_Raw_Annual_Performance'!D12 -> 16240 | H27: 05_Raw_Annual_Performance | I27: D12
A28: Consolidated Annual | B28: FY2025 | C28: 3 | D28: Total RBC | E28: Net Income | F28: CAD millions | G28: ='05_Raw_Annual_Performance'!E12 -> 20369 | H28: 05_Raw_Annual_Performance | I28: E12
A29: Consolidated Annual | B29: FY2023 | C29: 1 | D29: Total RBC | E29: Net Income Available to Common Shareholders | F29: CAD millions | G29: ='05_Raw_Annual_Performance'!C13 -> 14369 | H29: 05_Raw_Annual_Performance | I29: C13
A30: Consolidated Annual | B30: FY2024 | C30: 2 | D30: Total RBC | E30: Net Income Available to Common Shareholders | F30: CAD millions | G30: ='05_Raw_Annual_Performance'!D13 -> 15908 | H30: 05_Raw_Annual_Performance | I30: D13
A31: Consolidated Annual | B31: FY2025 | C31: 3 | D31: Total RBC | E31: Net Income Available to Common Shareholders | F31: CAD millions | G31: ='05_Raw_Annual_Performance'!E13 -> 19868 | H31: 05_Raw_Annual_Performance | I31: E13
A32: Consolidated Annual | B32: FY2023 | C32: 1 | D32: Total RBC | E32: Diluted EPS | F32: CAD per share | G32: ='05_Raw_Annual_Performance'!C14 -> 10.32 | H32: 05_Raw_Annual_Performance | I32: C14
A33: Consolidated Annual | B33: FY2024 | C33: 2 | D33: Total RBC | E33: Diluted EPS | F33: CAD per share | G33: ='05_Raw_Annual_Performance'!D14 -> 11.25 | H33: 05_Raw_Annual_Performance | I33: D14
A34: Consolidated Annual | B34: FY2025 | C34: 3 | D34: Total RBC | E34: Diluted EPS | F34: CAD per share | G34: ='05_Raw_Annual_Performance'!E14 -> 14.07 | H34: 05_Raw_Annual_Performance | I34: E14
A35: Consolidated Annual | B35: FY2023 | C35: 1 | D35: Total RBC | E35: ROE | F35: % | G35: ='05_Raw_Annual_Performance'!C15 -> 0.143 | H35: 05_Raw_Annual_Performance | I35: C15
A36: Consolidated Annual | B36: FY2024 | C36: 2 | D36: Total RBC | E36: ROE | F36: % | G36: ='05_Raw_Annual_Performance'!D15 -> 0.144 | H36: 05_Raw_Annual_Performance | I36: D15
A37: Consolidated Annual | B37: FY2025 | C37: 3 | D37: Total RBC | E37: ROE | F37: % | G37: ='05_Raw_Annual_Performance'!E15 -> 0.163 | H37: 05_Raw_Annual_Performance | I37: E15
A38: Consolidated Annual | B38: FY2023 | C38: 1 | D38: Total RBC | E38: Efficiency Ratio | F38: % | G38: ='05_Raw_Annual_Performance'!C16 -> 0.599 | H38: 05_Raw_Annual_Performance | I38: C16
A39: Consolidated Annual | B39: FY2024 | C39: 2 | D39: Total RBC | E39: Efficiency Ratio | F39: % | G39: ='05_Raw_Annual_Performance'!D16 -> 0.597 | H39: 05_Raw_Annual_Performance | I39: D16
A40: Consolidated Annual | B40: FY2025 | C40: 3 | D40: Total RBC | E40: Efficiency Ratio | F40: % | G40: ='05_Raw_Annual_Performance'!E16 -> 0.549 | H40: 05_Raw_Annual_Performance | I40: E16
A41: Consolidated Annual | B41: FY2023 | C41: 1 | D41: Total RBC | E41: Operating Leverage | F41: % | G41: ='05_Raw_Annual_Performance'!C17 -> -0.107 | H41: 05_Raw_Annual_Performance | I41: C17
A42: Consolidated Annual | B42: FY2024 | C42: 2 | D42: Total RBC | E42: Operating Leverage | F42: % | G42: ='05_Raw_Annual_Performance'!D17 -> 0.002 | H42: 05_Raw_Annual_Performance | I42: D17
A43: Consolidated Annual | B43: FY2025 | C43: 3 | D43: Total RBC | E43: Operating Leverage | F43: % | G43: ='05_Raw_Annual_Performance'!E17 -> 0.093 | H43: 05_Raw_Annual_Performance | I43: E17
A44: Consolidated Annual | B44: FY2023 | C44: 1 | D44: Total RBC | E44: PPPT Earnings | F44: CAD millions | G44: ='05_Raw_Annual_Performance'!C18 -> 20651 | H44: 05_Raw_Annual_Performance | I44: C18
A45: Consolidated Annual | B45: FY2024 | C45: 2 | D45: Total RBC | E45: PPPT Earnings | F45: CAD millions | G45: ='05_Raw_Annual_Performance'!D18 -> 23094 | H45: 05_Raw_Annual_Performance | I45: D18
A46: Consolidated Annual | B46: FY2025 | C46: 3 | D46: Total RBC | E46: PPPT Earnings | F46: CAD millions | G46: ='05_Raw_Annual_Performance'!E18 -> 30013 | H46: 05_Raw_Annual_Performance | I46: E18
A47: Consolidated Annual | B47: FY2023 | C47: 1 | D47: Total RBC | E47: Effective Tax Rate | F47: % | G47: ='05_Raw_Annual_Performance'!C19 -> 0.19639223 | H47: 05_Raw_Annual_Performance | I47: C19
A48: Consolidated Annual | B48: FY2024 | C48: 2 | D48: Total RBC | E48: Effective Tax Rate | F48: % | G48: ='05_Raw_Annual_Performance'!D19 -> 0.18235827 | H48: 05_Raw_Annual_Performance | I48: D19
A49: Consolidated Annual | B49: FY2025 | C49: 3 | D49: Total RBC | E49: Effective Tax Rate | F49: % | G49: ='05_Raw_Annual_Performance'!E19 -> 0.2059179 | H49: 05_Raw_Annual_Performance | I49: E19
A50: Consolidated Quarterly | B50: Q1 2024 | C50: 1 | D50: Total RBC | E50: Net Interest Income | F50: CAD millions | G50: ='06_Raw_Quarterly_Performance'!C5 -> 6332 | H50: 06_Raw_Quarterly_Performance | I50: C5
A51: Consolidated Quarterly | B51: Q2 2024 | C51: 2 | D51: Total RBC | E51: Net Interest Income | F51: CAD millions | G51: ='06_Raw_Quarterly_Performance'!D5 -> 6623 | H51: 06_Raw_Quarterly_Performance | I51: D5
A52: Consolidated Quarterly | B52: Q3 2024 | C52: 3 | D52: Total RBC | E52: Net Interest Income | F52: CAD millions | G52: ='06_Raw_Quarterly_Performance'!E5 -> 7327 | H52: 06_Raw_Quarterly_Performance | I52: E5
A53: Consolidated Quarterly | B53: Q4 2024 | C53: 4 | D53: Total RBC | E53: Net Interest Income | F53: CAD millions | G53: ='06_Raw_Quarterly_Performance'!F5 -> 7671 | H53: 06_Raw_Quarterly_Performance | I53: F5
A54: Consolidated Quarterly | B54: Q1 2025 | C54: 5 | D54: Total RBC | E54: Net Interest Income | F54: CAD millions | G54: ='06_Raw_Quarterly_Performance'!G5 -> 7948 | H54: 06_Raw_Quarterly_Performance | I54: G5
A55: Consolidated Quarterly | B55: Q2 2025 | C55: 6 | D55: Total RBC | E55: Net Interest Income | F55: CAD millions | G55: ='06_Raw_Quarterly_Performance'!H5 -> 8056 | H55: 06_Raw_Quarterly_Performance | I55: H5
A56: Consolidated Quarterly | B56: Q3 2025 | C56: 7 | D56: Total RBC | E56: Net Interest Income | F56: CAD millions | G56: ='06_Raw_Quarterly_Performance'!I5 -> 8351 | H56: 06_Raw_Quarterly_Performance | I56: I5
A57: Consolidated Quarterly | B57: Q4 2025 | C57: 8 | D57: Total RBC | E57: Net Interest Income | F57: CAD millions | G57: ='06_Raw_Quarterly_Performance'!J5 -> 8645 | H57: 06_Raw_Quarterly_Performance | I57: J5
A58: Consolidated Quarterly | B58: Q1 2026 | C58: 9 | D58: Total RBC | E58: Net Interest Income | F58: CAD millions | G58: ='06_Raw_Quarterly_Performance'!K5 -> 8585 | H58: 06_Raw_Quarterly_Performance | I58: K5
A59: Consolidated Quarterly | B59: Q2 2026 | C59: 10 | D59: Total RBC | E59: Net Interest Income | F59: CAD millions | G59: ='06_Raw_Quarterly_Performance'!L5 -> 8506 | H59: 06_Raw_Quarterly_Performance | I59: L5
A60: Consolidated Quarterly | B60: Q1 2024 | C60: 1 | D60: Total RBC | E60: Non-Interest Income | F60: CAD millions | G60: ='06_Raw_Quarterly_Performance'!C6 -> 7153 | H60: 06_Raw_Quarterly_Performance | I60: C6
A61: Consolidated Quarterly | B61: Q2 2024 | C61: 2 | D61: Total RBC | E61: Non-Interest Income | F61: CAD millions | G61: ='06_Raw_Quarterly_Performance'!D6 -> 7531 | H61: 06_Raw_Quarterly_Performance | I61: D6
A62: Consolidated Quarterly | B62: Q3 2024 | C62: 3 | D62: Total RBC | E62: Non-Interest Income | F62: CAD millions | G62: ='06_Raw_Quarterly_Performance'!E6 -> 7304 | H62: 06_Raw_Quarterly_Performance | I62: E6
A63: Consolidated Quarterly | B63: Q4 2024 | C63: 4 | D63: Total RBC | E63: Non-Interest Income | F63: CAD millions | G63: ='06_Raw_Quarterly_Performance'!F6 -> 7403 | H63: 06_Raw_Quarterly_Performance | I63: F6
A64: Consolidated Quarterly | B64: Q1 2025 | C64: 5 | D64: Total RBC | E64: Non-Interest Income | F64: CAD millions | G64: ='06_Raw_Quarterly_Performance'!G6 -> 8791 | H64: 06_Raw_Quarterly_Performance | I64: G6
A65: Consolidated Quarterly | B65: Q2 2025 | C65: 6 | D65: Total RBC | E65: Non-Interest Income | F65: CAD millions | G65: ='06_Raw_Quarterly_Performance'!H6 -> 7616 | H65: 06_Raw_Quarterly_Performance | I65: H6
A66: Consolidated Quarterly | B66: Q3 2025 | C66: 7 | D66: Total RBC | E66: Non-Interest Income | F66: CAD millions | G66: ='06_Raw_Quarterly_Performance'!I6 -> 8634 | H66: 06_Raw_Quarterly_Performance | I66: I6
A67: Consolidated Quarterly | B67: Q4 2025 | C67: 8 | D67: Total RBC | E67: Non-Interest Income | F67: CAD millions | G67: ='06_Raw_Quarterly_Performance'!J6 -> 8564 | H67: 06_Raw_Quarterly_Performance | I67: J6
A68: Consolidated Quarterly | B68: Q1 2026 | C68: 9 | D68: Total RBC | E68: Non-Interest Income | F68: CAD millions | G68: ='06_Raw_Quarterly_Performance'!K6 -> 9375 | H68: 06_Raw_Quarterly_Performance | I68: K6
A69: Consolidated Quarterly | B69: Q2 2026 | C69: 10 | D69: Total RBC | E69: Non-Interest Income | F69: CAD millions | G69: ='06_Raw_Quarterly_Performance'!L6 -> 8947 | H69: 06_Raw_Quarterly_Performance | I69: L6
A70: Consolidated Quarterly | B70: Q1 2024 | C70: 1 | D70: Total RBC | E70: Total Revenue | F70: CAD millions | G70: ='06_Raw_Quarterly_Performance'!C7 -> 13485 | H70: 06_Raw_Quarterly_Performance | I70: C7
A71: Consolidated Quarterly | B71: Q2 2024 | C71: 2 | D71: Total RBC | E71: Total Revenue | F71: CAD millions | G71: ='06_Raw_Quarterly_Performance'!D7 -> 14154 | H71: 06_Raw_Quarterly_Performance | I71: D7
A72: Consolidated Quarterly | B72: Q3 2024 | C72: 3 | D72: Total RBC | E72: Total Revenue | F72: CAD millions | G72: ='06_Raw_Quarterly_Performance'!E7 -> 14631 | H72: 06_Raw_Quarterly_Performance | I72: E7
A73: Consolidated Quarterly | B73: Q4 2024 | C73: 4 | D73: Total RBC | E73: Total Revenue | F73: CAD millions | G73: ='06_Raw_Quarterly_Performance'!F7 -> 15074 | H73: 06_Raw_Quarterly_Performance | I73: F7
A74: Consolidated Quarterly | B74: Q1 2025 | C74: 5 | D74: Total RBC | E74: Total Revenue | F74: CAD millions | G74: ='06_Raw_Quarterly_Performance'!G7 -> 16739 | H74: 06_Raw_Quarterly_Performance | I74: G7
A75: Consolidated Quarterly | B75: Q2 2025 | C75: 6 | D75: Total RBC | E75: Total Revenue | F75: CAD millions | G75: ='06_Raw_Quarterly_Performance'!H7 -> 15672 | H75: 06_Raw_Quarterly_Performance | I75: H7
A76: Consolidated Quarterly | B76: Q3 2025 | C76: 7 | D76: Total RBC | E76: Total Revenue | F76: CAD millions | G76: ='06_Raw_Quarterly_Performance'!I7 -> 16985 | H76: 06_Raw_Quarterly_Performance | I76: I7
A77: Consolidated Quarterly | B77: Q4 2025 | C77: 8 | D77: Total RBC | E77: Total Revenue | F77: CAD millions | G77: ='06_Raw_Quarterly_Performance'!J7 -> 17209 | H77: 06_Raw_Quarterly_Performance | I77: J7
A78: Consolidated Quarterly | B78: Q1 2026 | C78: 9 | D78: Total RBC | E78: Total Revenue | F78: CAD millions | G78: ='06_Raw_Quarterly_Performance'!K7 -> 17960 | H78: 06_Raw_Quarterly_Performance | I78: K7
A79: Consolidated Quarterly | B79: Q2 2026 | C79: 10 | D79: Total RBC | E79: Total Revenue | F79: CAD millions | G79: ='06_Raw_Quarterly_Performance'!L7 -> 17453 | H79: 06_Raw_Quarterly_Performance | I79: L7
A80: Consolidated Quarterly | B80: Q1 2024 | C80: 1 | D80: Total RBC | E80: Provision for Credit Losses | F80: CAD millions | G80: ='06_Raw_Quarterly_Performance'!C8 -> 813 | H80: 06_Raw_Quarterly_Performance | I80: C8
A81: Consolidated Quarterly | B81: Q2 2024 | C81: 2 | D81: Total RBC | E81: Provision for Credit Losses | F81: CAD millions | G81: ='06_Raw_Quarterly_Performance'!D8 -> 920 | H81: 06_Raw_Quarterly_Performance | I81: D8
A82: Consolidated Quarterly | B82: Q3 2024 | C82: 3 | D82: Total RBC | E82: Provision for Credit Losses | F82: CAD millions | G82: ='06_Raw_Quarterly_Performance'!E8 -> 659 | H82: 06_Raw_Quarterly_Performance | I82: E8
A83: Consolidated Quarterly | B83: Q4 2024 | C83: 4 | D83: Total RBC | E83: Provision for Credit Losses | F83: CAD millions | G83: ='06_Raw_Quarterly_Performance'!F8 -> 840 | H83: 06_Raw_Quarterly_Performance | I83: F8
A84: Consolidated Quarterly | B84: Q1 2025 | C84: 5 | D84: Total RBC | E84: Provision for Credit Losses | F84: CAD millions | G84: ='06_Raw_Quarterly_Performance'!G8 -> 1050 | H84: 06_Raw_Quarterly_Performance | I84: G8
A85: Consolidated Quarterly | B85: Q2 2025 | C85: 6 | D85: Total RBC | E85: Provision for Credit Losses | F85: CAD millions | G85: ='06_Raw_Quarterly_Performance'!H8 -> 1424 | H85: 06_Raw_Quarterly_Performance | I85: H8
A86: Consolidated Quarterly | B86: Q3 2025 | C86: 7 | D86: Total RBC | E86: Provision for Credit Losses | F86: CAD millions | G86: ='06_Raw_Quarterly_Performance'!I8 -> 881 | H86: 06_Raw_Quarterly_Performance | I86: I8
A87: Consolidated Quarterly | B87: Q4 2025 | C87: 8 | D87: Total RBC | E87: Provision for Credit Losses | F87: CAD millions | G87: ='06_Raw_Quarterly_Performance'!J8 -> 1007 | H87: 06_Raw_Quarterly_Performance | I87: J8
A88: Consolidated Quarterly | B88: Q1 2026 | C88: 9 | D88: Total RBC | E88: Provision for Credit Losses | F88: CAD millions | G88: ='06_Raw_Quarterly_Performance'!K8 -> 1090 | H88: 06_Raw_Quarterly_Performance | I88: K8
A89: Consolidated Quarterly | B89: Q2 2026 | C89: 10 | D89: Total RBC | E89: Provision for Credit Losses | F89: CAD millions | G89: ='06_Raw_Quarterly_Performance'!L8 -> 912 | H89: 06_Raw_Quarterly_Performance | I89: L8
A90: Consolidated Quarterly | B90: Q1 2024 | C90: 1 | D90: Total RBC | E90: Non-Interest Expense | F90: CAD millions | G90: ='06_Raw_Quarterly_Performance'!C9 -> 8324 | H90: 06_Raw_Quarterly_Performance | I90: C9
A91: Consolidated Quarterly | B91: Q2 2024 | C91: 2 | D91: Total RBC | E91: Non-Interest Expense | F91: CAD millions | G91: ='06_Raw_Quarterly_Performance'!D9 -> 8308 | H91: 06_Raw_Quarterly_Performance | I91: D9
A92: Consolidated Quarterly | B92: Q3 2024 | C92: 3 | D92: Total RBC | E92: Non-Interest Expense | F92: CAD millions | G92: ='06_Raw_Quarterly_Performance'!E9 -> 8599 | H92: 06_Raw_Quarterly_Performance | I92: E9
A93: Consolidated Quarterly | B93: Q4 2024 | C93: 4 | D93: Total RBC | E93: Non-Interest Expense | F93: CAD millions | G93: ='06_Raw_Quarterly_Performance'!F9 -> 9019 | H93: 06_Raw_Quarterly_Performance | I93: F9
A94: Consolidated Quarterly | B94: Q1 2025 | C94: 5 | D94: Total RBC | E94: Non-Interest Expense | F94: CAD millions | G94: ='06_Raw_Quarterly_Performance'!G9 -> 9256 | H94: 06_Raw_Quarterly_Performance | I94: G9
A95: Consolidated Quarterly | B95: Q2 2025 | C95: 6 | D95: Total RBC | E95: Non-Interest Expense | F95: CAD millions | G95: ='06_Raw_Quarterly_Performance'!H9 -> 8730 | H95: 06_Raw_Quarterly_Performance | I95: H9
A96: Consolidated Quarterly | B96: Q3 2025 | C96: 7 | D96: Total RBC | E96: Non-Interest Expense | F96: CAD millions | G96: ='06_Raw_Quarterly_Performance'!I9 -> 9232 | H96: 06_Raw_Quarterly_Performance | I96: I9
A97: Consolidated Quarterly | B97: Q4 2025 | C97: 8 | D97: Total RBC | E97: Non-Interest Expense | F97: CAD millions | G97: ='06_Raw_Quarterly_Performance'!J9 -> 9374 | H97: 06_Raw_Quarterly_Performance | I97: J9
A98: Consolidated Quarterly | B98: Q1 2026 | C98: 9 | D98: Total RBC | E98: Non-Interest Expense | F98: CAD millions | G98: ='06_Raw_Quarterly_Performance'!K9 -> 9463 | H98: 06_Raw_Quarterly_Performance | I98: K9
A99: Consolidated Quarterly | B99: Q2 2026 | C99: 10 | D99: Total RBC | E99: Non-Interest Expense | F99: CAD millions | G99: ='06_Raw_Quarterly_Performance'!L9 -> 9437 | H99: 06_Raw_Quarterly_Performance | I99: L9
A100: Consolidated Quarterly | B100: Q1 2024 | C100: 1 | D100: Total RBC | E100: Income Before Income Taxes | F100: CAD millions | G100: ='06_Raw_Quarterly_Performance'!C10 -> 4348 | H100: 06_Raw_Quarterly_Performance | I100: C10
A101: Consolidated Quarterly | B101: Q2 2024 | C101: 2 | D101: Total RBC | E101: Income Before Income Taxes | F101: CAD millions | G101: ='06_Raw_Quarterly_Performance'!D10 -> 4926 | H101: 06_Raw_Quarterly_Performance | I101: D10
...

Sheet 24_Pivot_Summary
A1: PIVOT-READY SEGMENT MANAGEMENT SUMMARY
A3: Formula-driven summary using the RBC_Pivot_Source Excel Table. A native PivotTable can be inserted from Sheet 23.
A5: Control | B5: Selection
A6: Selected Segment Metric | B6: Net Income
A8: Segment | B8: FY2023 | C8: FY2024 | D8: FY2025 | E8: Q1 2026 | F8: Q2 2026 | G8: FY23–FY25 Change | H8: FY2025 Rank | I8: Comment
A9: Personal Banking | B9: =IF(COUNTIFS('23_Pivot_Source'!$A$5:$A$439,"Segment",'23_Pivot_Source'!$B$5:$B$439,B$8,'23_Pivot_Source'!$D$5:$D$439,$A9,'23_Pivot_Source'!$E$5:$E$439,$B$6,'23_Pivot_Source'!$G$5:$G$439,"<>")=0,"",SUMIFS('23_Pivot_Source'!$G$5:$G$439,'23_Pivot_Source'!$A$5:$A$439,"Segment",'23_Pivot_Source'!$B$5:$B$439,B$8,'23_Pivot_Source'!$D$5:$D$439,$A9,'23_Pivot_Source'!$E$5:$E$439,$B$6)) -> 5418 | C9: =IF(COUNTIFS('23_Pivot_Source'!$A$5:$A$439,"Segment",'23_Pivot_Source'!$B$5:$B$439,C$8,'23_Pivot_Source'!$D$5:$D$439,$A9,'23_Pivot_Source'!$E$5:$E$439,$B$6,'23_Pivot_Source'!$G$5:$G$439,"<>")=0,"",SUMIFS('23_Pivot_Source'!$G$5:$G$439,'23_Pivot_Source'!$A$5:$A$439,"Segment",'23_Pivot_Source'!$B$5:$B$439,C$8,'23_Pivot_Source'!$D$5:$D$439,$A9,'23_Pivot_Source'!$E$5:$E$439,$B$6)) -> 5921 | D9: =IF(COUNTIFS('23_Pivot_Source'!$A$5:$A$439,"Segment",'23_Pivot_Source'!$B$5:$B$439,D$8,'23_Pivot_Source'!$D$5:$D$439,$A9,'23_Pivot_Source'!$E$5:$E$439,$B$6,'23_Pivot_Source'!$G$5:$G$439,"<>")=0,"",SUMIFS('23_Pivot_Source'!$G$5:$G$439,'23_Pivot_Source'!$A$5:$A$439,"Segment",'23_Pivot_Source'!$B$5:$B$439,D$8,'23_Pivot_Source'!$D$5:$D$439,$A9,'23_Pivot_Source'!$E$5:$E$439,$B$6)) -> 7105 | E9: =IF(COUNTIFS('23_Pivot_Source'!$A$5:$A$439,"Segment",'23_Pivot_Source'!$B$5:$B$439,E$8,'23_Pivot_Source'!$D$5:$D$439,$A9,'23_Pivot_Source'!$E$5:$E$439,$B$6,'23_Pivot_Source'!$G$5:$G$439,"<>")=0,"",SUMIFS('23_Pivot_Source'!$G$5:$G$439,'23_Pivot_Source'!$A$5:$A$439,"Segment",'23_Pivot_Source'!$B$5:$B$439,E$8,'23_Pivot_Source'!$D$5:$D$439,$A9,'23_Pivot_Source'!$E$5:$E$439,$B$6)) -> 1962 | F9: =IF(COUNTIFS('23_Pivot_Source'!$A$5:$A$439,"Segment",'23_Pivot_Source'!$B$5:$B$439,F$8,'23_Pivot_Source'!$D$5:$D$439,$A9,'23_Pivot_Source'!$E$5:$E$439,$B$6,'23_Pivot_Source'!$G$5:$G$439,"<>")=0,"",SUMIFS('23_Pivot_Source'!$G$5:$G$439,'23_Pivot_Source'!$A$5:$A$439,"Segment",'23_Pivot_Source'!$B$5:$B$439,F$8,'23_Pivot_Source'!$D$5:$D$439,$A9,'23_Pivot_Source'!$E$5:$E$439,$B$6)) -> 1870 | G9: =IF(OR(B9="",D9=""),"",IFERROR(D9/B9-1,"")) -> 0.31136951 | H9: =IF(D9="","",COUNTIF($D$9:$D$14,">"&D9)+COUNTIF($D$9:D9,D9)) -> 1 | I9: Largest domestic banking franchise.
A10: Commercial Banking | B10: =IF(COUNTIFS('23_Pivot_Source'!$A$5:$A$439,"Segment",'23_Pivot_Source'!$B$5:$B$439,B$8,'23_Pivot_Source'!$D$5:$D$439,$A10,'23_Pivot_Source'!$E$5:$E$439,$B$6,'23_Pivot_Source'!$G$5:$G$439,"<>")=0,"",SUMIFS('23_Pivot_Source'!$G$5:$G$439,'23_Pivot_Source'!$A$5:$A$439,"Segment",'23_Pivot_Source'!$B$5:$B$439,B$8,'23_Pivot_Source'!$D$5:$D$439,$A10,'23_Pivot_Source'!$E$5:$E$439,$B$6)) -> 2582 | C10: =IF(COUNTIFS('23_Pivot_Source'!$A$5:$A$439,"Segment",'23_Pivot_Source'!$B$5:$B$439,C$8,'23_Pivot_Source'!$D$5:$D$439,$A10,'23_Pivot_Source'!$E$5:$E$439,$B$6,'23_Pivot_Source'!$G$5:$G$439,"<>")=0,"",SUMIFS('23_Pivot_Source'!$G$5:$G$439,'23_Pivot_Source'!$A$5:$A$439,"Segment",'23_Pivot_Source'!$B$5:$B$439,C$8,'23_Pivot_Source'!$D$5:$D$439,$A10,'23_Pivot_Source'!$E$5:$E$439,$B$6)) -> 2818 | D10: =IF(COUNTIFS('23_Pivot_Source'!$A$5:$A$439,"Segment",'23_Pivot_Source'!$B$5:$B$439,D$8,'23_Pivot_Source'!$D$5:$D$439,$A10,'23_Pivot_Source'!$E$5:$E$439,$B$6,'23_Pivot_Source'!$G$5:$G$439,"<>")=0,"",SUMIFS('23_Pivot_Source'!$G$5:$G$439,'23_Pivot_Source'!$A$5:$A$439,"Segment",'23_Pivot_Source'!$B$5:$B$439,D$8,'23_Pivot_Source'!$D$5:$D$439,$A10,'23_Pivot_Source'!$E$5:$E$439,$B$6)) -> 3020 | E10: =IF(COUNTIFS('23_Pivot_Source'!$A$5:$A$439,"Segment",'23_Pivot_Source'!$B$5:$B$439,E$8,'23_Pivot_Source'!$D$5:$D$439,$A10,'23_Pivot_Source'!$E$5:$E$439,$B$6,'23_Pivot_Source'!$G$5:$G$439,"<>")=0,"",SUMIFS('23_Pivot_Source'!$G$5:$G$439,'23_Pivot_Source'!$A$5:$A$439,"Segment",'23_Pivot_Source'!$B$5:$B$439,E$8,'23_Pivot_Source'!$D$5:$D$439,$A10,'23_Pivot_Source'!$E$5:$E$439,$B$6)) -> 863 | F10: =IF(COUNTIFS('23_Pivot_Source'!$A$5:$A$439,"Segment",'23_Pivot_Source'!$B$5:$B$439,F$8,'23_Pivot_Source'!$D$5:$D$439,$A10,'23_Pivot_Source'!$E$5:$E$439,$B$6,'23_Pivot_Source'!$G$5:$G$439,"<>")=0,"",SUMIFS('23_Pivot_Source'!$G$5:$G$439,'23_Pivot_Source'!$A$5:$A$439,"Segment",'23_Pivot_Source'!$B$5:$B$439,F$8,'23_Pivot_Source'!$D$5:$D$439,$A10,'23_Pivot_Source'!$E$5:$E$439,$B$6)) -> 854 | G10: =IF(OR(B10="",D10=""),"",IFERROR(D10/B10-1,"")) -> 0.16963594 | H10: =IF(D10="","",COUNTIF($D$9:$D$14,">"&D10)+COUNTIF($D$9:D10,D10)) -> 4 | I10: Efficient but credit-cycle sensitive.
A11: Wealth Management | B11: =IF(COUNTIFS('23_Pivot_Source'!$A$5:$A$439,"Segment",'23_Pivot_Source'!$B$5:$B$439,B$8,'23_Pivot_Source'!$D$5:$D$439,$A11,'23_Pivot_Source'!$E$5:$E$439,$B$6,'23_Pivot_Source'!$G$5:$G$439,"<>")=0,"",SUMIFS('23_Pivot_Source'!$G$5:$G$439,'23_Pivot_Source'!$A$5:$A$439,"Segment",'23_Pivot_Source'!$B$5:$B$439,B$8,'23_Pivot_Source'!$D$5:$D$439,$A11,'23_Pivot_Source'!$E$5:$E$439,$B$6)) -> 2693 | C11: =IF(COUNTIFS('23_Pivot_Source'!$A$5:$A$439,"Segment",'23_Pivot_Source'!$B$5:$B$439,C$8,'23_Pivot_Source'!$D$5:$D$439,$A11,'23_Pivot_Source'!$E$5:$E$439,$B$6,'23_Pivot_Source'!$G$5:$G$439,"<>")=0,"",SUMIFS('23_Pivot_Source'!$G$5:$G$439,'23_Pivot_Source'!$A$5:$A$439,"Segment",'23_Pivot_Source'!$B$5:$B$439,C$8,'23_Pivot_Source'!$D$5:$D$439,$A11,'23_Pivot_Source'!$E$5:$E$439,$B$6)) -> 3422 | D11: =IF(COUNTIFS('23_Pivot_Source'!$A$5:$A$439,"Segment",'23_Pivot_Source'!$B$5:$B$439,D$8,'23_Pivot_Source'!$D$5:$D$439,$A11,'23_Pivot_Source'!$E$5:$E$439,$B$6,'23_Pivot_Source'!$G$5:$G$439,"<>")=0,"",SUMIFS('23_Pivot_Source'!$G$5:$G$439,'23_Pivot_Source'!$A$5:$A$439,"Segment",'23_Pivot_Source'!$B$5:$B$439,D$8,'23_Pivot_Source'!$D$5:$D$439,$A11,'23_Pivot_Source'!$E$5:$E$439,$B$6)) -> 4289 | E11: =IF(COUNTIFS('23_Pivot_Source'!$A$5:$A$439,"Segment",'23_Pivot_Source'!$B$5:$B$439,E$8,'23_Pivot_Source'!$D$5:$D$439,$A11,'23_Pivot_Source'!$E$5:$E$439,$B$6,'23_Pivot_Source'!$G$5:$G$439,"<>")=0,"",SUMIFS('23_Pivot_Source'!$G$5:$G$439,'23_Pivot_Source'!$A$5:$A$439,"Segment",'23_Pivot_Source'!$B$5:$B$439,E$8,'23_Pivot_Source'!$D$5:$D$439,$A11,'23_Pivot_Source'!$E$5:$E$439,$B$6)) -> 1295 | F11: =IF(COUNTIFS('23_Pivot_Source'!$A$5:$A$439,"Segment",'23_Pivot_Source'!$B$5:$B$439,F$8,'23_Pivot_Source'!$D$5:$D$439,$A11,'23_Pivot_Source'!$E$5:$E$439,$B$6,'23_Pivot_Source'!$G$5:$G$439,"<>")=0,"",SUMIFS('23_Pivot_Source'!$G$5:$G$439,'23_Pivot_Source'!$A$5:$A$439,"Segment",'23_Pivot_Source'!$B$5:$B$439,F$8,'23_Pivot_Source'!$D$5:$D$439,$A11,'23_Pivot_Source'!$E$5:$E$439,$B$6)) -> 1185 | G11: =IF(OR(B11="",D11=""),"",IFERROR(D11/B11-1,"")) -> 0.5926476 | H11: =IF(D11="","",COUNTIF($D$9:$D$14,">"&D11)+COUNTIF($D$9:D11,D11)) -> 3 | I11: Fee-based and market-sensitive.
A12: Insurance | B12: =IF(COUNTIFS('23_Pivot_Source'!$A$5:$A$439,"Segment",'23_Pivot_Source'!$B$5:$B$439,B$8,'23_Pivot_Source'!$D$5:$D$439,$A12,'23_Pivot_Source'!$E$5:$E$439,$B$6,'23_Pivot_Source'!$G$5:$G$439,"<>")=0,"",SUMIFS('23_Pivot_Source'!$G$5:$G$439,'23_Pivot_Source'!$A$5:$A$439,"Segment",'23_Pivot_Source'!$B$5:$B$439,B$8,'23_Pivot_Source'!$D$5:$D$439,$A12,'23_Pivot_Source'!$E$5:$E$439,$B$6)) -> 549 | C12: =IF(COUNTIFS('23_Pivot_Source'!$A$5:$A$439,"Segment",'23_Pivot_Source'!$B$5:$B$439,C$8,'23_Pivot_Source'!$D$5:$D$439,$A12,'23_Pivot_Source'!$E$5:$E$439,$B$6,'23_Pivot_Source'!$G$5:$G$439,"<>")=0,"",SUMIFS('23_Pivot_Source'!$G$5:$G$439,'23_Pivot_Source'!$A$5:$A$439,"Segment",'23_Pivot_Source'!$B$5:$B$439,C$8,'23_Pivot_Source'!$D$5:$D$439,$A12,'23_Pivot_Source'!$E$5:$E$439,$B$6)) -> 729 | D12: =IF(COUNTIFS('23_Pivot_Source'!$A$5:$A$439,"Segment",'23_Pivot_Source'!$B$5:$B$439,D$8,'23_Pivot_Source'!$D$5:$D$439,$A12,'23_Pivot_Source'!$E$5:$E$439,$B$6,'23_Pivot_Source'!$G$5:$G$439,"<>")=0,"",SUMIFS('23_Pivot_Source'!$G$5:$G$439,'23_Pivot_Source'!$A$5:$A$439,"Segment",'23_Pivot_Source'!$B$5:$B$439,D$8,'23_Pivot_Source'!$D$5:$D$439,$A12,'23_Pivot_Source'!$E$5:$E$439,$B$6)) -> 828 | E12: =IF(COUNTIFS('23_Pivot_Source'!$A$5:$A$439,"Segment",'23_Pivot_Source'!$B$5:$B$439,E$8,'23_Pivot_Source'!$D$5:$D$439,$A12,'23_Pivot_Source'!$E$5:$E$439,$B$6,'23_Pivot_Source'!$G$5:$G$439,"<>")=0,"",SUMIFS('23_Pivot_Source'!$G$5:$G$439,'23_Pivot_Source'!$A$5:$A$439,"Segment",'23_Pivot_Source'!$B$5:$B$439,E$8,'23_Pivot_Source'!$D$5:$D$439,$A12,'23_Pivot_Source'!$E$5:$E$439,$B$6)) -> 213 | F12: =IF(COUNTIFS('23_Pivot_Source'!$A$5:$A$439,"Segment",'23_Pivot_Source'!$B$5:$B$439,F$8,'23_Pivot_Source'!$D$5:$D$439,$A12,'23_Pivot_Source'!$E$5:$E$439,$B$6,'23_Pivot_Source'!$G$5:$G$439,"<>")=0,"",SUMIFS('23_Pivot_Source'!$G$5:$G$439,'23_Pivot_Source'!$A$5:$A$439,"Segment",'23_Pivot_Source'!$B$5:$B$439,F$8,'23_Pivot_Source'!$D$5:$D$439,$A12,'23_Pivot_Source'!$E$5:$E$439,$B$6)) -> 218 | G12: =IF(OR(B12="",D12=""),"",IFERROR(D12/B12-1,"")) -> 0.50819672 | H12: =IF(D12="","",COUNTIF($D$9:$D$14,">"&D12)+COUNTIF($D$9:D12,D12)) -> 5 | I12: Smaller, capital-efficient contributor.
A13: Capital Markets | B13: =IF(COUNTIFS('23_Pivot_Source'!$A$5:$A$439,"Segment",'23_Pivot_Source'!$B$5:$B$439,B$8,'23_Pivot_Source'!$D$5:$D$439,$A13,'23_Pivot_Source'!$E$5:$E$439,$B$6,'23_Pivot_Source'!$G$5:$G$439,"<>")=0,"",SUMIFS('23_Pivot_Source'!$G$5:$G$439,'23_Pivot_Source'!$A$5:$A$439,"Segment",'23_Pivot_Source'!$B$5:$B$439,B$8,'23_Pivot_Source'!$D$5:$D$439,$A13,'23_Pivot_Source'!$E$5:$E$439,$B$6)) -> 4139 | C13: =IF(COUNTIFS('23_Pivot_Source'!$A$5:$A$439,"Segment",'23_Pivot_Source'!$B$5:$B$439,C$8,'23_Pivot_Source'!$D$5:$D$439,$A13,'23_Pivot_Source'!$E$5:$E$439,$B$6,'23_Pivot_Source'!$G$5:$G$439,"<>")=0,"",SUMIFS('23_Pivot_Source'!$G$5:$G$439,'23_Pivot_Source'!$A$5:$A$439,"Segment",'23_Pivot_Source'!$B$5:$B$439,C$8,'23_Pivot_Source'!$D$5:$D$439,$A13,'23_Pivot_Source'!$E$5:$E$439,$B$6)) -> 4573 | D13: =IF(COUNTIFS('23_Pivot_Source'!$A$5:$A$439,"Segment",'23_Pivot_Source'!$B$5:$B$439,D$8,'23_Pivot_Source'!$D$5:$D$439,$A13,'23_Pivot_Source'!$E$5:$E$439,$B$6,'23_Pivot_Source'!$G$5:$G$439,"<>")=0,"",SUMIFS('23_Pivot_Source'!$G$5:$G$439,'23_Pivot_Source'!$A$5:$A$439,"Segment",'23_Pivot_Source'!$B$5:$B$439,D$8,'23_Pivot_Source'!$D$5:$D$439,$A13,'23_Pivot_Source'!$E$5:$E$439,$B$6)) -> 5393 | E13: =IF(COUNTIFS('23_Pivot_Source'!$A$5:$A$439,"Segment",'23_Pivot_Source'!$B$5:$B$439,E$8,'23_Pivot_Source'!$D$5:$D$439,$A13,'23_Pivot_Source'!$E$5:$E$439,$B$6,'23_Pivot_Source'!$G$5:$G$439,"<>")=0,"",SUMIFS('23_Pivot_Source'!$G$5:$G$439,'23_Pivot_Source'!$A$5:$A$439,"Segment",'23_Pivot_Source'!$B$5:$B$439,E$8,'23_Pivot_Source'!$D$5:$D$439,$A13,'23_Pivot_Source'!$E$5:$E$439,$B$6)) -> 1478 | F13: =IF(COUNTIFS('23_Pivot_Source'!$A$5:$A$439,"Segment",'23_Pivot_Source'!$B$5:$B$439,F$8,'23_Pivot_Source'!$D$5:$D$439,$A13,'23_Pivot_Source'!$E$5:$E$439,$B$6,'23_Pivot_Source'!$G$5:$G$439,"<>")=0,"",SUMIFS('23_Pivot_Source'!$G$5:$G$439,'23_Pivot_Source'!$A$5:$A$439,"Segment",'23_Pivot_Source'!$B$5:$B$439,F$8,'23_Pivot_Source'!$D$5:$D$439,$A13,'23_Pivot_Source'!$E$5:$E$439,$B$6)) -> 1484 | G13: =IF(OR(B13="",D13=""),"",IFERROR(D13/B13-1,"")) -> 0.30297173 | H13: =IF(D13="","",COUNTIF($D$9:$D$14,">"&D13)+COUNTIF($D$9:D13,D13)) -> 2 | I13: Strong earnings with market volatility.
A14: Corporate Support | B14: =IF(COUNTIFS('23_Pivot_Source'!$A$5:$A$439,"Segment",'23_Pivot_Source'!$B$5:$B$439,B$8,'23_Pivot_Source'!$D$5:$D$439,$A14,'23_Pivot_Source'!$E$5:$E$439,$B$6,'23_Pivot_Source'!$G$5:$G$439,"<>")=0,"",SUMIFS('23_Pivot_Source'!$G$5:$G$439,'23_Pivot_Source'!$A$5:$A$439,"Segment",'23_Pivot_Source'!$B$5:$B$439,B$8,'23_Pivot_Source'!$D$5:$D$439,$A14,'23_Pivot_Source'!$E$5:$E$439,$B$6)) -> -769 | C14: =IF(COUNTIFS('23_Pivot_Source'!$A$5:$A$439,"Segment",'23_Pivot_Source'!$B$5:$B$439,C$8,'23_Pivot_Source'!$D$5:$D$439,$A14,'23_Pivot_Source'!$E$5:$E$439,$B$6,'23_Pivot_Source'!$G$5:$G$439,"<>")=0,"",SUMIFS('23_Pivot_Source'!$G$5:$G$439,'23_Pivot_Source'!$A$5:$A$439,"Segment",'23_Pivot_Source'!$B$5:$B$439,C$8,'23_Pivot_Source'!$D$5:$D$439,$A14,'23_Pivot_Source'!$E$5:$E$439,$B$6)) -> -1223 | D14: =IF(COUNTIFS('23_Pivot_Source'!$A$5:$A$439,"Segment",'23_Pivot_Source'!$B$5:$B$439,D$8,'23_Pivot_Source'!$D$5:$D$439,$A14,'23_Pivot_Source'!$E$5:$E$439,$B$6,'23_Pivot_Source'!$G$5:$G$439,"<>")=0,"",SUMIFS('23_Pivot_Source'!$G$5:$G$439,'23_Pivot_Source'!$A$5:$A$439,"Segment",'23_Pivot_Source'!$B$5:$B$439,D$8,'23_Pivot_Source'!$D$5:$D$439,$A14,'23_Pivot_Source'!$E$5:$E$439,$B$6)) -> -266 | E14: =IF(COUNTIFS('23_Pivot_Source'!$A$5:$A$439,"Segment",'23_Pivot_Source'!$B$5:$B$439,E$8,'23_Pivot_Source'!$D$5:$D$439,$A14,'23_Pivot_Source'!$E$5:$E$439,$B$6,'23_Pivot_Source'!$G$5:$G$439,"<>")=0,"",SUMIFS('23_Pivot_Source'!$G$5:$G$439,'23_Pivot_Source'!$A$5:$A$439,"Segment",'23_Pivot_Source'!$B$5:$B$439,E$8,'23_Pivot_Source'!$D$5:$D$439,$A14,'23_Pivot_Source'!$E$5:$E$439,$B$6)) -> -26 | F14: =IF(COUNTIFS('23_Pivot_Source'!$A$5:$A$439,"Segment",'23_Pivot_Source'!$B$5:$B$439,F$8,'23_Pivot_Source'!$D$5:$D$439,$A14,'23_Pivot_Source'!$E$5:$E$439,$B$6,'23_Pivot_Source'!$G$5:$G$439,"<>")=0,"",SUMIFS('23_Pivot_Source'!$G$5:$G$439,'23_Pivot_Source'!$A$5:$A$439,"Segment",'23_Pivot_Source'!$B$5:$B$439,F$8,'23_Pivot_Source'!$D$5:$D$439,$A14,'23_Pivot_Source'!$E$5:$E$439,$B$6)) -> -102 | G14: =IF(OR(B14="",D14=""),"",IFERROR(D14/B14-1,"")) -> -0.65409623 | H14: =IF(D14="","",COUNTIF($D$9:$D$14,">"&D14)+COUNTIF($D$9:D14,D14)) -> 6 | I14: Treasury and consolidation items.
A16: Grand Total / Average | B16: =IF(OR($B$6="ROE",$B$6="Efficiency Ratio"),IFERROR(AVERAGE(B9:B14),""),SUM(B9:B14)) -> 14612 | C16: =IF(OR($B$6="ROE",$B$6="Efficiency Ratio"),IFERROR(AVERAGE(C9:C14),""),SUM(C9:C14)) -> 16240 | D16: =IF(OR($B$6="ROE",$B$6="Efficiency Ratio"),IFERROR(AVERAGE(D9:D14),""),SUM(D9:D14)) -> 20369 | E16: =IF(OR($B$6="ROE",$B$6="Efficiency Ratio"),IFERROR(AVERAGE(E9:E14),""),SUM(E9:E14)) -> 5785 | F16: =IF(OR($B$6="ROE",$B$6="Efficiency Ratio"),IFERROR(AVERAGE(F9:F14),""),SUM(F9:F14)) -> 5509 | G16: =IFERROR(D16/B16-1,"") -> 0.39399124 | H16: —
A20: HOW TO CREATE A NATIVE PIVOTTABLE
A21: 1 | B21: Open Sheet 23_Pivot_Source and click inside the RBC_Pivot_Source table.
A22: 2 | B22: Choose Insert → PivotTable → From Table/Range → New Worksheet.
A23: 3 | B23: Filters: Analysis Type and Metric.
A24: 4 | B24: Rows: Segment.
A25: 5 | B25: Columns: Period.
A26: 6 | B26: Values: Sum of Value. Change to Average for ROE or Efficiency Ratio.
A27: 7 | B27: Optional: add slicers for Period, Metric and Analysis Type.

Sheet 25_Data_Audit
A1: RBC MODEL DATA AUDIT & RECONCILIATION
A3: The checks below verify arithmetic integrity, period reconciliation and corrected source mappings.
A5: Annual Income Statement Reconciliation
A6: Check | B6: FY2023 Actual | C6: FY2023 Expected | D6: FY2024 Actual | E6: FY2024 Expected | F6: FY2025 Actual | G6: FY2025 Expected | H6: Maximum Difference | I6: Status | J6: Explanation
A7: Revenue = NII + Non-Interest Income | B7: ='05_Raw_Annual_Performance'!C7 -> 51464 | C7: ='05_Raw_Annual_Performance'!C5+'05_Raw_Annual_Performance'!C6 -> 51464 | D7: ='05_Raw_Annual_Performance'!D7 -> 57344 | E7: ='05_Raw_Annual_Performance'!D5+'05_Raw_Annual_Performance'!D6 -> 57344 | F7: ='05_Raw_Annual_Performance'!E7 -> 66605 | G7: ='05_Raw_Annual_Performance'!E5+'05_Raw_Annual_Performance'!E6 -> 66605 | H7: =MAX(ABS(B7-C7),ABS(D7-E7),ABS(F7-G7)) -> 0 | I7: =IF(H7=0,"PASS","REVIEW") -> PASS | J7: Reported revenue reconciles to its two main components.
A8: Pre-tax Income = Revenue - PCL - Expense | B8: ='05_Raw_Annual_Performance'!C10 -> 18183 | C8: ='05_Raw_Annual_Performance'!C7-'05_Raw_Annual_Performance'!C8-'05_Raw_Annual_Performance'!C9 -> 18183 | D8: ='05_Raw_Annual_Performance'!D10 -> 19862 | E8: ='05_Raw_Annual_Performance'!D7-'05_Raw_Annual_Performance'!D8-'05_Raw_Annual_Performance'!D9 -> 19862 | F8: ='05_Raw_Annual_Performance'!E10 -> 25651 | G8: ='05_Raw_Annual_Performance'!E7-'05_Raw_Annual_Performance'!E8-'05_Raw_Annual_Performance'!E9 -> 25651 | H8: =MAX(ABS(B8-C8),ABS(D8-E8),ABS(F8-G8)) -> 0 | I8: =IF(H8=0,"PASS","REVIEW") -> PASS | J8: Pre-tax earnings reconcile to revenue less PCL and non-interest expense.
A9: Net Income = Pre-tax Income - Tax | B9: ='05_Raw_Annual_Performance'!C12 -> 14612 | C9: ='05_Raw_Annual_Performance'!C10-'05_Raw_Annual_Performance'!C11 -> 14612 | D9: ='05_Raw_Annual_Performance'!D12 -> 16240 | E9: ='05_Raw_Annual_Performance'!D10-'05_Raw_Annual_Performance'!D11 -> 16240 | F9: ='05_Raw_Annual_Performance'!E12 -> 20369 | G9: ='05_Raw_Annual_Performance'!E10-'05_Raw_Annual_Performance'!E11 -> 20369 | H9: =MAX(ABS(B9-C9),ABS(D9-E9),ABS(F9-G9)) -> 0 | I9: =IF(H9=0,"PASS","REVIEW") -> PASS | J9: Net income reconciles after income tax.
A10: PPPT = Pre-tax Income + PCL | B10: ='05_Raw_Annual_Performance'!C18 -> 20651 | C10: ='05_Raw_Annual_Performance'!C10+'05_Raw_Annual_Performance'!C8 -> 20651 | D10: ='05_Raw_Annual_Performance'!D18 -> 23094 | E10: ='05_Raw_Annual_Performance'!D10+'05_Raw_Annual_Performance'!D8 -> 23094 | F10: ='05_Raw_Annual_Performance'!E18 -> 30013 | G10: ='05_Raw_Annual_Performance'!E10+'05_Raw_Annual_Performance'!E8 -> 30013 | H10: =MAX(ABS(B10-C10),ABS(D10-E10),ABS(F10-G10)) -> 0 | I10: =IF(H10=0,"PASS","REVIEW") -> PASS | J10: Model-calculated pre-provision, pre-tax earnings.
A13: Business Segment Reconciliation to Consolidated Results
A14: Period | B14: Segment Revenue Total | C14: Consolidated Revenue | D14: Revenue Difference | E14: Segment Net Income Total | F14: Consolidated Net Income | G14: Net Income Difference | H14: Revenue Status | I14: Income Status | J14: Note
A15: FY2023 | B15: =SUMIFS('10_Raw_Segment_Results'!$C$5:$C$34,'10_Raw_Segment_Results'!$A$5:$A$34,A15) -> 51464 | C15: ='05_Raw_Annual_Performance'!C7 -> 51464 | D15: =B15-C15 -> 0 | E15: =SUMIFS('10_Raw_Segment_Results'!$H$5:$H$34,'10_Raw_Segment_Results'!$A$5:$A$34,A15) -> 14612 | F15: ='05_Raw_Annual_Performance'!C12 -> 14612 | G15: =E15-F15 -> 0 | H15: =IF(D15=0,"PASS","REVIEW") -> PASS | I15: =IF(G15=0,"PASS","REVIEW") -> PASS | J15: Segment schedules should reconcile exactly, including Corporate Support.
A16: FY2024 | B16: =SUMIFS('10_Raw_Segment_Results'!$C$5:$C$34,'10_Raw_Segment_Results'!$A$5:$A$34,A16) -> 57344 | C16: ='05_Raw_Annual_Performance'!D7 -> 57344 | D16: =B16-C16 -> 0 | E16: =SUMIFS('10_Raw_Segment_Results'!$H$5:$H$34,'10_Raw_Segment_Results'!$A$5:$A$34,A16) -> 16240 | F16: ='05_Raw_Annual_Performance'!D12 -> 16240 | G16: =E16-F16 -> 0 | H16: =IF(D16=0,"PASS","REVIEW") -> PASS | I16: =IF(G16=0,"PASS","REVIEW") -> PASS | J16: Segment schedules should reconcile exactly, including Corporate Support.
A17: FY2025 | B17: =SUMIFS('10_Raw_Segment_Results'!$C$5:$C$34,'10_Raw_Segment_Results'!$A$5:$A$34,A17) -> 66605 | C17: ='05_Raw_Annual_Performance'!E7 -> 66605 | D17: =B17-C17 -> 0 | E17: =SUMIFS('10_Raw_Segment_Results'!$H$5:$H$34,'10_Raw_Segment_Results'!$A$5:$A$34,A17) -> 20369 | F17: ='05_Raw_Annual_Performance'!E12 -> 20369 | G17: =E17-F17 -> 0 | H17: =IF(D17=0,"PASS","REVIEW") -> PASS | I17: =IF(G17=0,"PASS","REVIEW") -> PASS | J17: Segment schedules should reconcile exactly, including Corporate Support.
A18: Q1 2026 | B18: =SUMIFS('10_Raw_Segment_Results'!$C$5:$C$34,'10_Raw_Segment_Results'!$A$5:$A$34,A18) -> 17960 | C18: ='06_Raw_Quarterly_Performance'!K7 -> 17960 | D18: =B18-C18 -> 0 | E18: =SUMIFS('10_Raw_Segment_Results'!$H$5:$H$34,'10_Raw_Segment_Results'!$A$5:$A$34,A18) -> 5785 | F18: ='06_Raw_Quarterly_Performance'!K12 -> 5785 | G18: =E18-F18 -> 0 | H18: =IF(D18=0,"PASS","REVIEW") -> PASS | I18: =IF(G18=0,"PASS","REVIEW") -> PASS | J18: Segment schedules should reconcile exactly, including Corporate Support.
A19: Q2 2026 | B19: =SUMIFS('10_Raw_Segment_Results'!$C$5:$C$34,'10_Raw_Segment_Results'!$A$5:$A$34,A19) -> 17453 | C19: ='06_Raw_Quarterly_Performance'!L7 -> 17453 | D19: =B19-C19 -> 0 | E19: =SUMIFS('10_Raw_Segment_Results'!$H$5:$H$34,'10_Raw_Segment_Results'!$A$5:$A$34,A19) -> 5509 | F19: ='06_Raw_Quarterly_Performance'!L12 -> 5509 | G19: =E19-F19 -> 0 | H19: =IF(D19=0,"PASS","REVIEW") -> PASS | I19: =IF(G19=0,"PASS","REVIEW") -> PASS | J19: Segment schedules should reconcile exactly, including Corporate Support.
A22: Balance Sheet, Credit and Capital Validation
A23: Check | B23: FY2023 | C23: FY2024 | D23: FY2025 | E23: Q1 2026 | F23: Q2 2026 | G23: Expected / Threshold | H23: Maximum Difference | I23: Status | J23: Explanation
A24: Gross Loans - Allowance = Net Loans | B24: ='07_Raw_Balance_Sheet'!C9+'07_Raw_Balance_Sheet'!C10-'07_Raw_Balance_Sheet'!C11 -> 0 | C24: ='07_Raw_Balance_Sheet'!D9+'07_Raw_Balance_Sheet'!D10-'07_Raw_Balance_Sheet'!D11 -> 0 | D24: ='07_Raw_Balance_Sheet'!E9+'07_Raw_Balance_Sheet'!E10-'07_Raw_Balance_Sheet'!E11 -> 0 | E24: ='07_Raw_Balance_Sheet'!F9+'07_Raw_Balance_Sheet'!F10-'07_Raw_Balance_Sheet'!F11 -> 0 | F24: ='07_Raw_Balance_Sheet'!G9+'07_Raw_Balance_Sheet'!G10-'07_Raw_Balance_Sheet'!G11 -> 0 | G24: 0 | H24: =MAX(ABS(B24),ABS(C24),ABS(D24),ABS(E24),ABS(F24)) -> 0 | I24: =IF(H24=0,"PASS","REVIEW") -> PASS | J24: Checks whether gross loans less allowance equal reported net loans.
A25: CET1 Capital / RWA versus Reported CET1 | B25: ='09_Raw_Capital_Liquidity'!C5/'09_Raw_Capital_Liquidity'!C8-'09_Raw_Capital_Liquidity'!C9 -> 0.00026611687 | C25: ='09_Raw_Capital_Liquidity'!D5/'09_Raw_Capital_Liquidity'!D8-'09_Raw_Capital_Liquidity'!D9 -> 0.00028972366 | D25: ='09_Raw_Capital_Liquidity'!E5/'09_Raw_Capital_Liquidity'!E8-'09_Raw_Capital_Liquidity'!E9 -> 0.00022955254 | E25: ='09_Raw_Capital_Liquidity'!F5/'09_Raw_Capital_Liquidity'!F8-'09_Raw_Capital_Liquidity'!F9 -> -0.00032386453 | F25: ='09_Raw_Capital_Liquidity'!G5/'09_Raw_Capital_Liquidity'!G8-'09_Raw_Capital_Liquidity'!G9 -> 0.00033843626 | G25: 0.0005 | H25: =MAX(ABS(B25),ABS(C25),ABS(D25),ABS(E25),ABS(F25)) -> 0.00033843626 | I25: =IF(H25<=G25,"PASS","REVIEW") -> PASS | J25: Small rounding differences are expected; reported regulatory ratios remain authoritative.
A26: Total Capital / RWA versus Reported Total Capital Ratio | B26: ='09_Raw_Capital_Liquidity'!C7/'09_Raw_Capital_Liquidity'!C8-'09_Raw_Capital_Liquidity'!C11 -> 2.809687e-05 | C26: ='09_Raw_Capital_Liquidity'!D7/'09_Raw_Capital_Liquidity'!D8-'09_Raw_Capital_Liquidity'!D11 -> 0.00034621186 | D26: ='09_Raw_Capital_Liquidity'!E7/'09_Raw_Capital_Liquidity'!E8-'09_Raw_Capital_Liquidity'!E11 -> -0.00038180013 | E26: ='09_Raw_Capital_Liquidity'!F7/'09_Raw_Capital_Liquidity'!F8-'09_Raw_Capital_Liquidity'!F11 -> 0.00041320116 | F26: ='09_Raw_Capital_Liquidity'!G7/'09_Raw_Capital_Liquidity'!G8-'09_Raw_Capital_Liquidity'!G11 -> -0.00030151351 | G26: 0.0005 | H26: =MAX(ABS(B26),ABS(C26),ABS(D26),ABS(E26),ABS(F26)) -> 0.00041320116 | I26: =IF(H26<=G26,"PASS","REVIEW") -> PASS | J26: Tests capital ratio consistency against reported amounts and RWA.
A27: Liquidity Ratios Meet 100% Minimum | B27: =IF('09_Raw_Capital_Liquidity'!C13="",0,MIN('09_Raw_Capital_Liquidity'!C13,'09_Raw_Capital_Liquidity'!C14)-1) -> 0 | C27: =MIN('09_Raw_Capital_Liquidity'!D13,'09_Raw_Capital_Liquidity'!D14)-1 -> 0.14 | D27: =MIN('09_Raw_Capital_Liquidity'!E13,'09_Raw_Capital_Liquidity'!E14)-1 -> 0.12 | E27: =MIN('09_Raw_Capital_Liquidity'!F13,'09_Raw_Capital_Liquidity'!F14)-1 -> 0.11 | F27: =MIN('09_Raw_Capital_Liquidity'!G13,'09_Raw_Capital_Liquidity'!G14)-1 -> 0.11 | G27: 0 | H27: =MIN(C27:F27) -> 0.11 | I27: =IF(H27>=G27,"PASS","REVIEW") -> PASS | J27: A non-negative value means both LCR and NSFR meet the 100% minimum. FY2023 is not tested.
A31: Correction Log from Source Audit
A32: Area | B32: Original Issue | C32: Corrected Value / Treatment | D32: Primary Source | E32: Impact | F32: Verified | G32: Reviewer Note
A33: Advanced formulas | B33: Newer dynamic-array and lookup functions were not evaluated correctly after export | C33: Replaced with INDEX/MATCH, SUMIFS, IFERROR, RANK, COUNTIF and CHOOSE | D33: Excel compatibility review | E33: Removed visible formula errors | F33: Yes | G33: The advanced outcomes remain interactive and auditable.
A34: Dashboard | B34: Amounts and percentages were plotted on the same axis | C34: Separated amount charts from ratio charts | D34: Model presentation review | E34: Ratios are now readable | F34: Yes | G34: All chart series now share compatible units.
A35: Segment results | B35: Several FY2025 and Insurance/Corporate Support figures were mapped incorrectly | C35: All 30 segment-period rows replaced with exact RBC supplement values | D35: RBC Financial Supplements Pages 8–14 | E35: Corrected segment analysis and charts | F35: Yes | G35: Segment revenue and net income now reconcile exactly.
A36: Credit risk | B36: FY2023 net write-off ratio entered as 0.17% | C36: Corrected to 0.14% | D36: RBC 2025 Annual Report Table 75 | E36: Corrected historical credit trend | F36: Yes | G36: Annual reported ratio used.
A37: Capital | B37: FY2023 RWA entered as 596,200 | C37: Corrected to 596,223 | D37: RBC Q4 2024 Financial Supplement Page 20 | E37: Improved ratio reconciliation | F37: Yes | G37: Reported amount used.
A38: Liquidity | B38: Historical LCR/NSFR values were incomplete | C38: Added FY2024 128%/114%, FY2025 127%/112%, Q1 2026 124%/111%, Q2 2026 126%/111% | D38: RBC 2025 Annual Report and Q2 2026 Report | E38: Completed liquidity analysis | F38: Yes | G38: FY2023 remains blank because it was not collected in this source set.
A39: Dividends | B39: Q2 2026 dividend per share entered as $1.76 | C39: Corrected to $1.64 | D39: RBC Q2 2026 Financial Supplement Page 3 | E39: Corrected shareholder-return schedule | F39: Yes | G39: $1.76 was announced later and is not the Q2 2026 declared dividend.

Sheet 26_Native_PivotTable
A1: RBC Segment Net Income PivotTable
D3: Interactive analysis by business segment and reporting period | CAD millions
A6: Analysis Type | B6: Segment
A7: Metric | B7: Net Income
A9: Sum of Value | B9: Period
A10: Segment | B10: FY2023 | C10: FY2024 | D10: FY2025 | E10: Q1 2026 | F10: Q2 2026
A11: Capital Markets | B11: 4139 | C11: 4573 | D11: 5393 | E11: 1478 | F11: 1484
A12: Commercial Banking | B12: 2582 | C12: 2818 | D12: 3020 | E12: 863 | F12: 854
A13: Corporate Support | B13: -769 | C13: -1223 | D13: -266 | E13: -26 | F13: -102
A14: Insurance | B14: 549 | C14: 729 | D14: 828 | E14: 213 | F14: 218
A15: Personal Banking | B15: 5418 | C15: 5921 | D15: 7105 | E15: 1962 | F15: 1870
A16: Wealth Management | B16: 2693 | C16: 3422 | D16: 4289 | E16: 1295 | F16: 1185
